Workbook

Sheet PANEL MENSUAL
A2: MES A EVALUAR | B2: OCTUBRE | D2: AÑO | E2: ='ESTADO CONTABLE'!B2 -> 2026
A4: MENSUALIDADES ESPERADAS | B4: =COUNTIF(F15:F150,"COBRADA")+COUNTIF(F15:F150,"ABONO")+COUNTIF(F15:F150,"PENDIENTE") -> 78 | C4: MENSUALIDADES COBRADAS | D4: =COUNTIF(F15:F150,"COBRADA") -> 70 | E4: MENSUALIDADES FALTANTES | F4: =COUNTIF(F15:F150,"PENDIENTE")+COUNTIF(F15:F150,"ABONO") -> 8
A7: INGRESO ESPERADO NETO (SIN IVA) | B7: =SUM(C15:C150) -> 58275.862 | C7: INGRESO REGISTRADO BRUTO | D7: {=_xlfn.XLOOKUP($B$2,'ESTADO CONTABLE'!$A$5:$A$16,'ESTADO CONTABLE'!$B$5:$B$16,0)} -> 66356 | E7: INGRESO NETO (IVA DIGITAL) | F7: {=_xlfn.XLOOKUP($B$2,'ESTADO CONTABLE'!$A$5:$A$16,'ESTADO CONTABLE'!$J$5:$J$16,0)} -> 61045.655
A9: EGRESOS DEL MES | B9: {=_xlfn.XLOOKUP($B$2,'ESTADO CONTABLE'!$A$5:$A$16,'ESTADO CONTABLE'!$K$5:$K$16,0)} -> 35596.97 | C9: UTILIDAD REAL | D9: {=_xlfn.XLOOKUP($B$2,'ESTADO CONTABLE'!$A$5:$A$16,'ESTADO CONTABLE'!$L$5:$L$16,0)} -> 25448.685 | E9: GASTOS FIJOS PRESUP. | F9: {=_xlfn.XLOOKUP($B$2,'ESTADO CONTABLE'!$A$5:$A$16,'ESTADO CONTABLE'!$M$5:$M$16,0)} -> 43926
A11: RESULTADO ACTUAL VS FIJOS | B11: {=_xlfn.XLOOKUP($B$2,'ESTADO CONTABLE'!$A$5:$A$16,'ESTADO CONTABLE'!$N$5:$N$16,0)} -> 17119.655 | E11: RESULTADO PRESUPUESTADO | F11: =B7-F9 -> 14349.862
A13: DETALLE DE MENSUALIDADES DEL MES SELECCIONADO
A14: ALUMNA | B14: GRUPO | C14: MENSUALIDAD ESPERADA NETA (BONIFICACIÓN E IVA) | D14: PAGO REGISTRADO | E14: MÉTODO | F14: ESTATUS | G14: COBRAR DESDE
A15: {=IFERROR(INDEX('BASE DE DATOSS'!A:A,ROW()-13),"")} -> AMEYALI MARTÍNEZ I. MORALES | B15: {=IF(A15="","",IFERROR(INDEX('BASE DE DATOSS'!C:C,ROW()-13),""))} -> KIDS 3 | C15: {=IF(A15="","",LET(mes,DATE($E$2,MATCH($B$2,'ESTADO CONTABLE'!$A$5:$A$16,0),1),cobrarDesde,IFERROR(INDEX('BASE DE DATOSS'!I:I,ROW()-13),""),pausada,SUMPRODUCT((UPPER(TRIM('PAUSAS MENSUALIDADES'!$A$5:$A$500))=UPPER(TRIM(A15)))*('PAUSAS MENSUALIDADES'!$B$5:$B$500=mes)*(UPPER(TRIM('PAUSAS MENSUALIDADES'!$D$5:$D$500))="APLICAR"))>0,IF(OR(AND(cobrarDesde<>"",mes<cobrarDesde),pausada),0,MAX(IFNA(VLOOKUP(B15,COSTOS!$A$3:$B$13,2,FALSE),0)-150,0)/1.16)))} -> 689.65517 | D15: {=IF(A15="","",LET(mes,DATE($E$2,MATCH($B$2,'ESTADO CONTABLE'!$A$5:$A$16,0),1),abonos,SUMIFS('ABONOS MENSUALIDADES'!$F$5:$F$500,'ABONOS MENSUALIDADES'!$C$5:$C$500,A15,'ABONOS MENSUALIDADES'!$D$5:$D$500,mes),pago,CHOOSE(MATCH($B$2,'ESTADO CONTABLE'!$A$5:$A$16,0),IFNA(_xlfn.XLOOKUP(A15,PAGOS!$A$2:$A$996,PAGOS!$E$2:$E$996,""),""),IFNA(_xlfn.XLOOKUP(A15,PAGOS!$A$2:$A$996,PAGOS!$G$2:$G$996,""),""),IFNA(_xlfn.XLOOKUP(A15,PAGOS!$A$2:$A$996,PAGOS!$J$2:$J$996,""),""),IFNA(_xlfn.XLOOKUP(A15,PAGOS!$A$2:$A$996,PAGOS!$M$2:$M$996,""),""),IFNA(_xlfn.XLOOKUP(A15,PAGOS!$A$2:$A$996,PAGOS!$P$2:$P$996,""),""),IFNA(_xlfn.XLOOKUP(A15,PAGOS!$A$2:$A$996,PAGOS!$S$2:$S$996,""),""),IFNA(_xlfn.XLOOKUP(A15,PAGOS!$A$2:$A$996,PAGOS!$V$2:$V$996,""),""),IFNA(_xlfn.XLOOKUP(A15,PAGOS!$A$2:$A$996,PAGOS!$Y$2:$Y$996,""),""),IFNA(_xlfn.XLOOKUP(A15,PAGOS!$A$2:$A$996,PAGOS!$AB$2:$AB$996,""),""),IFNA(_xlfn.XLOOKUP(A15,PAGOS!$A$2:$A$996,PAGOS!$AE$2:$AE$996,""),""),IFNA(_xlfn.XLOOKUP(A15,PAGOS!$A$2:$A$996,PAGOS!$AH$2:$AH$996,""),""),IFNA(_xlfn.XLOOKUP(A15,PAGOS!$A$2:$A$996,PAGOS!$AK$2:$AK$996,""),"")),IF(abonos>0,abonos,pago)))} -> 400 | E15: =IFERROR(__xludf.DUMMYFUNCTION("IF(A15="""","""",LET(mes,DATE($E$2,MATCH($B$2,'ESTADO CONTABLE'!$A$5:$A$16,0),1),abonos,SUMIFS('ABONOS MENSUALIDADES'!$F$5:$F$500,'ABONOS MENSUALIDADES'!$C$5:$C$500,A15,'ABONOS MENSUALIDADES'!$D$5:$D$500,mes),metodoDirecto,CHOOSE(MATCH($B$2,'ESTADO CONTAB"&"LE'!$A$5:$A$16,0),IF(ISNUMBER(D15),""POR CLASIFICAR"",""""),IFNA(XLOOKUP(A15,PAGOS!$A$2:$A$996,PAGOS!$H$2:$H$996,""""),""""),IFNA(XLOOKUP(A15,PAGOS!$A$2:$A$996,PAGOS!$K$2:$K$996,""""),""""),IFNA(XLOOKUP(A15,PAGOS!$A$2:$A$996,PAGOS!$N$2:$N$996,""""),""""),"&"IFNA(XLOOKUP(A15,PAGOS!$A$2:$A$996,PAGOS!$Q$2:$Q$996,""""),""""),IFNA(XLOOKUP(A15,PAGOS!$A$2:$A$996,PAGOS!$T$2:$T$996,""""),""""),IFNA(XLOOKUP(A15,PAGOS!$A$2:$A$996,PAGOS!$W$2:$W$996,""""),""""),IFNA(XLOOKUP(A15,PAGOS!$A$2:$A$996,PAGOS!$Z$2:$Z$996,""""),"&"""""),IFNA(XLOOKUP(A15,PAGOS!$A$2:$A$996,PAGOS!$AC$2:$AC$996,""""),""""),IFNA(XLOOKUP(A15,PAGOS!$A$2:$A$996,PAGOS!$AF$2:$AF$996,""""),""""),IFNA(XLOOKUP(A15,PAGOS!$A$2:$A$996,PAGOS!$AI$2:$AI$996,""""),""""),IFNA(XLOOKUP(A15,PAGOS!$A$2:$A$996,PAGOS!$AL$2:$"&"AL$996,""""),"""")),IF(abonos>0,IFERROR(TEXTJOIN("" + "",TRUE,UNIQUE(FILTER('ABONOS MENSUALIDADES'!$E$5:$E$500,'ABONOS MENSUALIDADES'!$C$5:$C$500=A15,'ABONOS MENSUALIDADES'!$D$5:$D$500=mes))),""""),metodoDirecto)))"),"TRANSFERENCIA") -> TRANSFERENCIA | F15: {=IF(A15="","",LET(mes,DATE($E$2,MATCH($B$2,'ESTADO CONTABLE'!$A$5:$A$16,0),1),cobrarDesde,IFERROR(INDEX('BASE DE DATOSS'!I:I,ROW()-13),""),pausada,SUMPRODUCT((UPPER(TRIM('PAUSAS MENSUALIDADES'!$A$5:$A$500))=UPPER(TRIM(A15)))*('PAUSAS MENSUALIDADES'!$B$5:$B$500=mes)*(UPPER(TRIM('PAUSAS MENSUALIDADES'!$D$5:$D$500))="APLICAR"))>0,abonoActivo,SUMIFS('ABONOS MENSUALIDADES'!$F$5:$F$500,'ABONOS MENSUALIDADES'!$C$5:$C$500,A15,'ABONOS MENSUALIDADES'!$D$5:$D$500,mes,'ABONOS MENSUALIDADES'!$G$5:$G$500,"<>*CONSOLIDADO EN PAGOS*")>0,esperadaBruta,MAX(IFNA(VLOOKUP(B15,COSTOS!$A$3:$B$13,2,FALSE),0)-150,0),IF(AND(cobrarDesde<>"",mes<cobrarDesde),"AÚN NO INICIA",IF(pausada,"PAUSADA",IF(AND(abonoActivo,COUNTIFS('ABONOS MENSUALIDADES'!$C$5:$C$500,A15,'ABONOS MENSUALIDADES'!$D$5:$D$500,mes,'ABONOS MENSUALIDADES'!$G$5:$G$500,"*MENSUALIDAD LIQUIDADA*")=0),"ABONO",IF(N(D15)>=esperadaBruta,"COBRADA",IF(N(D15)>0,"ABONO","PENDIENTE")))))))} -> ABONO | G15: {=IF(A15="","",IFERROR(INDEX('BASE DE DATOSS'!I:I,ROW()-13),""))} -> 46023
A16: {=IFERROR(INDEX('BASE DE DATOSS'!A:A,ROW()-13),"")} -> ANA PAULA GUTIERREZ MENESES | B16: {=IF(A16="","",IFERROR(INDEX('BASE DE DATOSS'!C:C,ROW()-13),""))} -> KIDS 3 | C16: {=IF(A16="","",LET(mes,DATE($E$2,MATCH($B$2,'ESTADO CONTABLE'!$A$5:$A$16,0),1),cobrarDesde,IFERROR(INDEX('BASE DE DATOSS'!I:I,ROW()-13),""),pausada,SUMPRODUCT((UPPER(TRIM('PAUSAS MENSUALIDADES'!$A$5:$A$500))=UPPER(TRIM(A16)))*('PAUSAS MENSUALIDADES'!$B$5:$B$500=mes)*(UPPER(TRIM('PAUSAS MENSUALIDADES'!$D$5:$D$500))="APLICAR"))>0,IF(OR(AND(cobrarDesde<>"",mes<cobrarDesde),pausada),0,MAX(IFNA(VLOOKUP(B16,COSTOS!$A$3:$B$13,2,FALSE),0)-150,0)/1.16)))} -> 689.65517 | D16: {=IF(A16="","",LET(mes,DATE($E$2,MATCH($B$2,'ESTADO CONTABLE'!$A$5:$A$16,0),1),abonos,SUMIFS('ABONOS MENSUALIDADES'!$F$5:$F$500,'ABONOS MENSUALIDADES'!$C$5:$C$500,A16,'ABONOS MENSUALIDADES'!$D$5:$D$500,mes),pago,CHOOSE(MATCH($B$2,'ESTADO CONTABLE'!$A$5:$A$16,0),IFNA(_xlfn.XLOOKUP(A16,PAGOS!$A$2:$A$996,PAGOS!$E$2:$E$996,""),""),IFNA(_xlfn.XLOOKUP(A16,PAGOS!$A$2:$A$996,PAGOS!$G$2:$G$996,""),""),IFNA(_xlfn.XLOOKUP(A16,PAGOS!$A$2:$A$996,PAGOS!$J$2:$J$996,""),""),IFNA(_xlfn.XLOOKUP(A16,PAGOS!$A$2:$A$996,PAGOS!$M$2:$M$996,""),""),IFNA(_xlfn.XLOOKUP(A16,PAGOS!$A$2:$A$996,PAGOS!$P$2:$P$996,""),""),IFNA(_xlfn.XLOOKUP(A16,PAGOS!$A$2:$A$996,PAGOS!$S$2:$S$996,""),""),IFNA(_xlfn.XLOOKUP(A16,PAGOS!$A$2:$A$996,PAGOS!$V$2:$V$996,""),""),IFNA(_xlfn.XLOOKUP(A16,PAGOS!$A$2:$A$996,PAGOS!$Y$2:$Y$996,""),""),IFNA(_xlfn.XLOOKUP(A16,PAGOS!$A$2:$A$996,PAGOS!$AB$2:$AB$996,""),""),IFNA(_xlfn.XLOOKUP(A16,PAGOS!$A$2:$A$996,PAGOS!$AE$2:$AE$996,""),""),IFNA(_xlfn.XLOOKUP(A16,PAGOS!$A$2:$A$996,PAGOS!$AH$2:$AH$996,""),""),IFNA(_xlfn.XLOOKUP(A16,PAGOS!$A$2:$A$996,PAGOS!$AK$2:$AK$996,""),"")),IF(abonos>0,abonos,pago)))} -> 800 | E16: =IFERROR(__xludf.DUMMYFUNCTION("IF(A16="""","""",LET(mes,DATE($E$2,MATCH($B$2,'ESTADO CONTABLE'!$A$5:$A$16,0),1),abonos,SUMIFS('ABONOS MENSUALIDADES'!$F$5:$F$500,'ABONOS MENSUALIDADES'!$C$5:$C$500,A16,'ABONOS MENSUALIDADES'!$D$5:$D$500,mes),metodoDirecto,CHOOSE(MATCH($B$2,'ESTADO CONTAB"&"LE'!$A$5:$A$16,0),IF(ISNUMBER(D16),""POR CLASIFICAR"",""""),IFNA(XLOOKUP(A16,PAGOS!$A$2:$A$996,PAGOS!$H$2:$H$996,""""),""""),IFNA(XLOOKUP(A16,PAGOS!$A$2:$A$996,PAGOS!$K$2:$K$996,""""),""""),IFNA(XLOOKUP(A16,PAGOS!$A$2:$A$996,PAGOS!$N$2:$N$996,""""),""""),"&"IFNA(XLOOKUP(A16,PAGOS!$A$2:$A$996,PAGOS!$Q$2:$Q$996,""""),""""),IFNA(XLOOKUP(A16,PAGOS!$A$2:$A$996,PAGOS!$T$2:$T$996,""""),""""),IFNA(XLOOKUP(A16,PAGOS!$A$2:$A$996,PAGOS!$W$2:$W$996,""""),""""),IFNA(XLOOKUP(A16,PAGOS!$A$2:$A$996,PAGOS!$Z$2:$Z$996,""""),"&"""""),IFNA(XLOOKUP(A16,PAGOS!$A$2:$A$996,PAGOS!$AC$2:$AC$996,""""),""""),IFNA(XLOOKUP(A16,PAGOS!$A$2:$A$996,PAGOS!$AF$2:$AF$996,""""),""""),IFNA(XLOOKUP(A16,PAGOS!$A$2:$A$996,PAGOS!$AI$2:$AI$996,""""),""""),IFNA(XLOOKUP(A16,PAGOS!$A$2:$A$996,PAGOS!$AL$2:$"&"AL$996,""""),"""")),IF(abonos>0,IFERROR(TEXTJOIN("" + "",TRUE,UNIQUE(FILTER('ABONOS MENSUALIDADES'!$E$5:$E$500,'ABONOS MENSUALIDADES'!$C$5:$C$500=A16,'ABONOS MENSUALIDADES'!$D$5:$D$500=mes))),""""),metodoDirecto)))"),"TRANSFERENCIA") -> TRANSFERENCIA | F16: {=IF(A16="","",LET(mes,DATE($E$2,MATCH($B$2,'ESTADO CONTABLE'!$A$5:$A$16,0),1),cobrarDesde,IFERROR(INDEX('BASE DE DATOSS'!I:I,ROW()-13),""),pausada,SUMPRODUCT((UPPER(TRIM('PAUSAS MENSUALIDADES'!$A$5:$A$500))=UPPER(TRIM(A16)))*('PAUSAS MENSUALIDADES'!$B$5:$B$500=mes)*(UPPER(TRIM('PAUSAS MENSUALIDADES'!$D$5:$D$500))="APLICAR"))>0,abonoActivo,SUMIFS('ABONOS MENSUALIDADES'!$F$5:$F$500,'ABONOS MENSUALIDADES'!$C$5:$C$500,A16,'ABONOS MENSUALIDADES'!$D$5:$D$500,mes,'ABONOS MENSUALIDADES'!$G$5:$G$500,"<>*CONSOLIDADO EN PAGOS*")>0,esperadaBruta,MAX(IFNA(VLOOKUP(B16,COSTOS!$A$3:$B$13,2,FALSE),0)-150,0),IF(AND(cobrarDesde<>"",mes<cobrarDesde),"AÚN NO INICIA",IF(pausada,"PAUSADA",IF(AND(abonoActivo,COUNTIFS('ABONOS MENSUALIDADES'!$C$5:$C$500,A16,'ABONOS MENSUALIDADES'!$D$5:$D$500,mes,'ABONOS MENSUALIDADES'!$G$5:$G$500,"*MENSUALIDAD LIQUIDADA*")=0),"ABONO",IF(N(D16)>=esperadaBruta,"COBRADA",IF(N(D16)>0,"ABONO","PENDIENTE")))))))} -> COBRADA | G16: {=IF(A16="","",IFERROR(INDEX('BASE DE DATOSS'!I:I,ROW()-13),""))} -> 46023
A17: {=IFERROR(INDEX('BASE DE DATOSS'!A:A,ROW()-13),"")} -> ANA VICTORIA REVUELTA LARA | B17: {=IF(A17="","",IFERROR(INDEX('BASE DE DATOSS'!C:C,ROW()-13),""))} -> JR 2 | C17: {=IF(A17="","",LET(mes,DATE($E$2,MATCH($B$2,'ESTADO CONTABLE'!$A$5:$A$16,0),1),cobrarDesde,IFERROR(INDEX('BASE DE DATOSS'!I:I,ROW()-13),""),pausada,SUMPRODUCT((UPPER(TRIM('PAUSAS MENSUALIDADES'!$A$5:$A$500))=UPPER(TRIM(A17)))*('PAUSAS MENSUALIDADES'!$B$5:$B$500=mes)*(UPPER(TRIM('PAUSAS MENSUALIDADES'!$D$5:$D$500))="APLICAR"))>0,IF(OR(AND(cobrarDesde<>"",mes<cobrarDesde),pausada),0,MAX(IFNA(VLOOKUP(B17,COSTOS!$A$3:$B$13,2,FALSE),0)-150,0)/1.16)))} -> 689.65517 | D17: {=IF(A17="","",LET(mes,DATE($E$2,MATCH($B$2,'ESTADO CONTABLE'!$A$5:$A$16,0),1),abonos,SUMIFS('ABONOS MENSUALIDADES'!$F$5:$F$500,'ABONOS MENSUALIDADES'!$C$5:$C$500,A17,'ABONOS MENSUALIDADES'!$D$5:$D$500,mes),pago,CHOOSE(MATCH($B$2,'ESTADO CONTABLE'!$A$5:$A$16,0),IFNA(_xlfn.XLOOKUP(A17,PAGOS!$A$2:$A$996,PAGOS!$E$2:$E$996,""),""),IFNA(_xlfn.XLOOKUP(A17,PAGOS!$A$2:$A$996,PAGOS!$G$2:$G$996,""),""),IFNA(_xlfn.XLOOKUP(A17,PAGOS!$A$2:$A$996,PAGOS!$J$2:$J$996,""),""),IFNA(_xlfn.XLOOKUP(A17,PAGOS!$A$2:$A$996,PAGOS!$M$2:$M$996,""),""),IFNA(_xlfn.XLOOKUP(A17,PAGOS!$A$2:$A$996,PAGOS!$P$2:$P$996,""),""),IFNA(_xlfn.XLOOKUP(A17,PAGOS!$A$2:$A$996,PAGOS!$S$2:$S$996,""),""),IFNA(_xlfn.XLOOKUP(A17,PAGOS!$A$2:$A$996,PAGOS!$V$2:$V$996,""),""),IFNA(_xlfn.XLOOKUP(A17,PAGOS!$A$2:$A$996,PAGOS!$Y$2:$Y$996,""),""),IFNA(_xlfn.XLOOKUP(A17,PAGOS!$A$2:$A$996,PAGOS!$AB$2:$AB$996,""),""),IFNA(_xlfn.XLOOKUP(A17,PAGOS!$A$2:$A$996,PAGOS!$AE$2:$AE$996,""),""),IFNA(_xlfn.XLOOKUP(A17,PAGOS!$A$2:$A$996,PAGOS!$AH$2:$AH$996,""),""),IFNA(_xlfn.XLOOKUP(A17,PAGOS!$A$2:$A$996,PAGOS!$AK$2:$AK$996,""),"")),IF(abonos>0,abonos,pago)))} -> 950 | E17: =IFERROR(__xludf.DUMMYFUNCTION("IF(A17="""","""",LET(mes,DATE($E$2,MATCH($B$2,'ESTADO CONTABLE'!$A$5:$A$16,0),1),abonos,SUMIFS('ABONOS MENSUALIDADES'!$F$5:$F$500,'ABONOS MENSUALIDADES'!$C$5:$C$500,A17,'ABONOS MENSUALIDADES'!$D$5:$D$500,mes),metodoDirecto,CHOOSE(MATCH($B$2,'ESTADO CONTAB"&"LE'!$A$5:$A$16,0),IF(ISNUMBER(D17),""POR CLASIFICAR"",""""),IFNA(XLOOKUP(A17,PAGOS!$A$2:$A$996,PAGOS!$H$2:$H$996,""""),""""),IFNA(XLOOKUP(A17,PAGOS!$A$2:$A$996,PAGOS!$K$2:$K$996,""""),""""),IFNA(XLOOKUP(A17,PAGOS!$A$2:$A$996,PAGOS!$N$2:$N$996,""""),""""),"&"IFNA(XLOOKUP(A17,PAGOS!$A$2:$A$996,PAGOS!$Q$2:$Q$996,""""),""""),IFNA(XLOOKUP(A17,PAGOS!$A$2:$A$996,PAGOS!$T$2:$T$996,""""),""""),IFNA(XLOOKUP(A17,PAGOS!$A$2:$A$996,PAGOS!$W$2:$W$996,""""),""""),IFNA(XLOOKUP(A17,PAGOS!$A$2:$A$996,PAGOS!$Z$2:$Z$996,""""),"&"""""),IFNA(XLOOKUP(A17,PAGOS!$A$2:$A$996,PAGOS!$AC$2:$AC$996,""""),""""),IFNA(XLOOKUP(A17,PAGOS!$A$2:$A$996,PAGOS!$AF$2:$AF$996,""""),""""),IFNA(XLOOKUP(A17,PAGOS!$A$2:$A$996,PAGOS!$AI$2:$AI$996,""""),""""),IFNA(XLOOKUP(A17,PAGOS!$A$2:$A$996,PAGOS!$AL$2:$"&"AL$996,""""),"""")),IF(abonos>0,IFERROR(TEXTJOIN("" + "",TRUE,UNIQUE(FILTER('ABONOS MENSUALIDADES'!$E$5:$E$500,'ABONOS MENSUALIDADES'!$C$5:$C$500=A17,'ABONOS MENSUALIDADES'!$D$5:$D$500=mes))),""""),metodoDirecto)))"),"TRANSFERENCIA") -> TRANSFERENCIA | F17: {=IF(A17="","",LET(mes,DATE($E$2,MATCH($B$2,'ESTADO CONTABLE'!$A$5:$A$16,0),1),cobrarDesde,IFERROR(INDEX('BASE DE DATOSS'!I:I,ROW()-13),""),pausada,SUMPRODUCT((UPPER(TRIM('PAUSAS MENSUALIDADES'!$A$5:$A$500))=UPPER(TRIM(A17)))*('PAUSAS MENSUALIDADES'!$B$5:$B$500=mes)*(UPPER(TRIM('PAUSAS MENSUALIDADES'!$D$5:$D$500))="APLICAR"))>0,abonoActivo,SUMIFS('ABONOS MENSUALIDADES'!$F$5:$F$500,'ABONOS MENSUALIDADES'!$C$5:$C$500,A17,'ABONOS MENSUALIDADES'!$D$5:$D$500,mes,'ABONOS MENSUALIDADES'!$G$5:$G$500,"<>*CONSOLIDADO EN PAGOS*")>0,esperadaBruta,MAX(IFNA(VLOOKUP(B17,COSTOS!$A$3:$B$13,2,FALSE),0)-150,0),IF(AND(cobrarDesde<>"",mes<cobrarDesde),"AÚN NO INICIA",IF(pausada,"PAUSADA",IF(AND(abonoActivo,COUNTIFS('ABONOS MENSUALIDADES'!$C$5:$C$500,A17,'ABONOS MENSUALIDADES'!$D$5:$D$500,mes,'ABONOS MENSUALIDADES'!$G$5:$G$500,"*MENSUALIDAD LIQUIDADA*")=0),"ABONO",IF(N(D17)>=esperadaBruta,"COBRADA",IF(N(D17)>0,"ABONO","PENDIENTE")))))))} -> COBRADA | G17: {=IF(A17="","",IFERROR(INDEX('BASE DE DATOSS'!I:I,ROW()-13),""))} -> 46023
A18: {=IFERROR(INDEX('BASE DE DATOSS'!A:A,ROW()-13),"")} -> ATENAS KORHEIMI FIGEROA FIGUEROA | B18: {=IF(A18="","",IFERROR(INDEX('BASE DE DATOSS'!C:C,ROW()-13),""))} -> ADULTS 2 | C18: {=IF(A18="","",LET(mes,DATE($E$2,MATCH($B$2,'ESTADO CONTABLE'!$A$5:$A$16,0),1),cobrarDesde,IFERROR(INDEX('BASE DE DATOSS'!I:I,ROW()-13),""),pausada,SUMPRODUCT((UPPER(TRIM('PAUSAS MENSUALIDADES'!$A$5:$A$500))=UPPER(TRIM(A18)))*('PAUSAS MENSUALIDADES'!$B$5:$B$500=mes)*(UPPER(TRIM('PAUSAS MENSUALIDADES'!$D$5:$D$500))="APLICAR"))>0,IF(OR(AND(cobrarDesde<>"",mes<cobrarDesde),pausada),0,MAX(IFNA(VLOOKUP(B18,COSTOS!$A$3:$B$13,2,FALSE),0)-150,0)/1.16)))} -> 818.96552 | D18: {=IF(A18="","",LET(mes,DATE($E$2,MATCH($B$2,'ESTADO CONTABLE'!$A$5:$A$16,0),1),abonos,SUMIFS('ABONOS MENSUALIDADES'!$F$5:$F$500,'ABONOS MENSUALIDADES'!$C$5:$C$500,A18,'ABONOS MENSUALIDADES'!$D$5:$D$500,mes),pago,CHOOSE(MATCH($B$2,'ESTADO CONTABLE'!$A$5:$A$16,0),IFNA(_xlfn.XLOOKUP(A18,PAGOS!$A$2:$A$996,PAGOS!$E$2:$E$996,""),""),IFNA(_xlfn.XLOOKUP(A18,PAGOS!$A$2:$A$996,PAGOS!$G$2:$G$996,""),""),IFNA(_xlfn.XLOOKUP(A18,PAGOS!$A$2:$A$996,PAGOS!$J$2:$J$996,""),""),IFNA(_xlfn.XLOOKUP(A18,PAGOS!$A$2:$A$996,PAGOS!$M$2:$M$996,""),""),IFNA(_xlfn.XLOOKUP(A18,PAGOS!$A$2:$A$996,PAGOS!$P$2:$P$996,""),""),IFNA(_xlfn.XLOOKUP(A18,PAGOS!$A$2:$A$996,PAGOS!$S$2:$S$996,""),""),IFNA(_xlfn.XLOOKUP(A18,PAGOS!$A$2:$A$996,PAGOS!$V$2:$V$996,""),""),IFNA(_xlfn.XLOOKUP(A18,PAGOS!$A$2:$A$996,PAGOS!$Y$2:$Y$996,""),""),IFNA(_xlfn.XLOOKUP(A18,PAGOS!$A$2:$A$996,PAGOS!$AB$2:$AB$996,""),""),IFNA(_xlfn.XLOOKUP(A18,PAGOS!$A$2:$A$996,PAGOS!$AE$2:$AE$996,""),""),IFNA(_xlfn.XLOOKUP(A18,PAGOS!$A$2:$A$996,PAGOS!$AH$2:$AH$996,""),""),IFNA(_xlfn.XLOOKUP(A18,PAGOS!$A$2:$A$996,PAGOS!$AK$2:$AK$996,""),"")),IF(abonos>0,abonos,pago)))} -> 950 | E18: =IFERROR(__xludf.DUMMYFUNCTION("IF(A18="""","""",LET(mes,DATE($E$2,MATCH($B$2,'ESTADO CONTABLE'!$A$5:$A$16,0),1),abonos,SUMIFS('ABONOS MENSUALIDADES'!$F$5:$F$500,'ABONOS MENSUALIDADES'!$C$5:$C$500,A18,'ABONOS MENSUALIDADES'!$D$5:$D$500,mes),metodoDirecto,CHOOSE(MATCH($B$2,'ESTADO CONTAB"&"LE'!$A$5:$A$16,0),IF(ISNUMBER(D18),""POR CLASIFICAR"",""""),IFNA(XLOOKUP(A18,PAGOS!$A$2:$A$996,PAGOS!$H$2:$H$996,""""),""""),IFNA(XLOOKUP(A18,PAGOS!$A$2:$A$996,PAGOS!$K$2:$K$996,""""),""""),IFNA(XLOOKUP(A18,PAGOS!$A$2:$A$996,PAGOS!$N$2:$N$996,""""),""""),"&"IFNA(XLOOKUP(A18,PAGOS!$A$2:$A$996,PAGOS!$Q$2:$Q$996,""""),""""),IFNA(XLOOKUP(A18,PAGOS!$A$2:$A$996,PAGOS!$T$2:$T$996,""""),""""),IFNA(XLOOKUP(A18,PAGOS!$A$2:$A$996,PAGOS!$W$2:$W$996,""""),""""),IFNA(XLOOKUP(A18,PAGOS!$A$2:$A$996,PAGOS!$Z$2:$Z$996,""""),"&"""""),IFNA(XLOOKUP(A18,PAGOS!$A$2:$A$996,PAGOS!$AC$2:$AC$996,""""),""""),IFNA(XLOOKUP(A18,PAGOS!$A$2:$A$996,PAGOS!$AF$2:$AF$996,""""),""""),IFNA(XLOOKUP(A18,PAGOS!$A$2:$A$996,PAGOS!$AI$2:$AI$996,""""),""""),IFNA(XLOOKUP(A18,PAGOS!$A$2:$A$996,PAGOS!$AL$2:$"&"AL$996,""""),"""")),IF(abonos>0,IFERROR(TEXTJOIN("" + "",TRUE,UNIQUE(FILTER('ABONOS MENSUALIDADES'!$E$5:$E$500,'ABONOS MENSUALIDADES'!$C$5:$C$500=A18,'ABONOS MENSUALIDADES'!$D$5:$D$500=mes))),""""),metodoDirecto)))"),"EFECTIVO") -> EFECTIVO | F18: {=IF(A18="","",LET(mes,DATE($E$2,MATCH($B$2,'ESTADO CONTABLE'!$A$5:$A$16,0),1),cobrarDesde,IFERROR(INDEX('BASE DE DATOSS'!I:I,ROW()-13),""),pausada,SUMPRODUCT((UPPER(TRIM('PAUSAS MENSUALIDADES'!$A$5:$A$500))=UPPER(TRIM(A18)))*('PAUSAS MENSUALIDADES'!$B$5:$B$500=mes)*(UPPER(TRIM('PAUSAS MENSUALIDADES'!$D$5:$D$500))="APLICAR"))>0,abonoActivo,SUMIFS('ABONOS MENSUALIDADES'!$F$5:$F$500,'ABONOS MENSUALIDADES'!$C$5:$C$500,A18,'ABONOS MENSUALIDADES'!$D$5:$D$500,mes,'ABONOS MENSUALIDADES'!$G$5:$G$500,"<>*CONSOLIDADO EN PAGOS*")>0,esperadaBruta,MAX(IFNA(VLOOKUP(B18,COSTOS!$A$3:$B$13,2,FALSE),0)-150,0),IF(AND(cobrarDesde<>"",mes<cobrarDesde),"AÚN NO INICIA",IF(pausada,"PAUSADA",IF(AND(abonoActivo,COUNTIFS('ABONOS MENSUALIDADES'!$C$5:$C$500,A18,'ABONOS MENSUALIDADES'!$D$5:$D$500,mes,'ABONOS MENSUALIDADES'!$G$5:$G$500,"*MENSUALIDAD LIQUIDADA*")=0),"ABONO",IF(N(D18)>=esperadaBruta,"COBRADA",IF(N(D18)>0,"ABONO","PENDIENTE")))))))} -> COBRADA | G18: {=IF(A18="","",IFERROR(INDEX('BASE DE DATOSS'!I:I,ROW()-13),""))} -> 46023
A19: {=IFERROR(INDEX('BASE DE DATOSS'!A:A,ROW()-13),"")} -> CARLA VALENTINA GUZMÁN DELGADO | B19: {=IF(A19="","",IFERROR(INDEX('BASE DE DATOSS'!C:C,ROW()-13),""))} -> 5 DIAS KIDS | C19: {=IF(A19="","",LET(mes,DATE($E$2,MATCH($B$2,'ESTADO CONTABLE'!$A$5:$A$16,0),1),cobrarDesde,IFERROR(INDEX('BASE DE DATOSS'!I:I,ROW()-13),""),pausada,SUMPRODUCT((UPPER(TRIM('PAUSAS MENSUALIDADES'!$A$5:$A$500))=UPPER(TRIM(A19)))*('PAUSAS MENSUALIDADES'!$B$5:$B$500=mes)*(UPPER(TRIM('PAUSAS MENSUALIDADES'!$D$5:$D$500))="APLICAR"))>0,IF(OR(AND(cobrarDesde<>"",mes<cobrarDesde),pausada),0,MAX(IFNA(VLOOKUP(B19,COSTOS!$A$3:$B$13,2,FALSE),0)-150,0)/1.16)))} -> 1120.6897 | D19: {=IF(A19="","",LET(mes,DATE($E$2,MATCH($B$2,'ESTADO CONTABLE'!$A$5:$A$16,0),1),abonos,SUMIFS('ABONOS MENSUALIDADES'!$F$5:$F$500,'ABONOS MENSUALIDADES'!$C$5:$C$500,A19,'ABONOS MENSUALIDADES'!$D$5:$D$500,mes),pago,CHOOSE(MATCH($B$2,'ESTADO CONTABLE'!$A$5:$A$16,0),IFNA(_xlfn.XLOOKUP(A19,PAGOS!$A$2:$A$996,PAGOS!$E$2:$E$996,""),""),IFNA(_xlfn.XLOOKUP(A19,PAGOS!$A$2:$A$996,PAGOS!$G$2:$G$996,""),""),IFNA(_xlfn.XLOOKUP(A19,PAGOS!$A$2:$A$996,PAGOS!$J$2:$J$996,""),""),IFNA(_xlfn.XLOOKUP(A19,PAGOS!$A$2:$A$996,PAGOS!$M$2:$M$996,""),""),IFNA(_xlfn.XLOOKUP(A19,PAGOS!$A$2:$A$996,PAGOS!$P$2:$P$996,""),""),IFNA(_xlfn.XLOOKUP(A19,PAGOS!$A$2:$A$996,PAGOS!$S$2:$S$996,""),""),IFNA(_xlfn.XLOOKUP(A19,PAGOS!$A$2:$A$996,PAGOS!$V$2:$V$996,""),""),IFNA(_xlfn.XLOOKUP(A19,PAGOS!$A$2:$A$996,PAGOS!$Y$2:$Y$996,""),""),IFNA(_xlfn.XLOOKUP(A19,PAGOS!$A$2:$A$996,PAGOS!$AB$2:$AB$996,""),""),IFNA(_xlfn.XLOOKUP(A19,PAGOS!$A$2:$A$996,PAGOS!$AE$2:$AE$996,""),""),IFNA(_xlfn.XLOOKUP(A19,PAGOS!$A$2:$A$996,PAGOS!$AH$2:$AH$996,""),""),IFNA(_xlfn.XLOOKUP(A19,PAGOS!$A$2:$A$996,PAGOS!$AK$2:$AK$996,""),"")),IF(abonos>0,abonos,pago)))} -> 1300 | E19: =IFERROR(__xludf.DUMMYFUNCTION("IF(A19="""","""",LET(mes,DATE($E$2,MATCH($B$2,'ESTADO CONTABLE'!$A$5:$A$16,0),1),abonos,SUMIFS('ABONOS MENSUALIDADES'!$F$5:$F$500,'ABONOS MENSUALIDADES'!$C$5:$C$500,A19,'ABONOS MENSUALIDADES'!$D$5:$D$500,mes),metodoDirecto,CHOOSE(MATCH($B$2,'ESTADO CONTAB"&"LE'!$A$5:$A$16,0),IF(ISNUMBER(D19),""POR CLASIFICAR"",""""),IFNA(XLOOKUP(A19,PAGOS!$A$2:$A$996,PAGOS!$H$2:$H$996,""""),""""),IFNA(XLOOKUP(A19,PAGOS!$A$2:$A$996,PAGOS!$K$2:$K$996,""""),""""),IFNA(XLOOKUP(A19,PAGOS!$A$2:$A$996,PAGOS!$N$2:$N$996,""""),""""),"&"IFNA(XLOOKUP(A19,PAGOS!$A$2:$A$996,PAGOS!$Q$2:$Q$996,""""),""""),IFNA(XLOOKUP(A19,PAGOS!$A$2:$A$996,PAGOS!$T$2:$T$996,""""),""""),IFNA(XLOOKUP(A19,PAGOS!$A$2:$A$996,PAGOS!$W$2:$W$996,""""),""""),IFNA(XLOOKUP(A19,PAGOS!$A$2:$A$996,PAGOS!$Z$2:$Z$996,""""),"&"""""),IFNA(XLOOKUP(A19,PAGOS!$A$2:$A$996,PAGOS!$AC$2:$AC$996,""""),""""),IFNA(XLOOKUP(A19,PAGOS!$A$2:$A$996,PAGOS!$AF$2:$AF$996,""""),""""),IFNA(XLOOKUP(A19,PAGOS!$A$2:$A$996,PAGOS!$AI$2:$AI$996,""""),""""),IFNA(XLOOKUP(A19,PAGOS!$A$2:$A$996,PAGOS!$AL$2:$"&"AL$996,""""),"""")),IF(abonos>0,IFERROR(TEXTJOIN("" + "",TRUE,UNIQUE(FILTER('ABONOS MENSUALIDADES'!$E$5:$E$500,'ABONOS MENSUALIDADES'!$C$5:$C$500=A19,'ABONOS MENSUALIDADES'!$D$5:$D$500=mes))),""""),metodoDirecto)))"),"TRANSFERENCIA") -> TRANSFERENCIA | F19: {=IF(A19="","",LET(mes,DATE($E$2,MATCH($B$2,'ESTADO CONTABLE'!$A$5:$A$16,0),1),cobrarDesde,IFERROR(INDEX('BASE DE DATOSS'!I:I,ROW()-13),""),pausada,SUMPRODUCT((UPPER(TRIM('PAUSAS MENSUALIDADES'!$A$5:$A$500))=UPPER(TRIM(A19)))*('PAUSAS MENSUALIDADES'!$B$5:$B$500=mes)*(UPPER(TRIM('PAUSAS MENSUALIDADES'!$D$5:$D$500))="APLICAR"))>0,abonoActivo,SUMIFS('ABONOS MENSUALIDADES'!$F$5:$F$500,'ABONOS MENSUALIDADES'!$C$5:$C$500,A19,'ABONOS MENSUALIDADES'!$D$5:$D$500,mes,'ABONOS MENSUALIDADES'!$G$5:$G$500,"<>*CONSOLIDADO EN PAGOS*")>0,esperadaBruta,MAX(IFNA(VLOOKUP(B19,COSTOS!$A$3:$B$13,2,FALSE),0)-150,0),IF(AND(cobrarDesde<>"",mes<cobrarDesde),"AÚN NO INICIA",IF(pausada,"PAUSADA",IF(AND(abonoActivo,COUNTIFS('ABONOS MENSUALIDADES'!$C$5:$C$500,A19,'ABONOS MENSUALIDADES'!$D$5:$D$500,mes,'ABONOS MENSUALIDADES'!$G$5:$G$500,"*MENSUALIDAD LIQUIDADA*")=0),"ABONO",IF(N(D19)>=esperadaBruta,"COBRADA",IF(N(D19)>0,"ABONO","PENDIENTE")))))))} -> COBRADA | G19: {=IF(A19="","",IFERROR(INDEX('BASE DE DATOSS'!I:I,ROW()-13),""))} -> 46023
A20: {=IFERROR(INDEX('BASE DE DATOSS'!A:A,ROW()-13),"")} -> DANIELA AGUILAR CAZORLA | B20: {=IF(A20="","",IFERROR(INDEX('BASE DE DATOSS'!C:C,ROW()-13),""))} -> ADULTS 2 | C20: {=IF(A20="","",LET(mes,DATE($E$2,MATCH($B$2,'ESTADO CONTABLE'!$A$5:$A$16,0),1),cobrarDesde,IFERROR(INDEX('BASE DE DATOSS'!I:I,ROW()-13),""),pausada,SUMPRODUCT((UPPER(TRIM('PAUSAS MENSUALIDADES'!$A$5:$A$500))=UPPER(TRIM(A20)))*('PAUSAS MENSUALIDADES'!$B$5:$B$500=mes)*(UPPER(TRIM('PAUSAS MENSUALIDADES'!$D$5:$D$500))="APLICAR"))>0,IF(OR(AND(cobrarDesde<>"",mes<cobrarDesde),pausada),0,MAX(IFNA(VLOOKUP(B20,COSTOS!$A$3:$B$13,2,FALSE),0)-150,0)/1.16)))} -> 818.96552 | D20: {=IF(A20="","",LET(mes,DATE($E$2,MATCH($B$2,'ESTADO CONTABLE'!$A$5:$A$16,0),1),abonos,SUMIFS('ABONOS MENSUALIDADES'!$F$5:$F$500,'ABONOS MENSUALIDADES'!$C$5:$C$500,A20,'ABONOS MENSUALIDADES'!$D$5:$D$500,mes),pago,CHOOSE(MATCH($B$2,'ESTADO CONTABLE'!$A$5:$A$16,0),IFNA(_xlfn.XLOOKUP(A20,PAGOS!$A$2:$A$996,PAGOS!$E$2:$E$996,""),""),IFNA(_xlfn.XLOOKUP(A20,PAGOS!$A$2:$A$996,PAGOS!$G$2:$G$996,""),""),IFNA(_xlfn.XLOOKUP(A20,PAGOS!$A$2:$A$996,PAGOS!$J$2:$J$996,""),""),IFNA(_xlfn.XLOOKUP(A20,PAGOS!$A$2:$A$996,PAGOS!$M$2:$M$996,""),""),IFNA(_xlfn.XLOOKUP(A20,PAGOS!$A$2:$A$996,PAGOS!$P$2:$P$996,""),""),IFNA(_xlfn.XLOOKUP(A20,PAGOS!$A$2:$A$996,PAGOS!$S$2:$S$996,""),""),IFNA(_xlfn.XLOOKUP(A20,PAGOS!$A$2:$A$996,PAGOS!$V$2:$V$996,""),""),IFNA(_xlfn.XLOOKUP(A20,PAGOS!$A$2:$A$996,PAGOS!$Y$2:$Y$996,""),""),IFNA(_xlfn.XLOOKUP(A20,PAGOS!$A$2:$A$996,PAGOS!$AB$2:$AB$996,""),""),IFNA(_xlfn.XLOOKUP(A20,PAGOS!$A$2:$A$996,PAGOS!$AE$2:$AE$996,""),""),IFNA(_xlfn.XLOOKUP(A20,PAGOS!$A$2:$A$996,PAGOS!$AH$2:$AH$996,""),""),IFNA(_xlfn.XLOOKUP(A20,PAGOS!$A$2:$A$996,PAGOS!$AK$2:$AK$996,""),"")),IF(abonos>0,abonos,pago)))} | E20: =IFERROR(__xludf.DUMMYFUNCTION("IF(A20="""","""",LET(mes,DATE($E$2,MATCH($B$2,'ESTADO CONTABLE'!$A$5:$A$16,0),1),abonos,SUMIFS('ABONOS MENSUALIDADES'!$F$5:$F$500,'ABONOS MENSUALIDADES'!$C$5:$C$500,A20,'ABONOS MENSUALIDADES'!$D$5:$D$500,mes),metodoDirecto,CHOOSE(MATCH($B$2,'ESTADO CONTAB"&"LE'!$A$5:$A$16,0),IF(ISNUMBER(D20),""POR CLASIFICAR"",""""),IFNA(XLOOKUP(A20,PAGOS!$A$2:$A$996,PAGOS!$H$2:$H$996,""""),""""),IFNA(XLOOKUP(A20,PAGOS!$A$2:$A$996,PAGOS!$K$2:$K$996,""""),""""),IFNA(XLOOKUP(A20,PAGOS!$A$2:$A$996,PAGOS!$N$2:$N$996,""""),""""),"&"IFNA(XLOOKUP(A20,PAGOS!$A$2:$A$996,PAGOS!$Q$2:$Q$996,""""),""""),IFNA(XLOOKUP(A20,PAGOS!$A$2:$A$996,PAGOS!$T$2:$T$996,""""),""""),IFNA(XLOOKUP(A20,PAGOS!$A$2:$A$996,PAGOS!$W$2:$W$996,""""),""""),IFNA(XLOOKUP(A20,PAGOS!$A$2:$A$996,PAGOS!$Z$2:$Z$996,""""),"&"""""),IFNA(XLOOKUP(A20,PAGOS!$A$2:$A$996,PAGOS!$AC$2:$AC$996,""""),""""),IFNA(XLOOKUP(A20,PAGOS!$A$2:$A$996,PAGOS!$AF$2:$AF$996,""""),""""),IFNA(XLOOKUP(A20,PAGOS!$A$2:$A$996,PAGOS!$AI$2:$AI$996,""""),""""),IFNA(XLOOKUP(A20,PAGOS!$A$2:$A$996,PAGOS!$AL$2:$"&"AL$996,""""),"""")),IF(abonos>0,IFERROR(TEXTJOIN("" + "",TRUE,UNIQUE(FILTER('ABONOS MENSUALIDADES'!$E$5:$E$500,'ABONOS MENSUALIDADES'!$C$5:$C$500=A20,'ABONOS MENSUALIDADES'!$D$5:$D$500=mes))),""""),metodoDirecto)))"),"") | F20: {=IF(A20="","",LET(mes,DATE($E$2,MATCH($B$2,'ESTADO CONTABLE'!$A$5:$A$16,0),1),cobrarDesde,IFERROR(INDEX('BASE DE DATOSS'!I:I,ROW()-13),""),pausada,SUMPRODUCT((UPPER(TRIM('PAUSAS MENSUALIDADES'!$A$5:$A$500))=UPPER(TRIM(A20)))*('PAUSAS MENSUALIDADES'!$B$5:$B$500=mes)*(UPPER(TRIM('PAUSAS MENSUALIDADES'!$D$5:$D$500))="APLICAR"))>0,abonoActivo,SUMIFS('ABONOS MENSUALIDADES'!$F$5:$F$500,'ABONOS MENSUALIDADES'!$C$5:$C$500,A20,'ABONOS MENSUALIDADES'!$D$5:$D$500,mes,'ABONOS MENSUALIDADES'!$G$5:$G$500,"<>*CONSOLIDADO EN PAGOS*")>0,esperadaBruta,MAX(IFNA(VLOOKUP(B20,COSTOS!$A$3:$B$13,2,FALSE),0)-150,0),IF(AND(cobrarDesde<>"",mes<cobrarDesde),"AÚN NO INICIA",IF(pausada,"PAUSADA",IF(AND(abonoActivo,COUNTIFS('ABONOS MENSUALIDADES'!$C$5:$C$500,A20,'ABONOS MENSUALIDADES'!$D$5:$D$500,mes,'ABONOS MENSUALIDADES'!$G$5:$G$500,"*MENSUALIDAD LIQUIDADA*")=0),"ABONO",IF(N(D20)>=esperadaBruta,"COBRADA",IF(N(D20)>0,"ABONO","PENDIENTE")))))))} -> PENDIENTE | G20: {=IF(A20="","",IFERROR(INDEX('BASE DE DATOSS'!I:I,ROW()-13),""))} -> 46023
A21: {=IFERROR(INDEX('BASE DE DATOSS'!A:A,ROW()-13),"")} -> DARIANA RODRIGUEZ SANCHEZ | B21: {=IF(A21="","",IFERROR(INDEX('BASE DE DATOSS'!C:C,ROW()-13),""))} -> MATUTINO | C21: {=IF(A21="","",LET(mes,DATE($E$2,MATCH($B$2,'ESTADO CONTABLE'!$A$5:$A$16,0),1),cobrarDesde,IFERROR(INDEX('BASE DE DATOSS'!I:I,ROW()-13),""),pausada,SUMPRODUCT((UPPER(TRIM('PAUSAS MENSUALIDADES'!$A$5:$A$500))=UPPER(TRIM(A21)))*('PAUSAS MENSUALIDADES'!$B$5:$B$500=mes)*(UPPER(TRIM('PAUSAS MENSUALIDADES'!$D$5:$D$500))="APLICAR"))>0,IF(OR(AND(cobrarDesde<>"",mes<cobrarDesde),pausada),0,MAX(IFNA(VLOOKUP(B21,COSTOS!$A$3:$B$13,2,FALSE),0)-150,0)/1.16)))} -> 818.96552 | D21: {=IF(A21="","",LET(mes,DATE($E$2,MATCH($B$2,'ESTADO CONTABLE'!$A$5:$A$16,0),1),abonos,SUMIFS('ABONOS MENSUALIDADES'!$F$5:$F$500,'ABONOS MENSUALIDADES'!$C$5:$C$500,A21,'ABONOS MENSUALIDADES'!$D$5:$D$500,mes),pago,CHOOSE(MATCH($B$2,'ESTADO CONTABLE'!$A$5:$A$16,0),IFNA(_xlfn.XLOOKUP(A21,PAGOS!$A$2:$A$996,PAGOS!$E$2:$E$996,""),""),IFNA(_xlfn.XLOOKUP(A21,PAGOS!$A$2:$A$996,PAGOS!$G$2:$G$996,""),""),IFNA(_xlfn.XLOOKUP(A21,PAGOS!$A$2:$A$996,PAGOS!$J$2:$J$996,""),""),IFNA(_xlfn.XLOOKUP(A21,PAGOS!$A$2:$A$996,PAGOS!$M$2:$M$996,""),""),IFNA(_xlfn.XLOOKUP(A21,PAGOS!$A$2:$A$996,PAGOS!$P$2:$P$996,""),""),IFNA(_xlfn.XLOOKUP(A21,PAGOS!$A$2:$A$996,PAGOS!$S$2:$S$996,""),""),IFNA(_xlfn.XLOOKUP(A21,PAGOS!$A$2:$A$996,PAGOS!$V$2:$V$996,""),""),IFNA(_xlfn.XLOOKUP(A21,PAGOS!$A$2:$A$996,PAGOS!$Y$2:$Y$996,""),""),IFNA(_xlfn.XLOOKUP(A21,PAGOS!$A$2:$A$996,PAGOS!$AB$2:$AB$996,""),""),IFNA(_xlfn.XLOOKUP(A21,PAGOS!$A$2:$A$996,PAGOS!$AE$2:$AE$996,""),""),IFNA(_xlfn.XLOOKUP(A21,PAGOS!$A$2:$A$996,PAGOS!$AH$2:$AH$996,""),""),IFNA(_xlfn.XLOOKUP(A21,PAGOS!$A$2:$A$996,PAGOS!$AK$2:$AK$996,""),"")),IF(abonos>0,abonos,pago)))} -> 950 | E21: =IFERROR(__xludf.DUMMYFUNCTION("IF(A21="""","""",LET(mes,DATE($E$2,MATCH($B$2,'ESTADO CONTABLE'!$A$5:$A$16,0),1),abonos,SUMIFS('ABONOS MENSUALIDADES'!$F$5:$F$500,'ABONOS MENSUALIDADES'!$C$5:$C$500,A21,'ABONOS MENSUALIDADES'!$D$5:$D$500,mes),metodoDirecto,CHOOSE(MATCH($B$2,'ESTADO CONTAB"&"LE'!$A$5:$A$16,0),IF(ISNUMBER(D21),""POR CLASIFICAR"",""""),IFNA(XLOOKUP(A21,PAGOS!$A$2:$A$996,PAGOS!$H$2:$H$996,""""),""""),IFNA(XLOOKUP(A21,PAGOS!$A$2:$A$996,PAGOS!$K$2:$K$996,""""),""""),IFNA(XLOOKUP(A21,PAGOS!$A$2:$A$996,PAGOS!$N$2:$N$996,""""),""""),"&"IFNA(XLOOKUP(A21,PAGOS!$A$2:$A$996,PAGOS!$Q$2:$Q$996,""""),""""),IFNA(XLOOKUP(A21,PAGOS!$A$2:$A$996,PAGOS!$T$2:$T$996,""""),""""),IFNA(XLOOKUP(A21,PAGOS!$A$2:$A$996,PAGOS!$W$2:$W$996,""""),""""),IFNA(XLOOKUP(A21,PAGOS!$A$2:$A$996,PAGOS!$Z$2:$Z$996,""""),"&"""""),IFNA(XLOOKUP(A21,PAGOS!$A$2:$A$996,PAGOS!$AC$2:$AC$996,""""),""""),IFNA(XLOOKUP(A21,PAGOS!$A$2:$A$996,PAGOS!$AF$2:$AF$996,""""),""""),IFNA(XLOOKUP(A21,PAGOS!$A$2:$A$996,PAGOS!$AI$2:$AI$996,""""),""""),IFNA(XLOOKUP(A21,PAGOS!$A$2:$A$996,PAGOS!$AL$2:$"&"AL$996,""""),"""")),IF(abonos>0,IFERROR(TEXTJOIN("" + "",TRUE,UNIQUE(FILTER('ABONOS MENSUALIDADES'!$E$5:$E$500,'ABONOS MENSUALIDADES'!$C$5:$C$500=A21,'ABONOS MENSUALIDADES'!$D$5:$D$500=mes))),""""),metodoDirecto)))"),"TRANSFERENCIA") -> TRANSFERENCIA | F21: {=IF(A21="","",LET(mes,DATE($E$2,MATCH($B$2,'ESTADO CONTABLE'!$A$5:$A$16,0),1),cobrarDesde,IFERROR(INDEX('BASE DE DATOSS'!I:I,ROW()-13),""),pausada,SUMPRODUCT((UPPER(TRIM('PAUSAS MENSUALIDADES'!$A$5:$A$500))=UPPER(TRIM(A21)))*('PAUSAS MENSUALIDADES'!$B$5:$B$500=mes)*(UPPER(TRIM('PAUSAS MENSUALIDADES'!$D$5:$D$500))="APLICAR"))>0,abonoActivo,SUMIFS('ABONOS MENSUALIDADES'!$F$5:$F$500,'ABONOS MENSUALIDADES'!$C$5:$C$500,A21,'ABONOS MENSUALIDADES'!$D$5:$D$500,mes,'ABONOS MENSUALIDADES'!$G$5:$G$500,"<>*CONSOLIDADO EN PAGOS*")>0,esperadaBruta,MAX(IFNA(VLOOKUP(B21,COSTOS!$A$3:$B$13,2,FALSE),0)-150,0),IF(AND(cobrarDesde<>"",mes<cobrarDesde),"AÚN NO INICIA",IF(pausada,"PAUSADA",IF(AND(abonoActivo,COUNTIFS('ABONOS MENSUALIDADES'!$C$5:$C$500,A21,'ABONOS MENSUALIDADES'!$D$5:$D$500,mes,'ABONOS MENSUALIDADES'!$G$5:$G$500,"*MENSUALIDAD LIQUIDADA*")=0),"ABONO",IF(N(D21)>=esperadaBruta,"COBRADA",IF(N(D21)>0,"ABONO","PENDIENTE")))))))} -> COBRADA | G21: {=IF(A21="","",IFERROR(INDEX('BASE DE DATOSS'!I:I,ROW()-13),""))} -> 46023
A22: {=IFERROR(INDEX('BASE DE DATOSS'!A:A,ROW()-13),"")} -> MIA ISABELLA CHAVEZ ARELLANO | B22: {=IF(A22="","",IFERROR(INDEX('BASE DE DATOSS'!C:C,ROW()-13),""))} -> SABATINO | C22: {=IF(A22="","",LET(mes,DATE($E$2,MATCH($B$2,'ESTADO CONTABLE'!$A$5:$A$16,0),1),cobrarDesde,IFERROR(INDEX('BASE DE DATOSS'!I:I,ROW()-13),""),pausada,SUMPRODUCT((UPPER(TRIM('PAUSAS MENSUALIDADES'!$A$5:$A$500))=UPPER(TRIM(A22)))*('PAUSAS MENSUALIDADES'!$B$5:$B$500=mes)*(UPPER(TRIM('PAUSAS MENSUALIDADES'!$D$5:$D$500))="APLICAR"))>0,IF(OR(AND(cobrarDesde<>"",mes<cobrarDesde),pausada),0,MAX(IFNA(VLOOKUP(B22,COSTOS!$A$3:$B$13,2,FALSE),0)-150,0)/1.16)))} -> 474.13793 | D22: {=IF(A22="","",LET(mes,DATE($E$2,MATCH($B$2,'ESTADO CONTABLE'!$A$5:$A$16,0),1),abonos,SUMIFS('ABONOS MENSUALIDADES'!$F$5:$F$500,'ABONOS MENSUALIDADES'!$C$5:$C$500,A22,'ABONOS MENSUALIDADES'!$D$5:$D$500,mes),pago,CHOOSE(MATCH($B$2,'ESTADO CONTABLE'!$A$5:$A$16,0),IFNA(_xlfn.XLOOKUP(A22,PAGOS!$A$2:$A$996,PAGOS!$E$2:$E$996,""),""),IFNA(_xlfn.XLOOKUP(A22,PAGOS!$A$2:$A$996,PAGOS!$G$2:$G$996,""),""),IFNA(_xlfn.XLOOKUP(A22,PAGOS!$A$2:$A$996,PAGOS!$J$2:$J$996,""),""),IFNA(_xlfn.XLOOKUP(A22,PAGOS!$A$2:$A$996,PAGOS!$M$2:$M$996,""),""),IFNA(_xlfn.XLOOKUP(A22,PAGOS!$A$2:$A$996,PAGOS!$P$2:$P$996,""),""),IFNA(_xlfn.XLOOKUP(A22,PAGOS!$A$2:$A$996,PAGOS!$S$2:$S$996,""),""),IFNA(_xlfn.XLOOKUP(A22,PAGOS!$A$2:$A$996,PAGOS!$V$2:$V$996,""),""),IFNA(_xlfn.XLOOKUP(A22,PAGOS!$A$2:$A$996,PAGOS!$Y$2:$Y$996,""),""),IFNA(_xlfn.XLOOKUP(A22,PAGOS!$A$2:$A$996,PAGOS!$AB$2:$AB$996,""),""),IFNA(_xlfn.XLOOKUP(A22,PAGOS!$A$2:$A$996,PAGOS!$AE$2:$AE$996,""),""),IFNA(_xlfn.XLOOKUP(A22,PAGOS!$A$2:$A$996,PAGOS!$AH$2:$AH$996,""),""),IFNA(_xlfn.XLOOKUP(A22,PAGOS!$A$2:$A$996,PAGOS!$AK$2:$AK$996,""),"")),IF(abonos>0,abonos,pago)))} -> 550 | E22: =IFERROR(__xludf.DUMMYFUNCTION("IF(A22="""","""",LET(mes,DATE($E$2,MATCH($B$2,'ESTADO CONTABLE'!$A$5:$A$16,0),1),abonos,SUMIFS('ABONOS MENSUALIDADES'!$F$5:$F$500,'ABONOS MENSUALIDADES'!$C$5:$C$500,A22,'ABONOS MENSUALIDADES'!$D$5:$D$500,mes),metodoDirecto,CHOOSE(MATCH($B$2,'ESTADO CONTAB"&"LE'!$A$5:$A$16,0),IF(ISNUMBER(D22),""POR CLASIFICAR"",""""),IFNA(XLOOKUP(A22,PAGOS!$A$2:$A$996,PAGOS!$H$2:$H$996,""""),""""),IFNA(XLOOKUP(A22,PAGOS!$A$2:$A$996,PAGOS!$K$2:$K$996,""""),""""),IFNA(XLOOKUP(A22,PAGOS!$A$2:$A$996,PAGOS!$N$2:$N$996,""""),""""),"&"IFNA(XLOOKUP(A22,PAGOS!$A$2:$A$996,PAGOS!$Q$2:$Q$996,""""),""""),IFNA(XLOOKUP(A22,PAGOS!$A$2:$A$996,PAGOS!$T$2:$T$996,""""),""""),IFNA(XLOOKUP(A22,PAGOS!$A$2:$A$996,PAGOS!$W$2:$W$996,""""),""""),IFNA(XLOOKUP(A22,PAGOS!$A$2:$A$996,PAGOS!$Z$2:$Z$996,""""),"&"""""),IFNA(XLOOKUP(A22,PAGOS!$A$2:$A$996,PAGOS!$AC$2:$AC$996,""""),""""),IFNA(XLOOKUP(A22,PAGOS!$A$2:$A$996,PAGOS!$AF$2:$AF$996,""""),""""),IFNA(XLOOKUP(A22,PAGOS!$A$2:$A$996,PAGOS!$AI$2:$AI$996,""""),""""),IFNA(XLOOKUP(A22,PAGOS!$A$2:$A$996,PAGOS!$AL$2:$"&"AL$996,""""),"""")),IF(abonos>0,IFERROR(TEXTJOIN("" + "",TRUE,UNIQUE(FILTER('ABONOS MENSUALIDADES'!$E$5:$E$500,'ABONOS MENSUALIDADES'!$C$5:$C$500=A22,'ABONOS MENSUALIDADES'!$D$5:$D$500=mes))),""""),metodoDirecto)))"),"TRANSFERENCIA") -> TRANSFERENCIA | F22: {=IF(A22="","",LET(mes,DATE($E$2,MATCH($B$2,'ESTADO CONTABLE'!$A$5:$A$16,0),1),cobrarDesde,IFERROR(INDEX('BASE DE DATOSS'!I:I,ROW()-13),""),pausada,SUMPRODUCT((UPPER(TRIM('PAUSAS MENSUALIDADES'!$A$5:$A$500))=UPPER(TRIM(A22)))*('PAUSAS MENSUALIDADES'!$B$5:$B$500=mes)*(UPPER(TRIM('PAUSAS MENSUALIDADES'!$D$5:$D$500))="APLICAR"))>0,abonoActivo,SUMIFS('ABONOS MENSUALIDADES'!$F$5:$F$500,'ABONOS MENSUALIDADES'!$C$5:$C$500,A22,'ABONOS MENSUALIDADES'!$D$5:$D$500,mes,'ABONOS MENSUALIDADES'!$G$5:$G$500,"<>*CONSOLIDADO EN PAGOS*")>0,esperadaBruta,MAX(IFNA(VLOOKUP(B22,COSTOS!$A$3:$B$13,2,FALSE),0)-150,0),IF(AND(cobrarDesde<>"",mes<cobrarDesde),"AÚN NO INICIA",IF(pausada,"PAUSADA",IF(AND(abonoActivo,COUNTIFS('ABONOS MENSUALIDADES'!$C$5:$C$500,A22,'ABONOS MENSUALIDADES'!$D$5:$D$500,mes,'ABONOS MENSUALIDADES'!$G$5:$G$500,"*MENSUALIDAD LIQUIDADA*")=0),"ABONO",IF(N(D22)>=esperadaBruta,"COBRADA",IF(N(D22)>0,"ABONO","PENDIENTE")))))))} -> COBRADA | G22: {=IF(A22="","",IFERROR(INDEX('BASE DE DATOSS'!I:I,ROW()-13),""))} -> 46023
A23: {=IFERROR(INDEX('BASE DE DATOSS'!A:A,ROW()-13),"")} -> OXANA VILLALOBOS | B23: {=IF(A23="","",IFERROR(INDEX('BASE DE DATOSS'!C:C,ROW()-13),""))} -> ADULTS 1 | C23: {=IF(A23="","",LET(mes,DATE($E$2,MATCH($B$2,'ESTADO CONTABLE'!$A$5:$A$16,0),1),cobrarDesde,IFERROR(INDEX('BASE DE DATOSS'!I:I,ROW()-13),""),pausada,SUMPRODUCT((UPPER(TRIM('PAUSAS MENSUALIDADES'!$A$5:$A$500))=UPPER(TRIM(A23)))*('PAUSAS MENSUALIDADES'!$B$5:$B$500=mes)*(UPPER(TRIM('PAUSAS MENSUALIDADES'!$D$5:$D$500))="APLICAR"))>0,IF(OR(AND(cobrarDesde<>"",mes<cobrarDesde),pausada),0,MAX(IFNA(VLOOKUP(B23,COSTOS!$A$3:$B$13,2,FALSE),0)-150,0)/1.16)))} -> 991.37931 | D23: {=IF(A23="","",LET(mes,DATE($E$2,MATCH($B$2,'ESTADO CONTABLE'!$A$5:$A$16,0),1),abonos,SUMIFS('ABONOS MENSUALIDADES'!$F$5:$F$500,'ABONOS MENSUALIDADES'!$C$5:$C$500,A23,'ABONOS MENSUALIDADES'!$D$5:$D$500,mes),pago,CHOOSE(MATCH($B$2,'ESTADO CONTABLE'!$A$5:$A$16,0),IFNA(_xlfn.XLOOKUP(A23,PAGOS!$A$2:$A$996,PAGOS!$E$2:$E$996,""),""),IFNA(_xlfn.XLOOKUP(A23,PAGOS!$A$2:$A$996,PAGOS!$G$2:$G$996,""),""),IFNA(_xlfn.XLOOKUP(A23,PAGOS!$A$2:$A$996,PAGOS!$J$2:$J$996,""),""),IFNA(_xlfn.XLOOKUP(A23,PAGOS!$A$2:$A$996,PAGOS!$M$2:$M$996,""),""),IFNA(_xlfn.XLOOKUP(A23,PAGOS!$A$2:$A$996,PAGOS!$P$2:$P$996,""),""),IFNA(_xlfn.XLOOKUP(A23,PAGOS!$A$2:$A$996,PAGOS!$S$2:$S$996,""),""),IFNA(_xlfn.XLOOKUP(A23,PAGOS!$A$2:$A$996,PAGOS!$V$2:$V$996,""),""),IFNA(_xlfn.XLOOKUP(A23,PAGOS!$A$2:$A$996,PAGOS!$Y$2:$Y$996,""),""),IFNA(_xlfn.XLOOKUP(A23,PAGOS!$A$2:$A$996,PAGOS!$AB$2:$AB$996,""),""),IFNA(_xlfn.XLOOKUP(A23,PAGOS!$A$2:$A$996,PAGOS!$AE$2:$AE$996,""),""),IFNA(_xlfn.XLOOKUP(A23,PAGOS!$A$2:$A$996,PAGOS!$AH$2:$AH$996,""),""),IFNA(_xlfn.XLOOKUP(A23,PAGOS!$A$2:$A$996,PAGOS!$AK$2:$AK$996,""),"")),IF(abonos>0,abonos,pago)))} | E23: =IFERROR(__xludf.DUMMYFUNCTION("IF(A23="""","""",LET(mes,DATE($E$2,MATCH($B$2,'ESTADO CONTABLE'!$A$5:$A$16,0),1),abonos,SUMIFS('ABONOS MENSUALIDADES'!$F$5:$F$500,'ABONOS MENSUALIDADES'!$C$5:$C$500,A23,'ABONOS MENSUALIDADES'!$D$5:$D$500,mes),metodoDirecto,CHOOSE(MATCH($B$2,'ESTADO CONTAB"&"LE'!$A$5:$A$16,0),IF(ISNUMBER(D23),""POR CLASIFICAR"",""""),IFNA(XLOOKUP(A23,PAGOS!$A$2:$A$996,PAGOS!$H$2:$H$996,""""),""""),IFNA(XLOOKUP(A23,PAGOS!$A$2:$A$996,PAGOS!$K$2:$K$996,""""),""""),IFNA(XLOOKUP(A23,PAGOS!$A$2:$A$996,PAGOS!$N$2:$N$996,""""),""""),"&"IFNA(XLOOKUP(A23,PAGOS!$A$2:$A$996,PAGOS!$Q$2:$Q$996,""""),""""),IFNA(XLOOKUP(A23,PAGOS!$A$2:$A$996,PAGOS!$T$2:$T$996,""""),""""),IFNA(XLOOKUP(A23,PAGOS!$A$2:$A$996,PAGOS!$W$2:$W$996,""""),""""),IFNA(XLOOKUP(A23,PAGOS!$A$2:$A$996,PAGOS!$Z$2:$Z$996,""""),"&"""""),IFNA(XLOOKUP(A23,PAGOS!$A$2:$A$996,PAGOS!$AC$2:$AC$996,""""),""""),IFNA(XLOOKUP(A23,PAGOS!$A$2:$A$996,PAGOS!$AF$2:$AF$996,""""),""""),IFNA(XLOOKUP(A23,PAGOS!$A$2:$A$996,PAGOS!$AI$2:$AI$996,""""),""""),IFNA(XLOOKUP(A23,PAGOS!$A$2:$A$996,PAGOS!$AL$2:$"&"AL$996,""""),"""")),IF(abonos>0,IFERROR(TEXTJOIN("" + "",TRUE,UNIQUE(FILTER('ABONOS MENSUALIDADES'!$E$5:$E$500,'ABONOS MENSUALIDADES'!$C$5:$C$500=A23,'ABONOS MENSUALIDADES'!$D$5:$D$500=mes))),""""),metodoDirecto)))"),"") | F23: {=IF(A23="","",LET(mes,DATE($E$2,MATCH($B$2,'ESTADO CONTABLE'!$A$5:$A$16,0),1),cobrarDesde,IFERROR(INDEX('BASE DE DATOSS'!I:I,ROW()-13),""),pausada,SUMPRODUCT((UPPER(TRIM('PAUSAS MENSUALIDADES'!$A$5:$A$500))=UPPER(TRIM(A23)))*('PAUSAS MENSUALIDADES'!$B$5:$B$500=mes)*(UPPER(TRIM('PAUSAS MENSUALIDADES'!$D$5:$D$500))="APLICAR"))>0,abonoActivo,SUMIFS('ABONOS MENSUALIDADES'!$F$5:$F$500,'ABONOS MENSUALIDADES'!$C$5:$C$500,A23,'ABONOS MENSUALIDADES'!$D$5:$D$500,mes,'ABONOS MENSUALIDADES'!$G$5:$G$500,"<>*CONSOLIDADO EN PAGOS*")>0,esperadaBruta,MAX(IFNA(VLOOKUP(B23,COSTOS!$A$3:$B$13,2,FALSE),0)-150,0),IF(AND(cobrarDesde<>"",mes<cobrarDesde),"AÚN NO INICIA",IF(pausada,"PAUSADA",IF(AND(abonoActivo,COUNTIFS('ABONOS MENSUALIDADES'!$C$5:$C$500,A23,'ABONOS MENSUALIDADES'!$D$5:$D$500,mes,'ABONOS MENSUALIDADES'!$G$5:$G$500,"*MENSUALIDAD LIQUIDADA*")=0),"ABONO",IF(N(D23)>=esperadaBruta,"COBRADA",IF(N(D23)>0,"ABONO","PENDIENTE")))))))} -> PENDIENTE | G23: {=IF(A23="","",IFERROR(INDEX('BASE DE DATOSS'!I:I,ROW()-13),""))} -> 46023
A24: {=IFERROR(INDEX('BASE DE DATOSS'!A:A,ROW()-13),"")} -> REGINA GUADALUPE RODRIGUEZ CHAVEZ | B24: {=IF(A24="","",IFERROR(INDEX('BASE DE DATOSS'!C:C,ROW()-13),""))} -> JR 2 | C24: {=IF(A24="","",LET(mes,DATE($E$2,MATCH($B$2,'ESTADO CONTABLE'!$A$5:$A$16,0),1),cobrarDesde,IFERROR(INDEX('BASE DE DATOSS'!I:I,ROW()-13),""),pausada,SUMPRODUCT((UPPER(TRIM('PAUSAS MENSUALIDADES'!$A$5:$A$500))=UPPER(TRIM(A24)))*('PAUSAS MENSUALIDADES'!$B$5:$B$500=mes)*(UPPER(TRIM('PAUSAS MENSUALIDADES'!$D$5:$D$500))="APLICAR"))>0,IF(OR(AND(cobrarDesde<>"",mes<cobrarDesde),pausada),0,MAX(IFNA(VLOOKUP(B24,COSTOS!$A$3:$B$13,2,FALSE),0)-150,0)/1.16)))} -> 689.65517 | D24: {=IF(A24="","",LET(mes,DATE($E$2,MATCH($B$2,'ESTADO CONTABLE'!$A$5:$A$16,0),1),abonos,SUMIFS('ABONOS MENSUALIDADES'!$F$5:$F$500,'ABONOS MENSUALIDADES'!$C$5:$C$500,A24,'ABONOS MENSUALIDADES'!$D$5:$D$500,mes),pago,CHOOSE(MATCH($B$2,'ESTADO CONTABLE'!$A$5:$A$16,0),IFNA(_xlfn.XLOOKUP(A24,PAGOS!$A$2:$A$996,PAGOS!$E$2:$E$996,""),""),IFNA(_xlfn.XLOOKUP(A24,PAGOS!$A$2:$A$996,PAGOS!$G$2:$G$996,""),""),IFNA(_xlfn.XLOOKUP(A24,PAGOS!$A$2:$A$996,PAGOS!$J$2:$J$996,""),""),IFNA(_xlfn.XLOOKUP(A24,PAGOS!$A$2:$A$996,PAGOS!$M$2:$M$996,""),""),IFNA(_xlfn.XLOOKUP(A24,PAGOS!$A$2:$A$996,PAGOS!$P$2:$P$996,""),""),IFNA(_xlfn.XLOOKUP(A24,PAGOS!$A$2:$A$996,PAGOS!$S$2:$S$996,""),""),IFNA(_xlfn.XLOOKUP(A24,PAGOS!$A$2:$A$996,PAGOS!$V$2:$V$996,""),""),IFNA(_xlfn.XLOOKUP(A24,PAGOS!$A$2:$A$996,PAGOS!$Y$2:$Y$996,""),""),IFNA(_xlfn.XLOOKUP(A24,PAGOS!$A$2:$A$996,PAGOS!$AB$2:$AB$996,""),""),IFNA(_xlfn.XLOOKUP(A24,PAGOS!$A$2:$A$996,PAGOS!$AE$2:$AE$996,""),""),IFNA(_xlfn.XLOOKUP(A24,PAGOS!$A$2:$A$996,PAGOS!$AH$2:$AH$996,""),""),IFNA(_xlfn.XLOOKUP(A24,PAGOS!$A$2:$A$996,PAGOS!$AK$2:$AK$996,""),"")),IF(abonos>0,abonos,pago)))} -> 800 | E24: =IFERROR(__xludf.DUMMYFUNCTION("IF(A24="""","""",LET(mes,DATE($E$2,MATCH($B$2,'ESTADO CONTABLE'!$A$5:$A$16,0),1),abonos,SUMIFS('ABONOS MENSUALIDADES'!$F$5:$F$500,'ABONOS MENSUALIDADES'!$C$5:$C$500,A24,'ABONOS MENSUALIDADES'!$D$5:$D$500,mes),metodoDirecto,CHOOSE(MATCH($B$2,'ESTADO CONTAB"&"LE'!$A$5:$A$16,0),IF(ISNUMBER(D24),""POR CLASIFICAR"",""""),IFNA(XLOOKUP(A24,PAGOS!$A$2:$A$996,PAGOS!$H$2:$H$996,""""),""""),IFNA(XLOOKUP(A24,PAGOS!$A$2:$A$996,PAGOS!$K$2:$K$996,""""),""""),IFNA(XLOOKUP(A24,PAGOS!$A$2:$A$996,PAGOS!$N$2:$N$996,""""),""""),"&"IFNA(XLOOKUP(A24,PAGOS!$A$2:$A$996,PAGOS!$Q$2:$Q$996,""""),""""),IFNA(XLOOKUP(A24,PAGOS!$A$2:$A$996,PAGOS!$T$2:$T$996,""""),""""),IFNA(XLOOKUP(A24,PAGOS!$A$2:$A$996,PAGOS!$W$2:$W$996,""""),""""),IFNA(XLOOKUP(A24,PAGOS!$A$2:$A$996,PAGOS!$Z$2:$Z$996,""""),"&"""""),IFNA(XLOOKUP(A24,PAGOS!$A$2:$A$996,PAGOS!$AC$2:$AC$996,""""),""""),IFNA(XLOOKUP(A24,PAGOS!$A$2:$A$996,PAGOS!$AF$2:$AF$996,""""),""""),IFNA(XLOOKUP(A24,PAGOS!$A$2:$A$996,PAGOS!$AI$2:$AI$996,""""),""""),IFNA(XLOOKUP(A24,PAGOS!$A$2:$A$996,PAGOS!$AL$2:$"&"AL$996,""""),"""")),IF(abonos>0,IFERROR(TEXTJOIN("" + "",TRUE,UNIQUE(FILTER('ABONOS MENSUALIDADES'!$E$5:$E$500,'ABONOS MENSUALIDADES'!$C$5:$C$500=A24,'ABONOS MENSUALIDADES'!$D$5:$D$500=mes))),""""),metodoDirecto)))"),"EFECTIVO") -> EFECTIVO | F24: {=IF(A24="","",LET(mes,DATE($E$2,MATCH($B$2,'ESTADO CONTABLE'!$A$5:$A$16,0),1),cobrarDesde,IFERROR(INDEX('BASE DE DATOSS'!I:I,ROW()-13),""),pausada,SUMPRODUCT((UPPER(TRIM('PAUSAS MENSUALIDADES'!$A$5:$A$500))=UPPER(TRIM(A24)))*('PAUSAS MENSUALIDADES'!$B$5:$B$500=mes)*(UPPER(TRIM('PAUSAS MENSUALIDADES'!$D$5:$D$500))="APLICAR"))>0,abonoActivo,SUMIFS('ABONOS MENSUALIDADES'!$F$5:$F$500,'ABONOS MENSUALIDADES'!$C$5:$C$500,A24,'ABONOS MENSUALIDADES'!$D$5:$D$500,mes,'ABONOS MENSUALIDADES'!$G$5:$G$500,"<>*CONSOLIDADO EN PAGOS*")>0,esperadaBruta,MAX(IFNA(VLOOKUP(B24,COSTOS!$A$3:$B$13,2,FALSE),0)-150,0),IF(AND(cobrarDesde<>"",mes<cobrarDesde),"AÚN NO INICIA",IF(pausada,"PAUSADA",IF(AND(abonoActivo,COUNTIFS('ABONOS MENSUALIDADES'!$C$5:$C$500,A24,'ABONOS MENSUALIDADES'!$D$5:$D$500,mes,'ABONOS MENSUALIDADES'!$G$5:$G$500,"*MENSUALIDAD LIQUIDADA*")=0),"ABONO",IF(N(D24)>=esperadaBruta,"COBRADA",IF(N(D24)>0,"ABONO","PENDIENTE")))))))} -> COBRADA | G24: {=IF(A24="","",IFERROR(INDEX('BASE DE DATOSS'!I:I,ROW()-13),""))} -> 46023
A25: {=IFERROR(INDEX('BASE DE DATOSS'!A:A,ROW()-13),"")} -> REGINA J CHAVEZ ALCARAZ | B25: {=IF(A25="","",LET(mes,DATE($E$2,MATCH($B$2,'ESTADO CONTABLE'!$A$5:$A$16,0),1),grupoActual,IFERROR(INDEX('BASE DE DATOSS'!C:C,ROW()-13),""),IF(AND(UPPER(TRIM(A25))="REGINA J CHAVEZ ALCARAZ",mes<DATE(2026,10,1)),"ADULTS 1",grupoActual)))} -> ADULTS 2 | C25: {=IF(A25="","",LET(mes,DATE($E$2,MATCH($B$2,'ESTADO CONTABLE'!$A$5:$A$16,0),1),cobrarDesde,IFERROR(INDEX('BASE DE DATOSS'!I:I,ROW()-13),""),pausada,SUMPRODUCT((UPPER(TRIM('PAUSAS MENSUALIDADES'!$A$5:$A$500))=UPPER(TRIM(A25)))*('PAUSAS MENSUALIDADES'!$B$5:$B$500=mes)*(UPPER(TRIM('PAUSAS MENSUALIDADES'!$D$5:$D$500))="APLICAR"))>0,IF(OR(AND(cobrarDesde<>"",mes<cobrarDesde),pausada),0,MAX(IFNA(VLOOKUP(B25,COSTOS!$A$3:$B$13,2,FALSE),0)-150,0)/1.16)))} -> 818.96552 | D25: {=IF(A25="","",LET(mes,DATE($E$2,MATCH($B$2,'ESTADO CONTABLE'!$A$5:$A$16,0),1),abonos,SUMIFS('ABONOS MENSUALIDADES'!$F$5:$F$500,'ABONOS MENSUALIDADES'!$C$5:$C$500,A25,'ABONOS MENSUALIDADES'!$D$5:$D$500,mes),pago,CHOOSE(MATCH($B$2,'ESTADO CONTABLE'!$A$5:$A$16,0),IFNA(_xlfn.XLOOKUP(A25,PAGOS!$A$2:$A$996,PAGOS!$E$2:$E$996,""),""),IFNA(_xlfn.XLOOKUP(A25,PAGOS!$A$2:$A$996,PAGOS!$G$2:$G$996,""),""),IFNA(_xlfn.XLOOKUP(A25,PAGOS!$A$2:$A$996,PAGOS!$J$2:$J$996,""),""),IFNA(_xlfn.XLOOKUP(A25,PAGOS!$A$2:$A$996,PAGOS!$M$2:$M$996,""),""),IFNA(_xlfn.XLOOKUP(A25,PAGOS!$A$2:$A$996,PAGOS!$P$2:$P$996,""),""),IFNA(_xlfn.XLOOKUP(A25,PAGOS!$A$2:$A$996,PAGOS!$S$2:$S$996,""),""),IFNA(_xlfn.XLOOKUP(A25,PAGOS!$A$2:$A$996,PAGOS!$V$2:$V$996,""),""),IFNA(_xlfn.XLOOKUP(A25,PAGOS!$A$2:$A$996,PAGOS!$Y$2:$Y$996,""),""),IFNA(_xlfn.XLOOKUP(A25,PAGOS!$A$2:$A$996,PAGOS!$AB$2:$AB$996,""),""),IFNA(_xlfn.XLOOKUP(A25,PAGOS!$A$2:$A$996,PAGOS!$AE$2:$AE$996,""),""),IFNA(_xlfn.XLOOKUP(A25,PAGOS!$A$2:$A$996,PAGOS!$AH$2:$AH$996,""),""),IFNA(_xlfn.XLOOKUP(A25,PAGOS!$A$2:$A$996,PAGOS!$AK$2:$AK$996,""),"")),IF(abonos>0,abonos,pago)))} -> 950 | E25: =IFERROR(__xludf.DUMMYFUNCTION("IF(A25="""","""",LET(mes,DATE($E$2,MATCH($B$2,'ESTADO CONTABLE'!$A$5:$A$16,0),1),abonos,SUMIFS('ABONOS MENSUALIDADES'!$F$5:$F$500,'ABONOS MENSUALIDADES'!$C$5:$C$500,A25,'ABONOS MENSUALIDADES'!$D$5:$D$500,mes),metodoDirecto,CHOOSE(MATCH($B$2,'ESTADO CONTAB"&"LE'!$A$5:$A$16,0),IF(ISNUMBER(D25),""POR CLASIFICAR"",""""),IFNA(XLOOKUP(A25,PAGOS!$A$2:$A$996,PAGOS!$H$2:$H$996,""""),""""),IFNA(XLOOKUP(A25,PAGOS!$A$2:$A$996,PAGOS!$K$2:$K$996,""""),""""),IFNA(XLOOKUP(A25,PAGOS!$A$2:$A$996,PAGOS!$N$2:$N$996,""""),""""),"&"IFNA(XLOOKUP(A25,PAGOS!$A$2:$A$996,PAGOS!$Q$2:$Q$996,""""),""""),IFNA(XLOOKUP(A25,PAGOS!$A$2:$A$996,PAGOS!$T$2:$T$996,""""),""""),IFNA(XLOOKUP(A25,PAGOS!$A$2:$A$996,PAGOS!$W$2:$W$996,""""),""""),IFNA(XLOOKUP(A25,PAGOS!$A$2:$A$996,PAGOS!$Z$2:$Z$996,""""),"&"""""),IFNA(XLOOKUP(A25,PAGOS!$A$2:$A$996,PAGOS!$AC$2:$AC$996,""""),""""),IFNA(XLOOKUP(A25,PAGOS!$A$2:$A$996,PAGOS!$AF$2:$AF$996,""""),""""),IFNA(XLOOKUP(A25,PAGOS!$A$2:$A$996,PAGOS!$AI$2:$AI$996,""""),""""),IFNA(XLOOKUP(A25,PAGOS!$A$2:$A$996,PAGOS!$AL$2:$"&"AL$996,""""),"""")),IF(abonos>0,IFERROR(TEXTJOIN("" + "",TRUE,UNIQUE(FILTER('ABONOS MENSUALIDADES'!$E$5:$E$500,'ABONOS MENSUALIDADES'!$C$5:$C$500=A25,'ABONOS MENSUALIDADES'!$D$5:$D$500=mes))),""""),metodoDirecto)))"),"TRANSFERENCIA") -> TRANSFERENCIA | F25: {=IF(A25="","",LET(mes,DATE($E$2,MATCH($B$2,'ESTADO CONTABLE'!$A$5:$A$16,0),1),cobrarDesde,IFERROR(INDEX('BASE DE DATOSS'!I:I,ROW()-13),""),pausada,SUMPRODUCT((UPPER(TRIM('PAUSAS MENSUALIDADES'!$A$5:$A$500))=UPPER(TRIM(A25)))*('PAUSAS MENSUALIDADES'!$B$5:$B$500=mes)*(UPPER(TRIM('PAUSAS MENSUALIDADES'!$D$5:$D$500))="APLICAR"))>0,abonoActivo,SUMIFS('ABONOS MENSUALIDADES'!$F$5:$F$500,'ABONOS MENSUALIDADES'!$C$5:$C$500,A25,'ABONOS MENSUALIDADES'!$D$5:$D$500,mes,'ABONOS MENSUALIDADES'!$G$5:$G$500,"<>*CONSOLIDADO EN PAGOS*")>0,esperadaBruta,MAX(IFNA(VLOOKUP(B25,COSTOS!$A$3:$B$13,2,FALSE),0)-150,0),IF(AND(cobrarDesde<>"",mes<cobrarDesde),"AÚN NO INICIA",IF(pausada,"PAUSADA",IF(AND(abonoActivo,COUNTIFS('ABONOS MENSUALIDADES'!$C$5:$C$500,A25,'ABONOS MENSUALIDADES'!$D$5:$D$500,mes,'ABONOS MENSUALIDADES'!$G$5:$G$500,"*MENSUALIDAD LIQUIDADA*")=0),"ABONO",IF(N(D25)>=esperadaBruta,"COBRADA",IF(N(D25)>0,"ABONO","PENDIENTE")))))))} -> COBRADA | G25: {=IF(A25="","",IFERROR(INDEX('BASE DE DATOSS'!I:I,ROW()-13),""))} -> 46023
A26: {=IFERROR(INDEX('BASE DE DATOSS'!A:A,ROW()-13),"")} -> SOFIA HERMAYONIE AVILA GUERRERO | B26: {=IF(A26="","",LET(mes,DATE($E$2,MATCH($B$2,'ESTADO CONTABLE'!$A$5:$A$16,0),1),grupoActual,IFERROR(INDEX('BASE DE DATOSS'!C:C,ROW()-13),""),IF(AND(UPPER(TRIM(A26))="SOFIA HERMAYONIE AVILA GUERRERO",mes<DATE(2026,10,1)),"JR 2",grupoActual)))} -> ADULTS 1 | C26: {=IF(A26="","",LET(mes,DATE($E$2,MATCH($B$2,'ESTADO CONTABLE'!$A$5:$A$16,0),1),cobrarDesde,IFERROR(INDEX('BASE DE DATOSS'!I:I,ROW()-13),""),pausada,SUMPRODUCT((UPPER(TRIM('PAUSAS MENSUALIDADES'!$A$5:$A$500))=UPPER(TRIM(A26)))*('PAUSAS MENSUALIDADES'!$B$5:$B$500=mes)*(UPPER(TRIM('PAUSAS MENSUALIDADES'!$D$5:$D$500))="APLICAR"))>0,IF(OR(AND(cobrarDesde<>"",mes<cobrarDesde),pausada),0,MAX(IFNA(VLOOKUP(B26,COSTOS!$A$3:$B$13,2,FALSE),0)-150,0)/1.16)))} -> 991.37931 | D26: {=IF(A26="","",LET(mes,DATE($E$2,MATCH($B$2,'ESTADO CONTABLE'!$A$5:$A$16,0),1),abonos,SUMIFS('ABONOS MENSUALIDADES'!$F$5:$F$500,'ABONOS MENSUALIDADES'!$C$5:$C$500,A26,'ABONOS MENSUALIDADES'!$D$5:$D$500,mes),pago,CHOOSE(MATCH($B$2,'ESTADO CONTABLE'!$A$5:$A$16,0),IFNA(_xlfn.XLOOKUP(A26,PAGOS!$A$2:$A$996,PAGOS!$E$2:$E$996,""),""),IFNA(_xlfn.XLOOKUP(A26,PAGOS!$A$2:$A$996,PAGOS!$G$2:$G$996,""),""),IFNA(_xlfn.XLOOKUP(A26,PAGOS!$A$2:$A$996,PAGOS!$J$2:$J$996,""),""),IFNA(_xlfn.XLOOKUP(A26,PAGOS!$A$2:$A$996,PAGOS!$M$2:$M$996,""),""),IFNA(_xlfn.XLOOKUP(A26,PAGOS!$A$2:$A$996,PAGOS!$P$2:$P$996,""),""),IFNA(_xlfn.XLOOKUP(A26,PAGOS!$A$2:$A$996,PAGOS!$S$2:$S$996,""),""),IFNA(_xlfn.XLOOKUP(A26,PAGOS!$A$2:$A$996,PAGOS!$V$2:$V$996,""),""),IFNA(_xlfn.XLOOKUP(A26,PAGOS!$A$2:$A$996,PAGOS!$Y$2:$Y$996,""),""),IFNA(_xlfn.XLOOKUP(A26,PAGOS!$A$2:$A$996,PAGOS!$AB$2:$AB$996,""),""),IFNA(_xlfn.XLOOKUP(A26,PAGOS!$A$2:$A$996,PAGOS!$AE$2:$AE$996,""),""),IFNA(_xlfn.XLOOKUP(A26,PAGOS!$A$2:$A$996,PAGOS!$AH$2:$AH$996,""),""),IFNA(_xlfn.XLOOKUP(A26,PAGOS!$A$2:$A$996,PAGOS!$AK$2:$AK$996,""),"")),IF(abonos>0,abonos,pago)))} | E26: =IFERROR(__xludf.DUMMYFUNCTION("IF(A26="""","""",LET(mes,DATE($E$2,MATCH($B$2,'ESTADO CONTABLE'!$A$5:$A$16,0),1),abonos,SUMIFS('ABONOS MENSUALIDADES'!$F$5:$F$500,'ABONOS MENSUALIDADES'!$C$5:$C$500,A26,'ABONOS MENSUALIDADES'!$D$5:$D$500,mes),metodoDirecto,CHOOSE(MATCH($B$2,'ESTADO CONTAB"&"LE'!$A$5:$A$16,0),IF(ISNUMBER(D26),""POR CLASIFICAR"",""""),IFNA(XLOOKUP(A26,PAGOS!$A$2:$A$996,PAGOS!$H$2:$H$996,""""),""""),IFNA(XLOOKUP(A26,PAGOS!$A$2:$A$996,PAGOS!$K$2:$K$996,""""),""""),IFNA(XLOOKUP(A26,PAGOS!$A$2:$A$996,PAGOS!$N$2:$N$996,""""),""""),"&"IFNA(XLOOKUP(A26,PAGOS!$A$2:$A$996,PAGOS!$Q$2:$Q$996,""""),""""),IFNA(XLOOKUP(A26,PAGOS!$A$2:$A$996,PAGOS!$T$2:$T$996,""""),""""),IFNA(XLOOKUP(A26,PAGOS!$A$2:$A$996,PAGOS!$W$2:$W$996,""""),""""),IFNA(XLOOKUP(A26,PAGOS!$A$2:$A$996,PAGOS!$Z$2:$Z$996,""""),"&"""""),IFNA(XLOOKUP(A26,PAGOS!$A$2:$A$996,PAGOS!$AC$2:$AC$996,""""),""""),IFNA(XLOOKUP(A26,PAGOS!$A$2:$A$996,PAGOS!$AF$2:$AF$996,""""),""""),IFNA(XLOOKUP(A26,PAGOS!$A$2:$A$996,PAGOS!$AI$2:$AI$996,""""),""""),IFNA(XLOOKUP(A26,PAGOS!$A$2:$A$996,PAGOS!$AL$2:$"&"AL$996,""""),"""")),IF(abonos>0,IFERROR(TEXTJOIN("" + "",TRUE,UNIQUE(FILTER('ABONOS MENSUALIDADES'!$E$5:$E$500,'ABONOS MENSUALIDADES'!$C$5:$C$500=A26,'ABONOS MENSUALIDADES'!$D$5:$D$500=mes))),""""),metodoDirecto)))"),"") | F26: {=IF(A26="","",LET(mes,DATE($E$2,MATCH($B$2,'ESTADO CONTABLE'!$A$5:$A$16,0),1),cobrarDesde,IFERROR(INDEX('BASE DE DATOSS'!I:I,ROW()-13),""),pausada,SUMPRODUCT((UPPER(TRIM('PAUSAS MENSUALIDADES'!$A$5:$A$500))=UPPER(TRIM(A26)))*('PAUSAS MENSUALIDADES'!$B$5:$B$500=mes)*(UPPER(TRIM('PAUSAS MENSUALIDADES'!$D$5:$D$500))="APLICAR"))>0,abonoActivo,SUMIFS('ABONOS MENSUALIDADES'!$F$5:$F$500,'ABONOS MENSUALIDADES'!$C$5:$C$500,A26,'ABONOS MENSUALIDADES'!$D$5:$D$500,mes,'ABONOS MENSUALIDADES'!$G$5:$G$500,"<>*CONSOLIDADO EN PAGOS*")>0,esperadaBruta,MAX(IFNA(VLOOKUP(B26,COSTOS!$A$3:$B$13,2,FALSE),0)-150,0),IF(AND(cobrarDesde<>"",mes<cobrarDesde),"AÚN NO INICIA",IF(pausada,"PAUSADA",IF(AND(abonoActivo,COUNTIFS('ABONOS MENSUALIDADES'!$C$5:$C$500,A26,'ABONOS MENSUALIDADES'!$D$5:$D$500,mes,'ABONOS MENSUALIDADES'!$G$5:$G$500,"*MENSUALIDAD LIQUIDADA*")=0),"ABONO",IF(N(D26)>=esperadaBruta,"COBRADA",IF(N(D26)>0,"ABONO","PENDIENTE")))))))} -> PENDIENTE | G26: {=IF(A26="","",IFERROR(INDEX('BASE DE DATOSS'!I:I,ROW()-13),""))} -> 46023
A27: {=IFERROR(INDEX('BASE DE DATOSS'!A:A,ROW()-13),"")} -> VALENTINA GÓMEZ NEGRETE | B27: {=IF(A27="","",IFERROR(INDEX('BASE DE DATOSS'!C:C,ROW()-13),""))} -> JR 2 | C27: {=IF(A27="","",LET(mes,DATE($E$2,MATCH($B$2,'ESTADO CONTABLE'!$A$5:$A$16,0),1),cobrarDesde,IFERROR(INDEX('BASE DE DATOSS'!I:I,ROW()-13),""),pausada,SUMPRODUCT((UPPER(TRIM('PAUSAS MENSUALIDADES'!$A$5:$A$500))=UPPER(TRIM(A27)))*('PAUSAS MENSUALIDADES'!$B$5:$B$500=mes)*(UPPER(TRIM('PAUSAS MENSUALIDADES'!$D$5:$D$500))="APLICAR"))>0,IF(OR(AND(cobrarDesde<>"",mes<cobrarDesde),pausada),0,MAX(IFNA(VLOOKUP(B27,COSTOS!$A$3:$B$13,2,FALSE),0)-150,0)/1.16)))} -> 689.65517 | D27: {=IF(A27="","",LET(mes,DATE($E$2,MATCH($B$2,'ESTADO CONTABLE'!$A$5:$A$16,0),1),abonos,SUMIFS('ABONOS MENSUALIDADES'!$F$5:$F$500,'ABONOS MENSUALIDADES'!$C$5:$C$500,A27,'ABONOS MENSUALIDADES'!$D$5:$D$500,mes),pago,CHOOSE(MATCH($B$2,'ESTADO CONTABLE'!$A$5:$A$16,0),IFNA(_xlfn.XLOOKUP(A27,PAGOS!$A$2:$A$996,PAGOS!$E$2:$E$996,""),""),IFNA(_xlfn.XLOOKUP(A27,PAGOS!$A$2:$A$996,PAGOS!$G$2:$G$996,""),""),IFNA(_xlfn.XLOOKUP(A27,PAGOS!$A$2:$A$996,PAGOS!$J$2:$J$996,""),""),IFNA(_xlfn.XLOOKUP(A27,PAGOS!$A$2:$A$996,PAGOS!$M$2:$M$996,""),""),IFNA(_xlfn.XLOOKUP(A27,PAGOS!$A$2:$A$996,PAGOS!$P$2:$P$996,""),""),IFNA(_xlfn.XLOOKUP(A27,PAGOS!$A$2:$A$996,PAGOS!$S$2:$S$996,""),""),IFNA(_xlfn.XLOOKUP(A27,PAGOS!$A$2:$A$996,PAGOS!$V$2:$V$996,""),""),IFNA(_xlfn.XLOOKUP(A27,PAGOS!$A$2:$A$996,PAGOS!$Y$2:$Y$996,""),""),IFNA(_xlfn.XLOOKUP(A27,PAGOS!$A$2:$A$996,PAGOS!$AB$2:$AB$996,""),""),IFNA(_xlfn.XLOOKUP(A27,PAGOS!$A$2:$A$996,PAGOS!$AE$2:$AE$996,""),""),IFNA(_xlfn.XLOOKUP(A27,PAGOS!$A$2:$A$996,PAGOS!$AH$2:$AH$996,""),""),IFNA(_xlfn.XLOOKUP(A27,PAGOS!$A$2:$A$996,PAGOS!$AK$2:$AK$996,""),"")),IF(abonos>0,abonos,pago)))} -> 800 | E27: =IFERROR(__xludf.DUMMYFUNCTION("IF(A27="""","""",LET(mes,DATE($E$2,MATCH($B$2,'ESTADO CONTABLE'!$A$5:$A$16,0),1),abonos,SUMIFS('ABONOS MENSUALIDADES'!$F$5:$F$500,'ABONOS MENSUALIDADES'!$C$5:$C$500,A27,'ABONOS MENSUALIDADES'!$D$5:$D$500,mes),metodoDirecto,CHOOSE(MATCH($B$2,'ESTADO CONTAB"&"LE'!$A$5:$A$16,0),IF(ISNUMBER(D27),""POR CLASIFICAR"",""""),IFNA(XLOOKUP(A27,PAGOS!$A$2:$A$996,PAGOS!$H$2:$H$996,""""),""""),IFNA(XLOOKUP(A27,PAGOS!$A$2:$A$996,PAGOS!$K$2:$K$996,""""),""""),IFNA(XLOOKUP(A27,PAGOS!$A$2:$A$996,PAGOS!$N$2:$N$996,""""),""""),"&"IFNA(XLOOKUP(A27,PAGOS!$A$2:$A$996,PAGOS!$Q$2:$Q$996,""""),""""),IFNA(XLOOKUP(A27,PAGOS!$A$2:$A$996,PAGOS!$T$2:$T$996,""""),""""),IFNA(XLOOKUP(A27,PAGOS!$A$2:$A$996,PAGOS!$W$2:$W$996,""""),""""),IFNA(XLOOKUP(A27,PAGOS!$A$2:$A$996,PAGOS!$Z$2:$Z$996,""""),"&"""""),IFNA(XLOOKUP(A27,PAGOS!$A$2:$A$996,PAGOS!$AC$2:$AC$996,""""),""""),IFNA(XLOOKUP(A27,PAGOS!$A$2:$A$996,PAGOS!$AF$2:$AF$996,""""),""""),IFNA(XLOOKUP(A27,PAGOS!$A$2:$A$996,PAGOS!$AI$2:$AI$996,""""),""""),IFNA(XLOOKUP(A27,PAGOS!$A$2:$A$996,PAGOS!$AL$2:$"&"AL$996,""""),"""")),IF(abonos>0,IFERROR(TEXTJOIN("" + "",TRUE,UNIQUE(FILTER('ABONOS MENSUALIDADES'!$E$5:$E$500,'ABONOS MENSUALIDADES'!$C$5:$C$500=A27,'ABONOS MENSUALIDADES'!$D$5:$D$500=mes))),""""),metodoDirecto)))"),"EFECTIVO") -> EFECTIVO | F27: {=IF(A27="","",LET(mes,DATE($E$2,MATCH($B$2,'ESTADO CONTABLE'!$A$5:$A$16,0),1),cobrarDesde,IFERROR(INDEX('BASE DE DATOSS'!I:I,ROW()-13),""),pausada,SUMPRODUCT((UPPER(TRIM('PAUSAS MENSUALIDADES'!$A$5:$A$500))=UPPER(TRIM(A27)))*('PAUSAS MENSUALIDADES'!$B$5:$B$500=mes)*(UPPER(TRIM('PAUSAS MENSUALIDADES'!$D$5:$D$500))="APLICAR"))>0,abonoActivo,SUMIFS('ABONOS MENSUALIDADES'!$F$5:$F$500,'ABONOS MENSUALIDADES'!$C$5:$C$500,A27,'ABONOS MENSUALIDADES'!$D$5:$D$500,mes,'ABONOS MENSUALIDADES'!$G$5:$G$500,"<>*CONSOLIDADO EN PAGOS*")>0,esperadaBruta,MAX(IFNA(VLOOKUP(B27,COSTOS!$A$3:$B$13,2,FALSE),0)-150,0),IF(AND(cobrarDesde<>"",mes<cobrarDesde),"AÚN NO INICIA",IF(pausada,"PAUSADA",IF(AND(abonoActivo,COUNTIFS('ABONOS MENSUALIDADES'!$C$5:$C$500,A27,'ABONOS MENSUALIDADES'!$D$5:$D$500,mes,'ABONOS MENSUALIDADES'!$G$5:$G$500,"*MENSUALIDAD LIQUIDADA*")=0),"ABONO",IF(N(D27)>=esperadaBruta,"COBRADA",IF(N(D27)>0,"ABONO","PENDIENTE")))))))} -> COBRADA | G27: {=IF(A27="","",IFERROR(INDEX('BASE DE DATOSS'!I:I,ROW()-13),""))} -> 46023
A28: {=IFERROR(INDEX('BASE DE DATOSS'!A:A,ROW()-13),"")} -> DANNA VALERIA DE LA CRUZ HEREDIA | B28: {=IF(A28="","",IFERROR(INDEX('BASE DE DATOSS'!C:C,ROW()-13),""))} -> KIDS 3 | C28: {=IF(A28="","",LET(mes,DATE($E$2,MATCH($B$2,'ESTADO CONTABLE'!$A$5:$A$16,0),1),cobrarDesde,IFERROR(INDEX('BASE DE DATOSS'!I:I,ROW()-13),""),pausada,SUMPRODUCT((UPPER(TRIM('PAUSAS MENSUALIDADES'!$A$5:$A$500))=UPPER(TRIM(A28)))*('PAUSAS MENSUALIDADES'!$B$5:$B$500=mes)*(UPPER(TRIM('PAUSAS MENSUALIDADES'!$D$5:$D$500))="APLICAR"))>0,IF(OR(AND(cobrarDesde<>"",mes<cobrarDesde),pausada),0,MAX(IFNA(VLOOKUP(B28,COSTOS!$A$3:$B$13,2,FALSE),0)-150,0)/1.16)))} -> 689.65517 | D28: {=IF(A28="","",LET(mes,DATE($E$2,MATCH($B$2,'ESTADO CONTABLE'!$A$5:$A$16,0),1),abonos,SUMIFS('ABONOS MENSUALIDADES'!$F$5:$F$500,'ABONOS MENSUALIDADES'!$C$5:$C$500,A28,'ABONOS MENSUALIDADES'!$D$5:$D$500,mes),pago,CHOOSE(MATCH($B$2,'ESTADO CONTABLE'!$A$5:$A$16,0),IFNA(_xlfn.XLOOKUP(A28,PAGOS!$A$2:$A$996,PAGOS!$E$2:$E$996,""),""),IFNA(_xlfn.XLOOKUP(A28,PAGOS!$A$2:$A$996,PAGOS!$G$2:$G$996,""),""),IFNA(_xlfn.XLOOKUP(A28,PAGOS!$A$2:$A$996,PAGOS!$J$2:$J$996,""),""),IFNA(_xlfn.XLOOKUP(A28,PAGOS!$A$2:$A$996,PAGOS!$M$2:$M$996,""),""),IFNA(_xlfn.XLOOKUP(A28,PAGOS!$A$2:$A$996,PAGOS!$P$2:$P$996,""),""),IFNA(_xlfn.XLOOKUP(A28,PAGOS!$A$2:$A$996,PAGOS!$S$2:$S$996,""),""),IFNA(_xlfn.XLOOKUP(A28,PAGOS!$A$2:$A$996,PAGOS!$V$2:$V$996,""),""),IFNA(_xlfn.XLOOKUP(A28,PAGOS!$A$2:$A$996,PAGOS!$Y$2:$Y$996,""),""),IFNA(_xlfn.XLOOKUP(A28,PAGOS!$A$2:$A$996,PAGOS!$AB$2:$AB$996,""),""),IFNA(_xlfn.XLOOKUP(A28,PAGOS!$A$2:$A$996,PAGOS!$AE$2:$AE$996,""),""),IFNA(_xlfn.XLOOKUP(A28,PAGOS!$A$2:$A$996,PAGOS!$AH$2:$AH$996,""),""),IFNA(_xlfn.XLOOKUP(A28,PAGOS!$A$2:$A$996,PAGOS!$AK$2:$AK$996,""),"")),IF(abonos>0,abonos,pago)))} -> 800 | E28: =IFERROR(__xludf.DUMMYFUNCTION("IF(A28="""","""",LET(mes,DATE($E$2,MATCH($B$2,'ESTADO CONTABLE'!$A$5:$A$16,0),1),abonos,SUMIFS('ABONOS MENSUALIDADES'!$F$5:$F$500,'ABONOS MENSUALIDADES'!$C$5:$C$500,A28,'ABONOS MENSUALIDADES'!$D$5:$D$500,mes),metodoDirecto,CHOOSE(MATCH($B$2,'ESTADO CONTAB"&"LE'!$A$5:$A$16,0),IF(ISNUMBER(D28),""POR CLASIFICAR"",""""),IFNA(XLOOKUP(A28,PAGOS!$A$2:$A$996,PAGOS!$H$2:$H$996,""""),""""),IFNA(XLOOKUP(A28,PAGOS!$A$2:$A$996,PAGOS!$K$2:$K$996,""""),""""),IFNA(XLOOKUP(A28,PAGOS!$A$2:$A$996,PAGOS!$N$2:$N$996,""""),""""),"&"IFNA(XLOOKUP(A28,PAGOS!$A$2:$A$996,PAGOS!$Q$2:$Q$996,""""),""""),IFNA(XLOOKUP(A28,PAGOS!$A$2:$A$996,PAGOS!$T$2:$T$996,""""),""""),IFNA(XLOOKUP(A28,PAGOS!$A$2:$A$996,PAGOS!$W$2:$W$996,""""),""""),IFNA(XLOOKUP(A28,PAGOS!$A$2:$A$996,PAGOS!$Z$2:$Z$996,""""),"&"""""),IFNA(XLOOKUP(A28,PAGOS!$A$2:$A$996,PAGOS!$AC$2:$AC$996,""""),""""),IFNA(XLOOKUP(A28,PAGOS!$A$2:$A$996,PAGOS!$AF$2:$AF$996,""""),""""),IFNA(XLOOKUP(A28,PAGOS!$A$2:$A$996,PAGOS!$AI$2:$AI$996,""""),""""),IFNA(XLOOKUP(A28,PAGOS!$A$2:$A$996,PAGOS!$AL$2:$"&"AL$996,""""),"""")),IF(abonos>0,IFERROR(TEXTJOIN("" + "",TRUE,UNIQUE(FILTER('ABONOS MENSUALIDADES'!$E$5:$E$500,'ABONOS MENSUALIDADES'!$C$5:$C$500=A28,'ABONOS MENSUALIDADES'!$D$5:$D$500=mes))),""""),metodoDirecto)))"),"EFECTIVO") -> EFECTIVO | F28: {=IF(A28="","",LET(mes,DATE($E$2,MATCH($B$2,'ESTADO CONTABLE'!$A$5:$A$16,0),1),cobrarDesde,IFERROR(INDEX('BASE DE DATOSS'!I:I,ROW()-13),""),pausada,SUMPRODUCT((UPPER(TRIM('PAUSAS MENSUALIDADES'!$A$5:$A$500))=UPPER(TRIM(A28)))*('PAUSAS MENSUALIDADES'!$B$5:$B$500=mes)*(UPPER(TRIM('PAUSAS MENSUALIDADES'!$D$5:$D$500))="APLICAR"))>0,abonoActivo,SUMIFS('ABONOS MENSUALIDADES'!$F$5:$F$500,'ABONOS MENSUALIDADES'!$C$5:$C$500,A28,'ABONOS MENSUALIDADES'!$D$5:$D$500,mes,'ABONOS MENSUALIDADES'!$G$5:$G$500,"<>*CONSOLIDADO EN PAGOS*")>0,esperadaBruta,MAX(IFNA(VLOOKUP(B28,COSTOS!$A$3:$B$13,2,FALSE),0)-150,0),IF(AND(cobrarDesde<>"",mes<cobrarDesde),"AÚN NO INICIA",IF(pausada,"PAUSADA",IF(AND(abonoActivo,COUNTIFS('ABONOS MENSUALIDADES'!$C$5:$C$500,A28,'ABONOS MENSUALIDADES'!$D$5:$D$500,mes,'ABONOS MENSUALIDADES'!$G$5:$G$500,"*MENSUALIDAD LIQUIDADA*")=0),"ABONO",IF(N(D28)>=esperadaBruta,"COBRADA",IF(N(D28)>0,"ABONO","PENDIENTE")))))))} -> COBRADA | G28: {=IF(A28="","",IFERROR(INDEX('BASE DE DATOSS'!I:I,ROW()-13),""))} -> 46023
A29: {=IFERROR(INDEX('BASE DE DATOSS'!A:A,ROW()-13),"")} -> VIVIANA MONTES CÁRDENAS | B29: {=IF(A29="","",IFERROR(INDEX('BASE DE DATOSS'!C:C,ROW()-13),""))} -> ADULTS 1 | C29: {=IF(A29="","",LET(mes,DATE($E$2,MATCH($B$2,'ESTADO CONTABLE'!$A$5:$A$16,0),1),cobrarDesde,IFERROR(INDEX('BASE DE DATOSS'!I:I,ROW()-13),""),pausada,SUMPRODUCT((UPPER(TRIM('PAUSAS MENSUALIDADES'!$A$5:$A$500))=UPPER(TRIM(A29)))*('PAUSAS MENSUALIDADES'!$B$5:$B$500=mes)*(UPPER(TRIM('PAUSAS MENSUALIDADES'!$D$5:$D$500))="APLICAR"))>0,IF(OR(AND(cobrarDesde<>"",mes<cobrarDesde),pausada),0,MAX(IFNA(VLOOKUP(B29,COSTOS!$A$3:$B$13,2,FALSE),0)-150,0)/1.16)))} -> 991.37931 | D29: {=IF(A29="","",LET(mes,DATE($E$2,MATCH($B$2,'ESTADO CONTABLE'!$A$5:$A$16,0),1),abonos,SUMIFS('ABONOS MENSUALIDADES'!$F$5:$F$500,'ABONOS MENSUALIDADES'!$C$5:$C$500,A29,'ABONOS MENSUALIDADES'!$D$5:$D$500,mes),pago,CHOOSE(MATCH($B$2,'ESTADO CONTABLE'!$A$5:$A$16,0),IFNA(_xlfn.XLOOKUP(A29,PAGOS!$A$2:$A$996,PAGOS!$E$2:$E$996,""),""),IFNA(_xlfn.XLOOKUP(A29,PAGOS!$A$2:$A$996,PAGOS!$G$2:$G$996,""),""),IFNA(_xlfn.XLOOKUP(A29,PAGOS!$A$2:$A$996,PAGOS!$J$2:$J$996,""),""),IFNA(_xlfn.XLOOKUP(A29,PAGOS!$A$2:$A$996,PAGOS!$M$2:$M$996,""),""),IFNA(_xlfn.XLOOKUP(A29,PAGOS!$A$2:$A$996,PAGOS!$P$2:$P$996,""),""),IFNA(_xlfn.XLOOKUP(A29,PAGOS!$A$2:$A$996,PAGOS!$S$2:$S$996,""),""),IFNA(_xlfn.XLOOKUP(A29,PAGOS!$A$2:$A$996,PAGOS!$V$2:$V$996,""),""),IFNA(_xlfn.XLOOKUP(A29,PAGOS!$A$2:$A$996,PAGOS!$Y$2:$Y$996,""),""),IFNA(_xlfn.XLOOKUP(A29,PAGOS!$A$2:$A$996,PAGOS!$AB$2:$AB$996,""),""),IFNA(_xlfn.XLOOKUP(A29,PAGOS!$A$2:$A$996,PAGOS!$AE$2:$AE$996,""),""),IFNA(_xlfn.XLOOKUP(A29,PAGOS!$A$2:$A$996,PAGOS!$AH$2:$AH$996,""),""),IFNA(_xlfn.XLOOKUP(A29,PAGOS!$A$2:$A$996,PAGOS!$AK$2:$AK$996,""),"")),IF(abonos>0,abonos,pago)))} -> 1300 | E29: =IFERROR(__xludf.DUMMYFUNCTION("IF(A29="""","""",LET(mes,DATE($E$2,MATCH($B$2,'ESTADO CONTABLE'!$A$5:$A$16,0),1),abonos,SUMIFS('ABONOS MENSUALIDADES'!$F$5:$F$500,'ABONOS MENSUALIDADES'!$C$5:$C$500,A29,'ABONOS MENSUALIDADES'!$D$5:$D$500,mes),metodoDirecto,CHOOSE(MATCH($B$2,'ESTADO CONTAB"&"LE'!$A$5:$A$16,0),IF(ISNUMBER(D29),""POR CLASIFICAR"",""""),IFNA(XLOOKUP(A29,PAGOS!$A$2:$A$996,PAGOS!$H$2:$H$996,""""),""""),IFNA(XLOOKUP(A29,PAGOS!$A$2:$A$996,PAGOS!$K$2:$K$996,""""),""""),IFNA(XLOOKUP(A29,PAGOS!$A$2:$A$996,PAGOS!$N$2:$N$996,""""),""""),"&"IFNA(XLOOKUP(A29,PAGOS!$A$2:$A$996,PAGOS!$Q$2:$Q$996,""""),""""),IFNA(XLOOKUP(A29,PAGOS!$A$2:$A$996,PAGOS!$T$2:$T$996,""""),""""),IFNA(XLOOKUP(A29,PAGOS!$A$2:$A$996,PAGOS!$W$2:$W$996,""""),""""),IFNA(XLOOKUP(A29,PAGOS!$A$2:$A$996,PAGOS!$Z$2:$Z$996,""""),"&"""""),IFNA(XLOOKUP(A29,PAGOS!$A$2:$A$996,PAGOS!$AC$2:$AC$996,""""),""""),IFNA(XLOOKUP(A29,PAGOS!$A$2:$A$996,PAGOS!$AF$2:$AF$996,""""),""""),IFNA(XLOOKUP(A29,PAGOS!$A$2:$A$996,PAGOS!$AI$2:$AI$996,""""),""""),IFNA(XLOOKUP(A29,PAGOS!$A$2:$A$996,PAGOS!$AL$2:$"&"AL$996,""""),"""")),IF(abonos>0,IFERROR(TEXTJOIN("" + "",TRUE,UNIQUE(FILTER('ABONOS MENSUALIDADES'!$E$5:$E$500,'ABONOS MENSUALIDADES'!$C$5:$C$500=A29,'ABONOS MENSUALIDADES'!$D$5:$D$500=mes))),""""),metodoDirecto)))"),"TERMINAL") -> TERMINAL | F29: {=IF(A29="","",LET(mes,DATE($E$2,MATCH($B$2,'ESTADO CONTABLE'!$A$5:$A$16,0),1),cobrarDesde,IFERROR(INDEX('BASE DE DATOSS'!I:I,ROW()-13),""),pausada,SUMPRODUCT((UPPER(TRIM('PAUSAS MENSUALIDADES'!$A$5:$A$500))=UPPER(TRIM(A29)))*('PAUSAS MENSUALIDADES'!$B$5:$B$500=mes)*(UPPER(TRIM('PAUSAS MENSUALIDADES'!$D$5:$D$500))="APLICAR"))>0,abonoActivo,SUMIFS('ABONOS MENSUALIDADES'!$F$5:$F$500,'ABONOS MENSUALIDADES'!$C$5:$C$500,A29,'ABONOS MENSUALIDADES'!$D$5:$D$500,mes,'ABONOS MENSUALIDADES'!$G$5:$G$500,"<>*CONSOLIDADO EN PAGOS*")>0,esperadaBruta,MAX(IFNA(VLOOKUP(B29,COSTOS!$A$3:$B$13,2,FALSE),0)-150,0),IF(AND(cobrarDesde<>"",mes<cobrarDesde),"AÚN NO INICIA",IF(pausada,"PAUSADA",IF(AND(abonoActivo,COUNTIFS('ABONOS MENSUALIDADES'!$C$5:$C$500,A29,'ABONOS MENSUALIDADES'!$D$5:$D$500,mes,'ABONOS MENSUALIDADES'!$G$5:$G$500,"*MENSUALIDAD LIQUIDADA*")=0),"ABONO",IF(N(D29)>=esperadaBruta,"COBRADA",IF(N(D29)>0,"ABONO","PENDIENTE")))))))} -> COBRADA | G29: {=IF(A29="","",IFERROR(INDEX('BASE DE DATOSS'!I:I,ROW()-13),""))} -> 46023
A30: {=IFERROR(INDEX('BASE DE DATOSS'!A:A,ROW()-13),"")} -> GRETA ATENEA ALMANZA RAMOS | B30: {=IF(A30="","",IFERROR(INDEX('BASE DE DATOSS'!C:C,ROW()-13),""))} -> KIDS 3 | C30: {=IF(A30="","",LET(mes,DATE($E$2,MATCH($B$2,'ESTADO CONTABLE'!$A$5:$A$16,0),1),cobrarDesde,IFERROR(INDEX('BASE DE DATOSS'!I:I,ROW()-13),""),pausada,SUMPRODUCT((UPPER(TRIM('PAUSAS MENSUALIDADES'!$A$5:$A$500))=UPPER(TRIM(A30)))*('PAUSAS MENSUALIDADES'!$B$5:$B$500=mes)*(UPPER(TRIM('PAUSAS MENSUALIDADES'!$D$5:$D$500))="APLICAR"))>0,IF(OR(AND(cobrarDesde<>"",mes<cobrarDesde),pausada),0,MAX(IFNA(VLOOKUP(B30,COSTOS!$A$3:$B$13,2,FALSE),0)-150,0)/1.16)))} -> 689.65517 | D30: {=IF(A30="","",LET(mes,DATE($E$2,MATCH($B$2,'ESTADO CONTABLE'!$A$5:$A$16,0),1),abonos,SUMIFS('ABONOS MENSUALIDADES'!$F$5:$F$500,'ABONOS MENSUALIDADES'!$C$5:$C$500,A30,'ABONOS MENSUALIDADES'!$D$5:$D$500,mes),pago,CHOOSE(MATCH($B$2,'ESTADO CONTABLE'!$A$5:$A$16,0),IFNA(_xlfn.XLOOKUP(A30,PAGOS!$A$2:$A$996,PAGOS!$E$2:$E$996,""),""),IFNA(_xlfn.XLOOKUP(A30,PAGOS!$A$2:$A$996,PAGOS!$G$2:$G$996,""),""),IFNA(_xlfn.XLOOKUP(A30,PAGOS!$A$2:$A$996,PAGOS!$J$2:$J$996,""),""),IFNA(_xlfn.XLOOKUP(A30,PAGOS!$A$2:$A$996,PAGOS!$M$2:$M$996,""),""),IFNA(_xlfn.XLOOKUP(A30,PAGOS!$A$2:$A$996,PAGOS!$P$2:$P$996,""),""),IFNA(_xlfn.XLOOKUP(A30,PAGOS!$A$2:$A$996,PAGOS!$S$2:$S$996,""),""),IFNA(_xlfn.XLOOKUP(A30,PAGOS!$A$2:$A$996,PAGOS!$V$2:$V$996,""),""),IFNA(_xlfn.XLOOKUP(A30,PAGOS!$A$2:$A$996,PAGOS!$Y$2:$Y$996,""),""),IFNA(_xlfn.XLOOKUP(A30,PAGOS!$A$2:$A$996,PAGOS!$AB$2:$AB$996,""),""),IFNA(_xlfn.XLOOKUP(A30,PAGOS!$A$2:$A$996,PAGOS!$AE$2:$AE$996,""),""),IFNA(_xlfn.XLOOKUP(A30,PAGOS!$A$2:$A$996,PAGOS!$AH$2:$AH$996,""),""),IFNA(_xlfn.XLOOKUP(A30,PAGOS!$A$2:$A$996,PAGOS!$AK$2:$AK$996,""),"")),IF(abonos>0,abonos,pago)))} -> 800 | E30: =IFERROR(__xludf.DUMMYFUNCTION("IF(A30="""","""",LET(mes,DATE($E$2,MATCH($B$2,'ESTADO CONTABLE'!$A$5:$A$16,0),1),abonos,SUMIFS('ABONOS MENSUALIDADES'!$F$5:$F$500,'ABONOS MENSUALIDADES'!$C$5:$C$500,A30,'ABONOS MENSUALIDADES'!$D$5:$D$500,mes),metodoDirecto,CHOOSE(MATCH($B$2,'ESTADO CONTAB"&"LE'!$A$5:$A$16,0),IF(ISNUMBER(D30),""POR CLASIFICAR"",""""),IFNA(XLOOKUP(A30,PAGOS!$A$2:$A$996,PAGOS!$H$2:$H$996,""""),""""),IFNA(XLOOKUP(A30,PAGOS!$A$2:$A$996,PAGOS!$K$2:$K$996,""""),""""),IFNA(XLOOKUP(A30,PAGOS!$A$2:$A$996,PAGOS!$N$2:$N$996,""""),""""),"&"IFNA(XLOOKUP(A30,PAGOS!$A$2:$A$996,PAGOS!$Q$2:$Q$996,""""),""""),IFNA(XLOOKUP(A30,PAGOS!$A$2:$A$996,PAGOS!$T$2:$T$996,""""),""""),IFNA(XLOOKUP(A30,PAGOS!$A$2:$A$996,PAGOS!$W$2:$W$996,""""),""""),IFNA(XLOOKUP(A30,PAGOS!$A$2:$A$996,PAGOS!$Z$2:$Z$996,""""),"&"""""),IFNA(XLOOKUP(A30,PAGOS!$A$2:$A$996,PAGOS!$AC$2:$AC$996,""""),""""),IFNA(XLOOKUP(A30,PAGOS!$A$2:$A$996,PAGOS!$AF$2:$AF$996,""""),""""),IFNA(XLOOKUP(A30,PAGOS!$A$2:$A$996,PAGOS!$AI$2:$AI$996,""""),""""),IFNA(XLOOKUP(A30,PAGOS!$A$2:$A$996,PAGOS!$AL$2:$"&"AL$996,""""),"""")),IF(abonos>0,IFERROR(TEXTJOIN("" + "",TRUE,UNIQUE(FILTER('ABONOS MENSUALIDADES'!$E$5:$E$500,'ABONOS MENSUALIDADES'!$C$5:$C$500=A30,'ABONOS MENSUALIDADES'!$D$5:$D$500=mes))),""""),metodoDirecto)))"),"TRANSFERENCIA") -> TRANSFERENCIA | F30: {=IF(A30="","",LET(mes,DATE($E$2,MATCH($B$2,'ESTADO CONTABLE'!$A$5:$A$16,0),1),cobrarDesde,IFERROR(INDEX('BASE DE DATOSS'!I:I,ROW()-13),""),pausada,SUMPRODUCT((UPPER(TRIM('PAUSAS MENSUALIDADES'!$A$5:$A$500))=UPPER(TRIM(A30)))*('PAUSAS MENSUALIDADES'!$B$5:$B$500=mes)*(UPPER(TRIM('PAUSAS MENSUALIDADES'!$D$5:$D$500))="APLICAR"))>0,abonoActivo,SUMIFS('ABONOS MENSUALIDADES'!$F$5:$F$500,'ABONOS MENSUALIDADES'!$C$5:$C$500,A30,'ABONOS MENSUALIDADES'!$D$5:$D$500,mes,'ABONOS MENSUALIDADES'!$G$5:$G$500,"<>*CONSOLIDADO EN PAGOS*")>0,esperadaBruta,MAX(IFNA(VLOOKUP(B30,COSTOS!$A$3:$B$13,2,FALSE),0)-150,0),IF(AND(cobrarDesde<>"",mes<cobrarDesde),"AÚN NO INICIA",IF(pausada,"PAUSADA",IF(AND(abonoActivo,COUNTIFS('ABONOS MENSUALIDADES'!$C$5:$C$500,A30,'ABONOS MENSUALIDADES'!$D$5:$D$500,mes,'ABONOS MENSUALIDADES'!$G$5:$G$500,"*MENSUALIDAD LIQUIDADA*")=0),"ABONO",IF(N(D30)>=esperadaBruta,"COBRADA",IF(N(D30)>0,"ABONO","PENDIENTE")))))))} -> ABONO | G30: {=IF(A30="","",IFERROR(INDEX('BASE DE DATOSS'!I:I,ROW()-13),""))} -> 46023
A31: {=IFERROR(INDEX('BASE DE DATOSS'!A:A,ROW()-13),"")} -> ARMIDA GABRIELA DE LA CRUZ ALCALA | B31: {=IF(A31="","",IFERROR(INDEX('BASE DE DATOSS'!C:C,ROW()-13),""))} -> SABATINO | C31: {=IF(A31="","",LET(mes,DATE($E$2,MATCH($B$2,'ESTADO CONTABLE'!$A$5:$A$16,0),1),cobrarDesde,IFERROR(INDEX('BASE DE DATOSS'!I:I,ROW()-13),""),pausada,SUMPRODUCT((UPPER(TRIM('PAUSAS MENSUALIDADES'!$A$5:$A$500))=UPPER(TRIM(A31)))*('PAUSAS MENSUALIDADES'!$B$5:$B$500=mes)*(UPPER(TRIM('PAUSAS MENSUALIDADES'!$D$5:$D$500))="APLICAR"))>0,IF(OR(AND(cobrarDesde<>"",mes<cobrarDesde),pausada),0,MAX(IFNA(VLOOKUP(B31,COSTOS!$A$3:$B$13,2,FALSE),0)-150,0)/1.16)))} -> 474.13793 | D31: {=IF(A31="","",LET(mes,DATE($E$2,MATCH($B$2,'ESTADO CONTABLE'!$A$5:$A$16,0),1),abonos,SUMIFS('ABONOS MENSUALIDADES'!$F$5:$F$500,'ABONOS MENSUALIDADES'!$C$5:$C$500,A31,'ABONOS MENSUALIDADES'!$D$5:$D$500,mes),pago,CHOOSE(MATCH($B$2,'ESTADO CONTABLE'!$A$5:$A$16,0),IFNA(_xlfn.XLOOKUP(A31,PAGOS!$A$2:$A$996,PAGOS!$E$2:$E$996,""),""),IFNA(_xlfn.XLOOKUP(A31,PAGOS!$A$2:$A$996,PAGOS!$G$2:$G$996,""),""),IFNA(_xlfn.XLOOKUP(A31,PAGOS!$A$2:$A$996,PAGOS!$J$2:$J$996,""),""),IFNA(_xlfn.XLOOKUP(A31,PAGOS!$A$2:$A$996,PAGOS!$M$2:$M$996,""),""),IFNA(_xlfn.XLOOKUP(A31,PAGOS!$A$2:$A$996,PAGOS!$P$2:$P$996,""),""),IFNA(_xlfn.XLOOKUP(A31,PAGOS!$A$2:$A$996,PAGOS!$S$2:$S$996,""),""),IFNA(_xlfn.XLOOKUP(A31,PAGOS!$A$2:$A$996,PAGOS!$V$2:$V$996,""),""),IFNA(_xlfn.XLOOKUP(A31,PAGOS!$A$2:$A$996,PAGOS!$Y$2:$Y$996,""),""),IFNA(_xlfn.XLOOKUP(A31,PAGOS!$A$2:$A$996,PAGOS!$AB$2:$AB$996,""),""),IFNA(_xlfn.XLOOKUP(A31,PAGOS!$A$2:$A$996,PAGOS!$AE$2:$AE$996,""),""),IFNA(_xlfn.XLOOKUP(A31,PAGOS!$A$2:$A$996,PAGOS!$AH$2:$AH$996,""),""),IFNA(_xlfn.XLOOKUP(A31,PAGOS!$A$2:$A$996,PAGOS!$AK$2:$AK$996,""),"")),IF(abonos>0,abonos,pago)))} -> 550 | E31: =IFERROR(__xludf.DUMMYFUNCTION("IF(A31="""","""",LET(mes,DATE($E$2,MATCH($B$2,'ESTADO CONTABLE'!$A$5:$A$16,0),1),abonos,SUMIFS('ABONOS MENSUALIDADES'!$F$5:$F$500,'ABONOS MENSUALIDADES'!$C$5:$C$500,A31,'ABONOS MENSUALIDADES'!$D$5:$D$500,mes),metodoDirecto,CHOOSE(MATCH($B$2,'ESTADO CONTAB"&"LE'!$A$5:$A$16,0),IF(ISNUMBER(D31),""POR CLASIFICAR"",""""),IFNA(XLOOKUP(A31,PAGOS!$A$2:$A$996,PAGOS!$H$2:$H$996,""""),""""),IFNA(XLOOKUP(A31,PAGOS!$A$2:$A$996,PAGOS!$K$2:$K$996,""""),""""),IFNA(XLOOKUP(A31,PAGOS!$A$2:$A$996,PAGOS!$N$2:$N$996,""""),""""),"&"IFNA(XLOOKUP(A31,PAGOS!$A$2:$A$996,PAGOS!$Q$2:$Q$996,""""),""""),IFNA(XLOOKUP(A31,PAGOS!$A$2:$A$996,PAGOS!$T$2:$T$996,""""),""""),IFNA(XLOOKUP(A31,PAGOS!$A$2:$A$996,PAGOS!$W$2:$W$996,""""),""""),IFNA(XLOOKUP(A31,PAGOS!$A$2:$A$996,PAGOS!$Z$2:$Z$996,""""),"&"""""),IFNA(XLOOKUP(A31,PAGOS!$A$2:$A$996,PAGOS!$AC$2:$AC$996,""""),""""),IFNA(XLOOKUP(A31,PAGOS!$A$2:$A$996,PAGOS!$AF$2:$AF$996,""""),""""),IFNA(XLOOKUP(A31,PAGOS!$A$2:$A$996,PAGOS!$AI$2:$AI$996,""""),""""),IFNA(XLOOKUP(A31,PAGOS!$A$2:$A$996,PAGOS!$AL$2:$"&"AL$996,""""),"""")),IF(abonos>0,IFERROR(TEXTJOIN("" + "",TRUE,UNIQUE(FILTER('ABONOS MENSUALIDADES'!$E$5:$E$500,'ABONOS MENSUALIDADES'!$C$5:$C$500=A31,'ABONOS MENSUALIDADES'!$D$5:$D$500=mes))),""""),metodoDirecto)))"),"EFECTIVO") -> EFECTIVO | F31: {=IF(A31="","",LET(mes,DATE($E$2,MATCH($B$2,'ESTADO CONTABLE'!$A$5:$A$16,0),1),cobrarDesde,IFERROR(INDEX('BASE DE DATOSS'!I:I,ROW()-13),""),pausada,SUMPRODUCT((UPPER(TRIM('PAUSAS MENSUALIDADES'!$A$5:$A$500))=UPPER(TRIM(A31)))*('PAUSAS MENSUALIDADES'!$B$5:$B$500=mes)*(UPPER(TRIM('PAUSAS MENSUALIDADES'!$D$5:$D$500))="APLICAR"))>0,abonoActivo,SUMIFS('ABONOS MENSUALIDADES'!$F$5:$F$500,'ABONOS MENSUALIDADES'!$C$5:$C$500,A31,'ABONOS MENSUALIDADES'!$D$5:$D$500,mes,'ABONOS MENSUALIDADES'!$G$5:$G$500,"<>*CONSOLIDADO EN PAGOS*")>0,esperadaBruta,MAX(IFNA(VLOOKUP(B31,COSTOS!$A$3:$B$13,2,FALSE),0)-150,0),IF(AND(cobrarDesde<>"",mes<cobrarDesde),"AÚN NO INICIA",IF(pausada,"PAUSADA",IF(AND(abonoActivo,COUNTIFS('ABONOS MENSUALIDADES'!$C$5:$C$500,A31,'ABONOS MENSUALIDADES'!$D$5:$D$500,mes,'ABONOS MENSUALIDADES'!$G$5:$G$500,"*MENSUALIDAD LIQUIDADA*")=0),"ABONO",IF(N(D31)>=esperadaBruta,"COBRADA",IF(N(D31)>0,"ABONO","PENDIENTE")))))))} -> COBRADA | G31: {=IF(A31="","",IFERROR(INDEX('BASE DE DATOSS'!I:I,ROW()-13),""))} -> 46023
A32: {=IFERROR(INDEX('BASE DE DATOSS'!A:A,ROW()-13),"")} -> NADIA MIREYA MORENO CARRILLO | B32: {=IF(A32="","",IFERROR(INDEX('BASE DE DATOSS'!C:C,ROW()-13),""))} -> ADULTS 2 | C32: {=IF(A32="","",LET(mes,DATE($E$2,MATCH($B$2,'ESTADO CONTABLE'!$A$5:$A$16,0),1),cobrarDesde,IFERROR(INDEX('BASE DE DATOSS'!I:I,ROW()-13),""),pausada,SUMPRODUCT((UPPER(TRIM('PAUSAS MENSUALIDADES'!$A$5:$A$500))=UPPER(TRIM(A32)))*('PAUSAS MENSUALIDADES'!$B$5:$B$500=mes)*(UPPER(TRIM('PAUSAS MENSUALIDADES'!$D$5:$D$500))="APLICAR"))>0,IF(OR(AND(cobrarDesde<>"",mes<cobrarDesde),pausada),0,MAX(IFNA(VLOOKUP(B32,COSTOS!$A$3:$B$13,2,FALSE),0)-150,0)/1.16)))} -> 818.96552 | D32: {=IF(A32="","",LET(mes,DATE($E$2,MATCH($B$2,'ESTADO CONTABLE'!$A$5:$A$16,0),1),abonos,SUMIFS('ABONOS MENSUALIDADES'!$F$5:$F$500,'ABONOS MENSUALIDADES'!$C$5:$C$500,A32,'ABONOS MENSUALIDADES'!$D$5:$D$500,mes),pago,CHOOSE(MATCH($B$2,'ESTADO CONTABLE'!$A$5:$A$16,0),IFNA(_xlfn.XLOOKUP(A32,PAGOS!$A$2:$A$996,PAGOS!$E$2:$E$996,""),""),IFNA(_xlfn.XLOOKUP(A32,PAGOS!$A$2:$A$996,PAGOS!$G$2:$G$996,""),""),IFNA(_xlfn.XLOOKUP(A32,PAGOS!$A$2:$A$996,PAGOS!$J$2:$J$996,""),""),IFNA(_xlfn.XLOOKUP(A32,PAGOS!$A$2:$A$996,PAGOS!$M$2:$M$996,""),""),IFNA(_xlfn.XLOOKUP(A32,PAGOS!$A$2:$A$996,PAGOS!$P$2:$P$996,""),""),IFNA(_xlfn.XLOOKUP(A32,PAGOS!$A$2:$A$996,PAGOS!$S$2:$S$996,""),""),IFNA(_xlfn.XLOOKUP(A32,PAGOS!$A$2:$A$996,PAGOS!$V$2:$V$996,""),""),IFNA(_xlfn.XLOOKUP(A32,PAGOS!$A$2:$A$996,PAGOS!$Y$2:$Y$996,""),""),IFNA(_xlfn.XLOOKUP(A32,PAGOS!$A$2:$A$996,PAGOS!$AB$2:$AB$996,""),""),IFNA(_xlfn.XLOOKUP(A32,PAGOS!$A$2:$A$996,PAGOS!$AE$2:$AE$996,""),""),IFNA(_xlfn.XLOOKUP(A32,PAGOS!$A$2:$A$996,PAGOS!$AH$2:$AH$996,""),""),IFNA(_xlfn.XLOOKUP(A32,PAGOS!$A$2:$A$996,PAGOS!$AK$2:$AK$996,""),"")),IF(abonos>0,abonos,pago)))} -> 950 | E32: =IFERROR(__xludf.DUMMYFUNCTION("IF(A32="""","""",LET(mes,DATE($E$2,MATCH($B$2,'ESTADO CONTABLE'!$A$5:$A$16,0),1),abonos,SUMIFS('ABONOS MENSUALIDADES'!$F$5:$F$500,'ABONOS MENSUALIDADES'!$C$5:$C$500,A32,'ABONOS MENSUALIDADES'!$D$5:$D$500,mes),metodoDirecto,CHOOSE(MATCH($B$2,'ESTADO CONTAB"&"LE'!$A$5:$A$16,0),IF(ISNUMBER(D32),""POR CLASIFICAR"",""""),IFNA(XLOOKUP(A32,PAGOS!$A$2:$A$996,PAGOS!$H$2:$H$996,""""),""""),IFNA(XLOOKUP(A32,PAGOS!$A$2:$A$996,PAGOS!$K$2:$K$996,""""),""""),IFNA(XLOOKUP(A32,PAGOS!$A$2:$A$996,PAGOS!$N$2:$N$996,""""),""""),"&"IFNA(XLOOKUP(A32,PAGOS!$A$2:$A$996,PAGOS!$Q$2:$Q$996,""""),""""),IFNA(XLOOKUP(A32,PAGOS!$A$2:$A$996,PAGOS!$T$2:$T$996,""""),""""),IFNA(XLOOKUP(A32,PAGOS!$A$2:$A$996,PAGOS!$W$2:$W$996,""""),""""),IFNA(XLOOKUP(A32,PAGOS!$A$2:$A$996,PAGOS!$Z$2:$Z$996,""""),"&"""""),IFNA(XLOOKUP(A32,PAGOS!$A$2:$A$996,PAGOS!$AC$2:$AC$996,""""),""""),IFNA(XLOOKUP(A32,PAGOS!$A$2:$A$996,PAGOS!$AF$2:$AF$996,""""),""""),IFNA(XLOOKUP(A32,PAGOS!$A$2:$A$996,PAGOS!$AI$2:$AI$996,""""),""""),IFNA(XLOOKUP(A32,PAGOS!$A$2:$A$996,PAGOS!$AL$2:$"&"AL$996,""""),"""")),IF(abonos>0,IFERROR(TEXTJOIN("" + "",TRUE,UNIQUE(FILTER('ABONOS MENSUALIDADES'!$E$5:$E$500,'ABONOS MENSUALIDADES'!$C$5:$C$500=A32,'ABONOS MENSUALIDADES'!$D$5:$D$500=mes))),""""),metodoDirecto)))"),"TRANSFERENCIA") -> TRANSFERENCIA | F32: {=IF(A32="","",LET(mes,DATE($E$2,MATCH($B$2,'ESTADO CONTABLE'!$A$5:$A$16,0),1),cobrarDesde,IFERROR(INDEX('BASE DE DATOSS'!I:I,ROW()-13),""),pausada,SUMPRODUCT((UPPER(TRIM('PAUSAS MENSUALIDADES'!$A$5:$A$500))=UPPER(TRIM(A32)))*('PAUSAS MENSUALIDADES'!$B$5:$B$500=mes)*(UPPER(TRIM('PAUSAS MENSUALIDADES'!$D$5:$D$500))="APLICAR"))>0,abonoActivo,SUMIFS('ABONOS MENSUALIDADES'!$F$5:$F$500,'ABONOS MENSUALIDADES'!$C$5:$C$500,A32,'ABONOS MENSUALIDADES'!$D$5:$D$500,mes,'ABONOS MENSUALIDADES'!$G$5:$G$500,"<>*CONSOLIDADO EN PAGOS*")>0,esperadaBruta,MAX(IFNA(VLOOKUP(B32,COSTOS!$A$3:$B$13,2,FALSE),0)-150,0),IF(AND(cobrarDesde<>"",mes<cobrarDesde),"AÚN NO INICIA",IF(pausada,"PAUSADA",IF(AND(abonoActivo,COUNTIFS('ABONOS MENSUALIDADES'!$C$5:$C$500,A32,'ABONOS MENSUALIDADES'!$D$5:$D$500,mes,'ABONOS MENSUALIDADES'!$G$5:$G$500,"*MENSUALIDAD LIQUIDADA*")=0),"ABONO",IF(N(D32)>=esperadaBruta,"COBRADA",IF(N(D32)>0,"ABONO","PENDIENTE")))))))} -> COBRADA | G32: {=IF(A32="","",IFERROR(INDEX('BASE DE DATOSS'!I:I,ROW()-13),""))} -> 46023
A33: {=IFERROR(INDEX('BASE DE DATOSS'!A:A,ROW()-13),"")} -> ARIADNA KATINA MORENO ROSENDO | B33: {=IF(A33="","",IFERROR(INDEX('BASE DE DATOSS'!C:C,ROW()-13),""))} -> KIDS 2 | C33: {=IF(A33="","",LET(mes,DATE($E$2,MATCH($B$2,'ESTADO CONTABLE'!$A$5:$A$16,0),1),cobrarDesde,IFERROR(INDEX('BASE DE DATOSS'!I:I,ROW()-13),""),pausada,SUMPRODUCT((UPPER(TRIM('PAUSAS MENSUALIDADES'!$A$5:$A$500))=UPPER(TRIM(A33)))*('PAUSAS MENSUALIDADES'!$B$5:$B$500=mes)*(UPPER(TRIM('PAUSAS MENSUALIDADES'!$D$5:$D$500))="APLICAR"))>0,IF(OR(AND(cobrarDesde<>"",mes<cobrarDesde),pausada),0,MAX(IFNA(VLOOKUP(B33,COSTOS!$A$3:$B$13,2,FALSE),0)-150,0)/1.16)))} -> 689.65517 | D33: {=IF(A33="","",LET(mes,DATE($E$2,MATCH($B$2,'ESTADO CONTABLE'!$A$5:$A$16,0),1),abonos,SUMIFS('ABONOS MENSUALIDADES'!$F$5:$F$500,'ABONOS MENSUALIDADES'!$C$5:$C$500,A33,'ABONOS MENSUALIDADES'!$D$5:$D$500,mes),pago,CHOOSE(MATCH($B$2,'ESTADO CONTABLE'!$A$5:$A$16,0),IFNA(_xlfn.XLOOKUP(A33,PAGOS!$A$2:$A$996,PAGOS!$E$2:$E$996,""),""),IFNA(_xlfn.XLOOKUP(A33,PAGOS!$A$2:$A$996,PAGOS!$G$2:$G$996,""),""),IFNA(_xlfn.XLOOKUP(A33,PAGOS!$A$2:$A$996,PAGOS!$J$2:$J$996,""),""),IFNA(_xlfn.XLOOKUP(A33,PAGOS!$A$2:$A$996,PAGOS!$M$2:$M$996,""),""),IFNA(_xlfn.XLOOKUP(A33,PAGOS!$A$2:$A$996,PAGOS!$P$2:$P$996,""),""),IFNA(_xlfn.XLOOKUP(A33,PAGOS!$A$2:$A$996,PAGOS!$S$2:$S$996,""),""),IFNA(_xlfn.XLOOKUP(A33,PAGOS!$A$2:$A$996,PAGOS!$V$2:$V$996,""),""),IFNA(_xlfn.XLOOKUP(A33,PAGOS!$A$2:$A$996,PAGOS!$Y$2:$Y$996,""),""),IFNA(_xlfn.XLOOKUP(A33,PAGOS!$A$2:$A$996,PAGOS!$AB$2:$AB$996,""),""),IFNA(_xlfn.XLOOKUP(A33,PAGOS!$A$2:$A$996,PAGOS!$AE$2:$AE$996,""),""),IFNA(_xlfn.XLOOKUP(A33,PAGOS!$A$2:$A$996,PAGOS!$AH$2:$AH$996,""),""),IFNA(_xlfn.XLOOKUP(A33,PAGOS!$A$2:$A$996,PAGOS!$AK$2:$AK$996,""),"")),IF(abonos>0,abonos,pago)))} -> 800 | E33: =IFERROR(__xludf.DUMMYFUNCTION("IF(A33="""","""",LET(mes,DATE($E$2,MATCH($B$2,'ESTADO CONTABLE'!$A$5:$A$16,0),1),abonos,SUMIFS('ABONOS MENSUALIDADES'!$F$5:$F$500,'ABONOS MENSUALIDADES'!$C$5:$C$500,A33,'ABONOS MENSUALIDADES'!$D$5:$D$500,mes),metodoDirecto,CHOOSE(MATCH($B$2,'ESTADO CONTAB"&"LE'!$A$5:$A$16,0),IF(ISNUMBER(D33),""POR CLASIFICAR"",""""),IFNA(XLOOKUP(A33,PAGOS!$A$2:$A$996,PAGOS!$H$2:$H$996,""""),""""),IFNA(XLOOKUP(A33,PAGOS!$A$2:$A$996,PAGOS!$K$2:$K$996,""""),""""),IFNA(XLOOKUP(A33,PAGOS!$A$2:$A$996,PAGOS!$N$2:$N$996,""""),""""),"&"IFNA(XLOOKUP(A33,PAGOS!$A$2:$A$996,PAGOS!$Q$2:$Q$996,""""),""""),IFNA(XLOOKUP(A33,PAGOS!$A$2:$A$996,PAGOS!$T$2:$T$996,""""),""""),IFNA(XLOOKUP(A33,PAGOS!$A$2:$A$996,PAGOS!$W$2:$W$996,""""),""""),IFNA(XLOOKUP(A33,PAGOS!$A$2:$A$996,PAGOS!$Z$2:$Z$996,""""),"&"""""),IFNA(XLOOKUP(A33,PAGOS!$A$2:$A$996,PAGOS!$AC$2:$AC$996,""""),""""),IFNA(XLOOKUP(A33,PAGOS!$A$2:$A$996,PAGOS!$AF$2:$AF$996,""""),""""),IFNA(XLOOKUP(A33,PAGOS!$A$2:$A$996,PAGOS!$AI$2:$AI$996,""""),""""),IFNA(XLOOKUP(A33,PAGOS!$A$2:$A$996,PAGOS!$AL$2:$"&"AL$996,""""),"""")),IF(abonos>0,IFERROR(TEXTJOIN("" + "",TRUE,UNIQUE(FILTER('ABONOS MENSUALIDADES'!$E$5:$E$500,'ABONOS MENSUALIDADES'!$C$5:$C$500=A33,'ABONOS MENSUALIDADES'!$D$5:$D$500=mes))),""""),metodoDirecto)))"),"EFECTIVO") -> EFECTIVO | F33: {=IF(A33="","",LET(mes,DATE($E$2,MATCH($B$2,'ESTADO CONTABLE'!$A$5:$A$16,0),1),cobrarDesde,IFERROR(INDEX('BASE DE DATOSS'!I:I,ROW()-13),""),pausada,SUMPRODUCT((UPPER(TRIM('PAUSAS MENSUALIDADES'!$A$5:$A$500))=UPPER(TRIM(A33)))*('PAUSAS MENSUALIDADES'!$B$5:$B$500=mes)*(UPPER(TRIM('PAUSAS MENSUALIDADES'!$D$5:$D$500))="APLICAR"))>0,abonoActivo,SUMIFS('ABONOS MENSUALIDADES'!$F$5:$F$500,'ABONOS MENSUALIDADES'!$C$5:$C$500,A33,'ABONOS MENSUALIDADES'!$D$5:$D$500,mes,'ABONOS MENSUALIDADES'!$G$5:$G$500,"<>*CONSOLIDADO EN PAGOS*")>0,esperadaBruta,MAX(IFNA(VLOOKUP(B33,COSTOS!$A$3:$B$13,2,FALSE),0)-150,0),IF(AND(cobrarDesde<>"",mes<cobrarDesde),"AÚN NO INICIA",IF(pausada,"PAUSADA",IF(AND(abonoActivo,COUNTIFS('ABONOS MENSUALIDADES'!$C$5:$C$500,A33,'ABONOS MENSUALIDADES'!$D$5:$D$500,mes,'ABONOS MENSUALIDADES'!$G$5:$G$500,"*MENSUALIDAD LIQUIDADA*")=0),"ABONO",IF(N(D33)>=esperadaBruta,"COBRADA",IF(N(D33)>0,"ABONO","PENDIENTE")))))))} -> COBRADA | G33: {=IF(A33="","",IFERROR(INDEX('BASE DE DATOSS'!I:I,ROW()-13),""))} -> 46023
A34: {=IFERROR(INDEX('BASE DE DATOSS'!A:A,ROW()-13),"")} -> ANIELA SIBEL ORDOÑEZ RAMÍREZ | B34: {=IF(A34="","",IFERROR(INDEX('BASE DE DATOSS'!C:C,ROW()-13),""))} -> ADULTS 2 | C34: {=IF(A34="","",LET(mes,DATE($E$2,MATCH($B$2,'ESTADO CONTABLE'!$A$5:$A$16,0),1),cobrarDesde,IFERROR(INDEX('BASE DE DATOSS'!I:I,ROW()-13),""),pausada,SUMPRODUCT((UPPER(TRIM('PAUSAS MENSUALIDADES'!$A$5:$A$500))=UPPER(TRIM(A34)))*('PAUSAS MENSUALIDADES'!$B$5:$B$500=mes)*(UPPER(TRIM('PAUSAS MENSUALIDADES'!$D$5:$D$500))="APLICAR"))>0,IF(OR(AND(cobrarDesde<>"",mes<cobrarDesde),pausada),0,MAX(IFNA(VLOOKUP(B34,COSTOS!$A$3:$B$13,2,FALSE),0)-150,0)/1.16)))} -> 818.96552 | D34: {=IF(A34="","",LET(mes,DATE($E$2,MATCH($B$2,'ESTADO CONTABLE'!$A$5:$A$16,0),1),abonos,SUMIFS('ABONOS MENSUALIDADES'!$F$5:$F$500,'ABONOS MENSUALIDADES'!$C$5:$C$500,A34,'ABONOS MENSUALIDADES'!$D$5:$D$500,mes),pago,CHOOSE(MATCH($B$2,'ESTADO CONTABLE'!$A$5:$A$16,0),IFNA(_xlfn.XLOOKUP(A34,PAGOS!$A$2:$A$996,PAGOS!$E$2:$E$996,""),""),IFNA(_xlfn.XLOOKUP(A34,PAGOS!$A$2:$A$996,PAGOS!$G$2:$G$996,""),""),IFNA(_xlfn.XLOOKUP(A34,PAGOS!$A$2:$A$996,PAGOS!$J$2:$J$996,""),""),IFNA(_xlfn.XLOOKUP(A34,PAGOS!$A$2:$A$996,PAGOS!$M$2:$M$996,""),""),IFNA(_xlfn.XLOOKUP(A34,PAGOS!$A$2:$A$996,PAGOS!$P$2:$P$996,""),""),IFNA(_xlfn.XLOOKUP(A34,PAGOS!$A$2:$A$996,PAGOS!$S$2:$S$996,""),""),IFNA(_xlfn.XLOOKUP(A34,PAGOS!$A$2:$A$996,PAGOS!$V$2:$V$996,""),""),IFNA(_xlfn.XLOOKUP(A34,PAGOS!$A$2:$A$996,PAGOS!$Y$2:$Y$996,""),""),IFNA(_xlfn.XLOOKUP(A34,PAGOS!$A$2:$A$996,PAGOS!$AB$2:$AB$996,""),""),IFNA(_xlfn.XLOOKUP(A34,PAGOS!$A$2:$A$996,PAGOS!$AE$2:$AE$996,""),""),IFNA(_xlfn.XLOOKUP(A34,PAGOS!$A$2:$A$996,PAGOS!$AH$2:$AH$996,""),""),IFNA(_xlfn.XLOOKUP(A34,PAGOS!$A$2:$A$996,PAGOS!$AK$2:$AK$996,""),"")),IF(abonos>0,abonos,pago)))} -> 950 | E34: =IFERROR(__xludf.DUMMYFUNCTION("IF(A34="""","""",LET(mes,DATE($E$2,MATCH($B$2,'ESTADO CONTABLE'!$A$5:$A$16,0),1),abonos,SUMIFS('ABONOS MENSUALIDADES'!$F$5:$F$500,'ABONOS MENSUALIDADES'!$C$5:$C$500,A34,'ABONOS MENSUALIDADES'!$D$5:$D$500,mes),metodoDirecto,CHOOSE(MATCH($B$2,'ESTADO CONTAB"&"LE'!$A$5:$A$16,0),IF(ISNUMBER(D34),""POR CLASIFICAR"",""""),IFNA(XLOOKUP(A34,PAGOS!$A$2:$A$996,PAGOS!$H$2:$H$996,""""),""""),IFNA(XLOOKUP(A34,PAGOS!$A$2:$A$996,PAGOS!$K$2:$K$996,""""),""""),IFNA(XLOOKUP(A34,PAGOS!$A$2:$A$996,PAGOS!$N$2:$N$996,""""),""""),"&"IFNA(XLOOKUP(A34,PAGOS!$A$2:$A$996,PAGOS!$Q$2:$Q$996,""""),""""),IFNA(XLOOKUP(A34,PAGOS!$A$2:$A$996,PAGOS!$T$2:$T$996,""""),""""),IFNA(XLOOKUP(A34,PAGOS!$A$2:$A$996,PAGOS!$W$2:$W$996,""""),""""),IFNA(XLOOKUP(A34,PAGOS!$A$2:$A$996,PAGOS!$Z$2:$Z$996,""""),"&"""""),IFNA(XLOOKUP(A34,PAGOS!$A$2:$A$996,PAGOS!$AC$2:$AC$996,""""),""""),IFNA(XLOOKUP(A34,PAGOS!$A$2:$A$996,PAGOS!$AF$2:$AF$996,""""),""""),IFNA(XLOOKUP(A34,PAGOS!$A$2:$A$996,PAGOS!$AI$2:$AI$996,""""),""""),IFNA(XLOOKUP(A34,PAGOS!$A$2:$A$996,PAGOS!$AL$2:$"&"AL$996,""""),"""")),IF(abonos>0,IFERROR(TEXTJOIN("" + "",TRUE,UNIQUE(FILTER('ABONOS MENSUALIDADES'!$E$5:$E$500,'ABONOS MENSUALIDADES'!$C$5:$C$500=A34,'ABONOS MENSUALIDADES'!$D$5:$D$500=mes))),""""),metodoDirecto)))"),"TRANSFERENCIA") -> TRANSFERENCIA | F34: {=IF(A34="","",LET(mes,DATE($E$2,MATCH($B$2,'ESTADO CONTABLE'!$A$5:$A$16,0),1),cobrarDesde,IFERROR(INDEX('BASE DE DATOSS'!I:I,ROW()-13),""),pausada,SUMPRODUCT((UPPER(TRIM('PAUSAS MENSUALIDADES'!$A$5:$A$500))=UPPER(TRIM(A34)))*('PAUSAS MENSUALIDADES'!$B$5:$B$500=mes)*(UPPER(TRIM('PAUSAS MENSUALIDADES'!$D$5:$D$500))="APLICAR"))>0,abonoActivo,SUMIFS('ABONOS MENSUALIDADES'!$F$5:$F$500,'ABONOS MENSUALIDADES'!$C$5:$C$500,A34,'ABONOS MENSUALIDADES'!$D$5:$D$500,mes,'ABONOS MENSUALIDADES'!$G$5:$G$500,"<>*CONSOLIDADO EN PAGOS*")>0,esperadaBruta,MAX(IFNA(VLOOKUP(B34,COSTOS!$A$3:$B$13,2,FALSE),0)-150,0),IF(AND(cobrarDesde<>"",mes<cobrarDesde),"AÚN NO INICIA",IF(pausada,"PAUSADA",IF(AND(abonoActivo,COUNTIFS('ABONOS MENSUALIDADES'!$C$5:$C$500,A34,'ABONOS MENSUALIDADES'!$D$5:$D$500,mes,'ABONOS MENSUALIDADES'!$G$5:$G$500,"*MENSUALIDAD LIQUIDADA*")=0),"ABONO",IF(N(D34)>=esperadaBruta,"COBRADA",IF(N(D34)>0,"ABONO","PENDIENTE")))))))} -> COBRADA | G34: {=IF(A34="","",IFERROR(INDEX('BASE DE DATOSS'!I:I,ROW()-13),""))} -> 46023
A35: {=IFERROR(INDEX('BASE DE DATOSS'!A:A,ROW()-13),"")} -> DENYS GUALINO PERALTA | B35: {=IF(A35="","",IFERROR(INDEX('BASE DE DATOSS'!C:C,ROW()-13),""))} -> ADULTS 2 | C35: {=IF(A35="","",LET(mes,DATE($E$2,MATCH($B$2,'ESTADO CONTABLE'!$A$5:$A$16,0),1),cobrarDesde,IFERROR(INDEX('BASE DE DATOSS'!I:I,ROW()-13),""),pausada,SUMPRODUCT((UPPER(TRIM('PAUSAS MENSUALIDADES'!$A$5:$A$500))=UPPER(TRIM(A35)))*('PAUSAS MENSUALIDADES'!$B$5:$B$500=mes)*(UPPER(TRIM('PAUSAS MENSUALIDADES'!$D$5:$D$500))="APLICAR"))>0,IF(OR(AND(cobrarDesde<>"",mes<cobrarDesde),pausada),0,MAX(IFNA(VLOOKUP(B35,COSTOS!$A$3:$B$13,2,FALSE),0)-150,0)/1.16)))} -> 818.96552 | D35: {=IF(A35="","",LET(mes,DATE($E$2,MATCH($B$2,'ESTADO CONTABLE'!$A$5:$A$16,0),1),abonos,SUMIFS('ABONOS MENSUALIDADES'!$F$5:$F$500,'ABONOS MENSUALIDADES'!$C$5:$C$500,A35,'ABONOS MENSUALIDADES'!$D$5:$D$500,mes),pago,CHOOSE(MATCH($B$2,'ESTADO CONTABLE'!$A$5:$A$16,0),IFNA(_xlfn.XLOOKUP(A35,PAGOS!$A$2:$A$996,PAGOS!$E$2:$E$996,""),""),IFNA(_xlfn.XLOOKUP(A35,PAGOS!$A$2:$A$996,PAGOS!$G$2:$G$996,""),""),IFNA(_xlfn.XLOOKUP(A35,PAGOS!$A$2:$A$996,PAGOS!$J$2:$J$996,""),""),IFNA(_xlfn.XLOOKUP(A35,PAGOS!$A$2:$A$996,PAGOS!$M$2:$M$996,""),""),IFNA(_xlfn.XLOOKUP(A35,PAGOS!$A$2:$A$996,PAGOS!$P$2:$P$996,""),""),IFNA(_xlfn.XLOOKUP(A35,PAGOS!$A$2:$A$996,PAGOS!$S$2:$S$996,""),""),IFNA(_xlfn.XLOOKUP(A35,PAGOS!$A$2:$A$996,PAGOS!$V$2:$V$996,""),""),IFNA(_xlfn.XLOOKUP(A35,PAGOS!$A$2:$A$996,PAGOS!$Y$2:$Y$996,""),""),IFNA(_xlfn.XLOOKUP(A35,PAGOS!$A$2:$A$996,PAGOS!$AB$2:$AB$996,""),""),IFNA(_xlfn.XLOOKUP(A35,PAGOS!$A$2:$A$996,PAGOS!$AE$2:$AE$996,""),""),IFNA(_xlfn.XLOOKUP(A35,PAGOS!$A$2:$A$996,PAGOS!$AH$2:$AH$996,""),""),IFNA(_xlfn.XLOOKUP(A35,PAGOS!$A$2:$A$996,PAGOS!$AK$2:$AK$996,""),"")),IF(abonos>0,abonos,pago)))} -> 950 | E35: =IFERROR(__xludf.DUMMYFUNCTION("IF(A35="""","""",LET(mes,DATE($E$2,MATCH($B$2,'ESTADO CONTABLE'!$A$5:$A$16,0),1),abonos,SUMIFS('ABONOS MENSUALIDADES'!$F$5:$F$500,'ABONOS MENSUALIDADES'!$C$5:$C$500,A35,'ABONOS MENSUALIDADES'!$D$5:$D$500,mes),metodoDirecto,CHOOSE(MATCH($B$2,'ESTADO CONTAB"&"LE'!$A$5:$A$16,0),IF(ISNUMBER(D35),""POR CLASIFICAR"",""""),IFNA(XLOOKUP(A35,PAGOS!$A$2:$A$996,PAGOS!$H$2:$H$996,""""),""""),IFNA(XLOOKUP(A35,PAGOS!$A$2:$A$996,PAGOS!$K$2:$K$996,""""),""""),IFNA(XLOOKUP(A35,PAGOS!$A$2:$A$996,PAGOS!$N$2:$N$996,""""),""""),"&"IFNA(XLOOKUP(A35,PAGOS!$A$2:$A$996,PAGOS!$Q$2:$Q$996,""""),""""),IFNA(XLOOKUP(A35,PAGOS!$A$2:$A$996,PAGOS!$T$2:$T$996,""""),""""),IFNA(XLOOKUP(A35,PAGOS!$A$2:$A$996,PAGOS!$W$2:$W$996,""""),""""),IFNA(XLOOKUP(A35,PAGOS!$A$2:$A$996,PAGOS!$Z$2:$Z$996,""""),"&"""""),IFNA(XLOOKUP(A35,PAGOS!$A$2:$A$996,PAGOS!$AC$2:$AC$996,""""),""""),IFNA(XLOOKUP(A35,PAGOS!$A$2:$A$996,PAGOS!$AF$2:$AF$996,""""),""""),IFNA(XLOOKUP(A35,PAGOS!$A$2:$A$996,PAGOS!$AI$2:$AI$996,""""),""""),IFNA(XLOOKUP(A35,PAGOS!$A$2:$A$996,PAGOS!$AL$2:$"&"AL$996,""""),"""")),IF(abonos>0,IFERROR(TEXTJOIN("" + "",TRUE,UNIQUE(FILTER('ABONOS MENSUALIDADES'!$E$5:$E$500,'ABONOS MENSUALIDADES'!$C$5:$C$500=A35,'ABONOS MENSUALIDADES'!$D$5:$D$500=mes))),""""),metodoDirecto)))"),"TRANSFERENCIA") -> TRANSFERENCIA | F35: {=IF(A35="","",LET(mes,DATE($E$2,MATCH($B$2,'ESTADO CONTABLE'!$A$5:$A$16,0),1),cobrarDesde,IFERROR(INDEX('BASE DE DATOSS'!I:I,ROW()-13),""),pausada,SUMPRODUCT((UPPER(TRIM('PAUSAS MENSUALIDADES'!$A$5:$A$500))=UPPER(TRIM(A35)))*('PAUSAS MENSUALIDADES'!$B$5:$B$500=mes)*(UPPER(TRIM('PAUSAS MENSUALIDADES'!$D$5:$D$500))="APLICAR"))>0,abonoActivo,SUMIFS('ABONOS MENSUALIDADES'!$F$5:$F$500,'ABONOS MENSUALIDADES'!$C$5:$C$500,A35,'ABONOS MENSUALIDADES'!$D$5:$D$500,mes,'ABONOS MENSUALIDADES'!$G$5:$G$500,"<>*CONSOLIDADO EN PAGOS*")>0,esperadaBruta,MAX(IFNA(VLOOKUP(B35,COSTOS!$A$3:$B$13,2,FALSE),0)-150,0),IF(AND(cobrarDesde<>"",mes<cobrarDesde),"AÚN NO INICIA",IF(pausada,"PAUSADA",IF(AND(abonoActivo,COUNTIFS('ABONOS MENSUALIDADES'!$C$5:$C$500,A35,'ABONOS MENSUALIDADES'!$D$5:$D$500,mes,'ABONOS MENSUALIDADES'!$G$5:$G$500,"*MENSUALIDAD LIQUIDADA*")=0),"ABONO",IF(N(D35)>=esperadaBruta,"COBRADA",IF(N(D35)>0,"ABONO","PENDIENTE")))))))} -> COBRADA | G35: {=IF(A35="","",IFERROR(INDEX('BASE DE DATOSS'!I:I,ROW()-13),""))} -> 46023
A36: {=IFERROR(INDEX('BASE DE DATOSS'!A:A,ROW()-13),"")} -> MARÍA SOFIA CÁRDENAS MENDOZA | B36: {=IF(A36="","",IFERROR(INDEX('BASE DE DATOSS'!C:C,ROW()-13),""))} -> JR 2 | C36: {=IF(A36="","",LET(mes,DATE($E$2,MATCH($B$2,'ESTADO CONTABLE'!$A$5:$A$16,0),1),cobrarDesde,IFERROR(INDEX('BASE DE DATOSS'!I:I,ROW()-13),""),pausada,SUMPRODUCT((UPPER(TRIM('PAUSAS MENSUALIDADES'!$A$5:$A$500))=UPPER(TRIM(A36)))*('PAUSAS MENSUALIDADES'!$B$5:$B$500=mes)*(UPPER(TRIM('PAUSAS MENSUALIDADES'!$D$5:$D$500))="APLICAR"))>0,IF(OR(AND(cobrarDesde<>"",mes<cobrarDesde),pausada),0,MAX(IFNA(VLOOKUP(B36,COSTOS!$A$3:$B$13,2,FALSE),0)-150,0)/1.16)))} -> 689.65517 | D36: {=IF(A36="","",LET(mes,DATE($E$2,MATCH($B$2,'ESTADO CONTABLE'!$A$5:$A$16,0),1),abonos,SUMIFS('ABONOS MENSUALIDADES'!$F$5:$F$500,'ABONOS MENSUALIDADES'!$C$5:$C$500,A36,'ABONOS MENSUALIDADES'!$D$5:$D$500,mes),pago,CHOOSE(MATCH($B$2,'ESTADO CONTABLE'!$A$5:$A$16,0),IFNA(_xlfn.XLOOKUP(A36,PAGOS!$A$2:$A$996,PAGOS!$E$2:$E$996,""),""),IFNA(_xlfn.XLOOKUP(A36,PAGOS!$A$2:$A$996,PAGOS!$G$2:$G$996,""),""),IFNA(_xlfn.XLOOKUP(A36,PAGOS!$A$2:$A$996,PAGOS!$J$2:$J$996,""),""),IFNA(_xlfn.XLOOKUP(A36,PAGOS!$A$2:$A$996,PAGOS!$M$2:$M$996,""),""),IFNA(_xlfn.XLOOKUP(A36,PAGOS!$A$2:$A$996,PAGOS!$P$2:$P$996,""),""),IFNA(_xlfn.XLOOKUP(A36,PAGOS!$A$2:$A$996,PAGOS!$S$2:$S$996,""),""),IFNA(_xlfn.XLOOKUP(A36,PAGOS!$A$2:$A$996,PAGOS!$V$2:$V$996,""),""),IFNA(_xlfn.XLOOKUP(A36,PAGOS!$A$2:$A$996,PAGOS!$Y$2:$Y$996,""),""),IFNA(_xlfn.XLOOKUP(A36,PAGOS!$A$2:$A$996,PAGOS!$AB$2:$AB$996,""),""),IFNA(_xlfn.XLOOKUP(A36,PAGOS!$A$2:$A$996,PAGOS!$AE$2:$AE$996,""),""),IFNA(_xlfn.XLOOKUP(A36,PAGOS!$A$2:$A$996,PAGOS!$AH$2:$AH$996,""),""),IFNA(_xlfn.XLOOKUP(A36,PAGOS!$A$2:$A$996,PAGOS!$AK$2:$AK$996,""),"")),IF(abonos>0,abonos,pago)))} -> 950 | E36: =IFERROR(__xludf.DUMMYFUNCTION("IF(A36="""","""",LET(mes,DATE($E$2,MATCH($B$2,'ESTADO CONTABLE'!$A$5:$A$16,0),1),abonos,SUMIFS('ABONOS MENSUALIDADES'!$F$5:$F$500,'ABONOS MENSUALIDADES'!$C$5:$C$500,A36,'ABONOS MENSUALIDADES'!$D$5:$D$500,mes),metodoDirecto,CHOOSE(MATCH($B$2,'ESTADO CONTAB"&"LE'!$A$5:$A$16,0),IF(ISNUMBER(D36),""POR CLASIFICAR"",""""),IFNA(XLOOKUP(A36,PAGOS!$A$2:$A$996,PAGOS!$H$2:$H$996,""""),""""),IFNA(XLOOKUP(A36,PAGOS!$A$2:$A$996,PAGOS!$K$2:$K$996,""""),""""),IFNA(XLOOKUP(A36,PAGOS!$A$2:$A$996,PAGOS!$N$2:$N$996,""""),""""),"&"IFNA(XLOOKUP(A36,PAGOS!$A$2:$A$996,PAGOS!$Q$2:$Q$996,""""),""""),IFNA(XLOOKUP(A36,PAGOS!$A$2:$A$996,PAGOS!$T$2:$T$996,""""),""""),IFNA(XLOOKUP(A36,PAGOS!$A$2:$A$996,PAGOS!$W$2:$W$996,""""),""""),IFNA(XLOOKUP(A36,PAGOS!$A$2:$A$996,PAGOS!$Z$2:$Z$996,""""),"&"""""),IFNA(XLOOKUP(A36,PAGOS!$A$2:$A$996,PAGOS!$AC$2:$AC$996,""""),""""),IFNA(XLOOKUP(A36,PAGOS!$A$2:$A$996,PAGOS!$AF$2:$AF$996,""""),""""),IFNA(XLOOKUP(A36,PAGOS!$A$2:$A$996,PAGOS!$AI$2:$AI$996,""""),""""),IFNA(XLOOKUP(A36,PAGOS!$A$2:$A$996,PAGOS!$AL$2:$"&"AL$996,""""),"""")),IF(abonos>0,IFERROR(TEXTJOIN("" + "",TRUE,UNIQUE(FILTER('ABONOS MENSUALIDADES'!$E$5:$E$500,'ABONOS MENSUALIDADES'!$C$5:$C$500=A36,'ABONOS MENSUALIDADES'!$D$5:$D$500=mes))),""""),metodoDirecto)))"),"TRANSFERENCIA") -> TRANSFERENCIA | F36: {=IF(A36="","",LET(mes,DATE($E$2,MATCH($B$2,'ESTADO CONTABLE'!$A$5:$A$16,0),1),cobrarDesde,IFERROR(INDEX('BASE DE DATOSS'!I:I,ROW()-13),""),pausada,SUMPRODUCT((UPPER(TRIM('PAUSAS MENSUALIDADES'!$A$5:$A$500))=UPPER(TRIM(A36)))*('PAUSAS MENSUALIDADES'!$B$5:$B$500=mes)*(UPPER(TRIM('PAUSAS MENSUALIDADES'!$D$5:$D$500))="APLICAR"))>0,abonoActivo,SUMIFS('ABONOS MENSUALIDADES'!$F$5:$F$500,'ABONOS MENSUALIDADES'!$C$5:$C$500,A36,'ABONOS MENSUALIDADES'!$D$5:$D$500,mes,'ABONOS MENSUALIDADES'!$G$5:$G$500,"<>*CONSOLIDADO EN PAGOS*")>0,esperadaBruta,MAX(IFNA(VLOOKUP(B36,COSTOS!$A$3:$B$13,2,FALSE),0)-150,0),IF(AND(cobrarDesde<>"",mes<cobrarDesde),"AÚN NO INICIA",IF(pausada,"PAUSADA",IF(AND(abonoActivo,COUNTIFS('ABONOS MENSUALIDADES'!$C$5:$C$500,A36,'ABONOS MENSUALIDADES'!$D$5:$D$500,mes,'ABONOS MENSUALIDADES'!$G$5:$G$500,"*MENSUALIDAD LIQUIDADA*")=0),"ABONO",IF(N(D36)>=esperadaBruta,"COBRADA",IF(N(D36)>0,"ABONO","PENDIENTE")))))))} -> COBRADA | G36: {=IF(A36="","",IFERROR(INDEX('BASE DE DATOSS'!I:I,ROW()-13),""))} -> 46054
A37: {=IFERROR(INDEX('BASE DE DATOSS'!A:A,ROW()-13),"")} -> MARTHA IVONNE CRUZ TORRES | B37: {=IF(A37="","",IFERROR(INDEX('BASE DE DATOSS'!C:C,ROW()-13),""))} -> JR 1 | C37: {=IF(A37="","",LET(mes,DATE($E$2,MATCH($B$2,'ESTADO CONTABLE'!$A$5:$A$16,0),1),cobrarDesde,IFERROR(INDEX('BASE DE DATOSS'!I:I,ROW()-13),""),pausada,SUMPRODUCT((UPPER(TRIM('PAUSAS MENSUALIDADES'!$A$5:$A$500))=UPPER(TRIM(A37)))*('PAUSAS MENSUALIDADES'!$B$5:$B$500=mes)*(UPPER(TRIM('PAUSAS MENSUALIDADES'!$D$5:$D$500))="APLICAR"))>0,IF(OR(AND(cobrarDesde<>"",mes<cobrarDesde),pausada),0,MAX(IFNA(VLOOKUP(B37,COSTOS!$A$3:$B$13,2,FALSE),0)-150,0)/1.16)))} -> 818.96552 | D37: {=IF(A37="","",LET(mes,DATE($E$2,MATCH($B$2,'ESTADO CONTABLE'!$A$5:$A$16,0),1),abonos,SUMIFS('ABONOS MENSUALIDADES'!$F$5:$F$500,'ABONOS MENSUALIDADES'!$C$5:$C$500,A37,'ABONOS MENSUALIDADES'!$D$5:$D$500,mes),pago,CHOOSE(MATCH($B$2,'ESTADO CONTABLE'!$A$5:$A$16,0),IFNA(_xlfn.XLOOKUP(A37,PAGOS!$A$2:$A$996,PAGOS!$E$2:$E$996,""),""),IFNA(_xlfn.XLOOKUP(A37,PAGOS!$A$2:$A$996,PAGOS!$G$2:$G$996,""),""),IFNA(_xlfn.XLOOKUP(A37,PAGOS!$A$2:$A$996,PAGOS!$J$2:$J$996,""),""),IFNA(_xlfn.XLOOKUP(A37,PAGOS!$A$2:$A$996,PAGOS!$M$2:$M$996,""),""),IFNA(_xlfn.XLOOKUP(A37,PAGOS!$A$2:$A$996,PAGOS!$P$2:$P$996,""),""),IFNA(_xlfn.XLOOKUP(A37,PAGOS!$A$2:$A$996,PAGOS!$S$2:$S$996,""),""),IFNA(_xlfn.XLOOKUP(A37,PAGOS!$A$2:$A$996,PAGOS!$V$2:$V$996,""),""),IFNA(_xlfn.XLOOKUP(A37,PAGOS!$A$2:$A$996,PAGOS!$Y$2:$Y$996,""),""),IFNA(_xlfn.XLOOKUP(A37,PAGOS!$A$2:$A$996,PAGOS!$AB$2:$AB$996,""),""),IFNA(_xlfn.XLOOKUP(A37,PAGOS!$A$2:$A$996,PAGOS!$AE$2:$AE$996,""),""),IFNA(_xlfn.XLOOKUP(A37,PAGOS!$A$2:$A$996,PAGOS!$AH$2:$AH$996,""),""),IFNA(_xlfn.XLOOKUP(A37,PAGOS!$A$2:$A$996,PAGOS!$AK$2:$AK$996,""),"")),IF(abonos>0,abonos,pago)))} -> 950 | E37: =IFERROR(__xludf.DUMMYFUNCTION("IF(A37="""","""",LET(mes,DATE($E$2,MATCH($B$2,'ESTADO CONTABLE'!$A$5:$A$16,0),1),abonos,SUMIFS('ABONOS MENSUALIDADES'!$F$5:$F$500,'ABONOS MENSUALIDADES'!$C$5:$C$500,A37,'ABONOS MENSUALIDADES'!$D$5:$D$500,mes),metodoDirecto,CHOOSE(MATCH($B$2,'ESTADO CONTAB"&"LE'!$A$5:$A$16,0),IF(ISNUMBER(D37),""POR CLASIFICAR"",""""),IFNA(XLOOKUP(A37,PAGOS!$A$2:$A$996,PAGOS!$H$2:$H$996,""""),""""),IFNA(XLOOKUP(A37,PAGOS!$A$2:$A$996,PAGOS!$K$2:$K$996,""""),""""),IFNA(XLOOKUP(A37,PAGOS!$A$2:$A$996,PAGOS!$N$2:$N$996,""""),""""),"&"IFNA(XLOOKUP(A37,PAGOS!$A$2:$A$996,PAGOS!$Q$2:$Q$996,""""),""""),IFNA(XLOOKUP(A37,PAGOS!$A$2:$A$996,PAGOS!$T$2:$T$996,""""),""""),IFNA(XLOOKUP(A37,PAGOS!$A$2:$A$996,PAGOS!$W$2:$W$996,""""),""""),IFNA(XLOOKUP(A37,PAGOS!$A$2:$A$996,PAGOS!$Z$2:$Z$996,""""),"&"""""),IFNA(XLOOKUP(A37,PAGOS!$A$2:$A$996,PAGOS!$AC$2:$AC$996,""""),""""),IFNA(XLOOKUP(A37,PAGOS!$A$2:$A$996,PAGOS!$AF$2:$AF$996,""""),""""),IFNA(XLOOKUP(A37,PAGOS!$A$2:$A$996,PAGOS!$AI$2:$AI$996,""""),""""),IFNA(XLOOKUP(A37,PAGOS!$A$2:$A$996,PAGOS!$AL$2:$"&"AL$996,""""),"""")),IF(abonos>0,IFERROR(TEXTJOIN("" + "",TRUE,UNIQUE(FILTER('ABONOS MENSUALIDADES'!$E$5:$E$500,'ABONOS MENSUALIDADES'!$C$5:$C$500=A37,'ABONOS MENSUALIDADES'!$D$5:$D$500=mes))),""""),metodoDirecto)))"),"EFECTIVO") -> EFECTIVO | F37: {=IF(A37="","",LET(mes,DATE($E$2,MATCH($B$2,'ESTADO CONTABLE'!$A$5:$A$16,0),1),cobrarDesde,IFERROR(INDEX('BASE DE DATOSS'!I:I,ROW()-13),""),pausada,SUMPRODUCT((UPPER(TRIM('PAUSAS MENSUALIDADES'!$A$5:$A$500))=UPPER(TRIM(A37)))*('PAUSAS MENSUALIDADES'!$B$5:$B$500=mes)*(UPPER(TRIM('PAUSAS MENSUALIDADES'!$D$5:$D$500))="APLICAR"))>0,abonoActivo,SUMIFS('ABONOS MENSUALIDADES'!$F$5:$F$500,'ABONOS MENSUALIDADES'!$C$5:$C$500,A37,'ABONOS MENSUALIDADES'!$D$5:$D$500,mes,'ABONOS MENSUALIDADES'!$G$5:$G$500,"<>*CONSOLIDADO EN PAGOS*")>0,esperadaBruta,MAX(IFNA(VLOOKUP(B37,COSTOS!$A$3:$B$13,2,FALSE),0)-150,0),IF(AND(cobrarDesde<>"",mes<cobrarDesde),"AÚN NO INICIA",IF(pausada,"PAUSADA",IF(AND(abonoActivo,COUNTIFS('ABONOS MENSUALIDADES'!$C$5:$C$500,A37,'ABONOS MENSUALIDADES'!$D$5:$D$500,mes,'ABONOS MENSUALIDADES'!$G$5:$G$500,"*MENSUALIDAD LIQUIDADA*")=0),"ABONO",IF(N(D37)>=esperadaBruta,"COBRADA",IF(N(D37)>0,"ABONO","PENDIENTE")))))))} -> COBRADA | G37: {=IF(A37="","",IFERROR(INDEX('BASE DE DATOSS'!I:I,ROW()-13),""))} -> 46054
A38: {=IFERROR(INDEX('BASE DE DATOSS'!A:A,ROW()-13),"")} -> GABRIELA GUADALUPE CRUZ TORRES | B38: {=IF(A38="","",IFERROR(INDEX('BASE DE DATOSS'!C:C,ROW()-13),""))} -> JR 1 | C38: {=IF(A38="","",LET(mes,DATE($E$2,MATCH($B$2,'ESTADO CONTABLE'!$A$5:$A$16,0),1),cobrarDesde,IFERROR(INDEX('BASE DE DATOSS'!I:I,ROW()-13),""),pausada,SUMPRODUCT((UPPER(TRIM('PAUSAS MENSUALIDADES'!$A$5:$A$500))=UPPER(TRIM(A38)))*('PAUSAS MENSUALIDADES'!$B$5:$B$500=mes)*(UPPER(TRIM('PAUSAS MENSUALIDADES'!$D$5:$D$500))="APLICAR"))>0,IF(OR(AND(cobrarDesde<>"",mes<cobrarDesde),pausada),0,MAX(IFNA(VLOOKUP(B38,COSTOS!$A$3:$B$13,2,FALSE),0)-150,0)/1.16)))} -> 818.96552 | D38: {=IF(A38="","",LET(mes,DATE($E$2,MATCH($B$2,'ESTADO CONTABLE'!$A$5:$A$16,0),1),abonos,SUMIFS('ABONOS MENSUALIDADES'!$F$5:$F$500,'ABONOS MENSUALIDADES'!$C$5:$C$500,A38,'ABONOS MENSUALIDADES'!$D$5:$D$500,mes),pago,CHOOSE(MATCH($B$2,'ESTADO CONTABLE'!$A$5:$A$16,0),IFNA(_xlfn.XLOOKUP(A38,PAGOS!$A$2:$A$996,PAGOS!$E$2:$E$996,""),""),IFNA(_xlfn.XLOOKUP(A38,PAGOS!$A$2:$A$996,PAGOS!$G$2:$G$996,""),""),IFNA(_xlfn.XLOOKUP(A38,PAGOS!$A$2:$A$996,PAGOS!$J$2:$J$996,""),""),IFNA(_xlfn.XLOOKUP(A38,PAGOS!$A$2:$A$996,PAGOS!$M$2:$M$996,""),""),IFNA(_xlfn.XLOOKUP(A38,PAGOS!$A$2:$A$996,PAGOS!$P$2:$P$996,""),""),IFNA(_xlfn.XLOOKUP(A38,PAGOS!$A$2:$A$996,PAGOS!$S$2:$S$996,""),""),IFNA(_xlfn.XLOOKUP(A38,PAGOS!$A$2:$A$996,PAGOS!$V$2:$V$996,""),""),IFNA(_xlfn.XLOOKUP(A38,PAGOS!$A$2:$A$996,PAGOS!$Y$2:$Y$996,""),""),IFNA(_xlfn.XLOOKUP(A38,PAGOS!$A$2:$A$996,PAGOS!$AB$2:$AB$996,""),""),IFNA(_xlfn.XLOOKUP(A38,PAGOS!$A$2:$A$996,PAGOS!$AE$2:$AE$996,""),""),IFNA(_xlfn.XLOOKUP(A38,PAGOS!$A$2:$A$996,PAGOS!$AH$2:$AH$996,""),""),IFNA(_xlfn.XLOOKUP(A38,PAGOS!$A$2:$A$996,PAGOS!$AK$2:$AK$996,""),"")),IF(abonos>0,abonos,pago)))} -> 950 | E38: =IFERROR(__xludf.DUMMYFUNCTION("IF(A38="""","""",LET(mes,DATE($E$2,MATCH($B$2,'ESTADO CONTABLE'!$A$5:$A$16,0),1),abonos,SUMIFS('ABONOS MENSUALIDADES'!$F$5:$F$500,'ABONOS MENSUALIDADES'!$C$5:$C$500,A38,'ABONOS MENSUALIDADES'!$D$5:$D$500,mes),metodoDirecto,CHOOSE(MATCH($B$2,'ESTADO CONTAB"&"LE'!$A$5:$A$16,0),IF(ISNUMBER(D38),""POR CLASIFICAR"",""""),IFNA(XLOOKUP(A38,PAGOS!$A$2:$A$996,PAGOS!$H$2:$H$996,""""),""""),IFNA(XLOOKUP(A38,PAGOS!$A$2:$A$996,PAGOS!$K$2:$K$996,""""),""""),IFNA(XLOOKUP(A38,PAGOS!$A$2:$A$996,PAGOS!$N$2:$N$996,""""),""""),"&"IFNA(XLOOKUP(A38,PAGOS!$A$2:$A$996,PAGOS!$Q$2:$Q$996,""""),""""),IFNA(XLOOKUP(A38,PAGOS!$A$2:$A$996,PAGOS!$T$2:$T$996,""""),""""),IFNA(XLOOKUP(A38,PAGOS!$A$2:$A$996,PAGOS!$W$2:$W$996,""""),""""),IFNA(XLOOKUP(A38,PAGOS!$A$2:$A$996,PAGOS!$Z$2:$Z$996,""""),"&"""""),IFNA(XLOOKUP(A38,PAGOS!$A$2:$A$996,PAGOS!$AC$2:$AC$996,""""),""""),IFNA(XLOOKUP(A38,PAGOS!$A$2:$A$996,PAGOS!$AF$2:$AF$996,""""),""""),IFNA(XLOOKUP(A38,PAGOS!$A$2:$A$996,PAGOS!$AI$2:$AI$996,""""),""""),IFNA(XLOOKUP(A38,PAGOS!$A$2:$A$996,PAGOS!$AL$2:$"&"AL$996,""""),"""")),IF(abonos>0,IFERROR(TEXTJOIN("" + "",TRUE,UNIQUE(FILTER('ABONOS MENSUALIDADES'!$E$5:$E$500,'ABONOS MENSUALIDADES'!$C$5:$C$500=A38,'ABONOS MENSUALIDADES'!$D$5:$D$500=mes))),""""),metodoDirecto)))"),"EFECTIVO") -> EFECTIVO | F38: {=IF(A38="","",LET(mes,DATE($E$2,MATCH($B$2,'ESTADO CONTABLE'!$A$5:$A$16,0),1),cobrarDesde,IFERROR(INDEX('BASE DE DATOSS'!I:I,ROW()-13),""),pausada,SUMPRODUCT((UPPER(TRIM('PAUSAS MENSUALIDADES'!$A$5:$A$500))=UPPER(TRIM(A38)))*('PAUSAS MENSUALIDADES'!$B$5:$B$500=mes)*(UPPER(TRIM('PAUSAS MENSUALIDADES'!$D$5:$D$500))="APLICAR"))>0,abonoActivo,SUMIFS('ABONOS MENSUALIDADES'!$F$5:$F$500,'ABONOS MENSUALIDADES'!$C$5:$C$500,A38,'ABONOS MENSUALIDADES'!$D$5:$D$500,mes,'ABONOS MENSUALIDADES'!$G$5:$G$500,"<>*CONSOLIDADO EN PAGOS*")>0,esperadaBruta,MAX(IFNA(VLOOKUP(B38,COSTOS!$A$3:$B$13,2,FALSE),0)-150,0),IF(AND(cobrarDesde<>"",mes<cobrarDesde),"AÚN NO INICIA",IF(pausada,"PAUSADA",IF(AND(abonoActivo,COUNTIFS('ABONOS MENSUALIDADES'!$C$5:$C$500,A38,'ABONOS MENSUALIDADES'!$D$5:$D$500,mes,'ABONOS MENSUALIDADES'!$G$5:$G$500,"*MENSUALIDAD LIQUIDADA*")=0),"ABONO",IF(N(D38)>=esperadaBruta,"COBRADA",IF(N(D38)>0,"ABONO","PENDIENTE")))))))} -> COBRADA | G38: {=IF(A38="","",IFERROR(INDEX('BASE DE DATOSS'!I:I,ROW()-13),""))} -> 46054
A39: {=IFERROR(INDEX('BASE DE DATOSS'!A:A,ROW()-13),"")} -> IVANNA ESPINOZA JACINTO | B39: {=IF(A39="","",IFERROR(INDEX('BASE DE DATOSS'!C:C,ROW()-13),""))} -> KIDS 1 | C39: {=IF(A39="","",LET(mes,DATE($E$2,MATCH($B$2,'ESTADO CONTABLE'!$A$5:$A$16,0),1),cobrarDesde,IFERROR(INDEX('BASE DE DATOSS'!I:I,ROW()-13),""),pausada,SUMPRODUCT((UPPER(TRIM('PAUSAS MENSUALIDADES'!$A$5:$A$500))=UPPER(TRIM(A39)))*('PAUSAS MENSUALIDADES'!$B$5:$B$500=mes)*(UPPER(TRIM('PAUSAS MENSUALIDADES'!$D$5:$D$500))="APLICAR"))>0,IF(OR(AND(cobrarDesde<>"",mes<cobrarDesde),pausada),0,MAX(IFNA(VLOOKUP(B39,COSTOS!$A$3:$B$13,2,FALSE),0)-150,0)/1.16)))} -> 818.96552 | D39: {=IF(A39="","",LET(mes,DATE($E$2,MATCH($B$2,'ESTADO CONTABLE'!$A$5:$A$16,0),1),abonos,SUMIFS('ABONOS MENSUALIDADES'!$F$5:$F$500,'ABONOS MENSUALIDADES'!$C$5:$C$500,A39,'ABONOS MENSUALIDADES'!$D$5:$D$500,mes),pago,CHOOSE(MATCH($B$2,'ESTADO CONTABLE'!$A$5:$A$16,0),IFNA(_xlfn.XLOOKUP(A39,PAGOS!$A$2:$A$996,PAGOS!$E$2:$E$996,""),""),IFNA(_xlfn.XLOOKUP(A39,PAGOS!$A$2:$A$996,PAGOS!$G$2:$G$996,""),""),IFNA(_xlfn.XLOOKUP(A39,PAGOS!$A$2:$A$996,PAGOS!$J$2:$J$996,""),""),IFNA(_xlfn.XLOOKUP(A39,PAGOS!$A$2:$A$996,PAGOS!$M$2:$M$996,""),""),IFNA(_xlfn.XLOOKUP(A39,PAGOS!$A$2:$A$996,PAGOS!$P$2:$P$996,""),""),IFNA(_xlfn.XLOOKUP(A39,PAGOS!$A$2:$A$996,PAGOS!$S$2:$S$996,""),""),IFNA(_xlfn.XLOOKUP(A39,PAGOS!$A$2:$A$996,PAGOS!$V$2:$V$996,""),""),IFNA(_xlfn.XLOOKUP(A39,PAGOS!$A$2:$A$996,PAGOS!$Y$2:$Y$996,""),""),IFNA(_xlfn.XLOOKUP(A39,PAGOS!$A$2:$A$996,PAGOS!$AB$2:$AB$996,""),""),IFNA(_xlfn.XLOOKUP(A39,PAGOS!$A$2:$A$996,PAGOS!$AE$2:$AE$996,""),""),IFNA(_xlfn.XLOOKUP(A39,PAGOS!$A$2:$A$996,PAGOS!$AH$2:$AH$996,""),""),IFNA(_xlfn.XLOOKUP(A39,PAGOS!$A$2:$A$996,PAGOS!$AK$2:$AK$996,""),"")),IF(abonos>0,abonos,pago)))} -> 950 | E39: =IFERROR(__xludf.DUMMYFUNCTION("IF(A39="""","""",LET(mes,DATE($E$2,MATCH($B$2,'ESTADO CONTABLE'!$A$5:$A$16,0),1),abonos,SUMIFS('ABONOS MENSUALIDADES'!$F$5:$F$500,'ABONOS MENSUALIDADES'!$C$5:$C$500,A39,'ABONOS MENSUALIDADES'!$D$5:$D$500,mes),metodoDirecto,CHOOSE(MATCH($B$2,'ESTADO CONTAB"&"LE'!$A$5:$A$16,0),IF(ISNUMBER(D39),""POR CLASIFICAR"",""""),IFNA(XLOOKUP(A39,PAGOS!$A$2:$A$996,PAGOS!$H$2:$H$996,""""),""""),IFNA(XLOOKUP(A39,PAGOS!$A$2:$A$996,PAGOS!$K$2:$K$996,""""),""""),IFNA(XLOOKUP(A39,PAGOS!$A$2:$A$996,PAGOS!$N$2:$N$996,""""),""""),"&"IFNA(XLOOKUP(A39,PAGOS!$A$2:$A$996,PAGOS!$Q$2:$Q$996,""""),""""),IFNA(XLOOKUP(A39,PAGOS!$A$2:$A$996,PAGOS!$T$2:$T$996,""""),""""),IFNA(XLOOKUP(A39,PAGOS!$A$2:$A$996,PAGOS!$W$2:$W$996,""""),""""),IFNA(XLOOKUP(A39,PAGOS!$A$2:$A$996,PAGOS!$Z$2:$Z$996,""""),"&"""""),IFNA(XLOOKUP(A39,PAGOS!$A$2:$A$996,PAGOS!$AC$2:$AC$996,""""),""""),IFNA(XLOOKUP(A39,PAGOS!$A$2:$A$996,PAGOS!$AF$2:$AF$996,""""),""""),IFNA(XLOOKUP(A39,PAGOS!$A$2:$A$996,PAGOS!$AI$2:$AI$996,""""),""""),IFNA(XLOOKUP(A39,PAGOS!$A$2:$A$996,PAGOS!$AL$2:$"&"AL$996,""""),"""")),IF(abonos>0,IFERROR(TEXTJOIN("" + "",TRUE,UNIQUE(FILTER('ABONOS MENSUALIDADES'!$E$5:$E$500,'ABONOS MENSUALIDADES'!$C$5:$C$500=A39,'ABONOS MENSUALIDADES'!$D$5:$D$500=mes))),""""),metodoDirecto)))"),"TRANSFERENCIA") -> TRANSFERENCIA | F39: {=IF(A39="","",LET(mes,DATE($E$2,MATCH($B$2,'ESTADO CONTABLE'!$A$5:$A$16,0),1),cobrarDesde,IFERROR(INDEX('BASE DE DATOSS'!I:I,ROW()-13),""),pausada,SUMPRODUCT((UPPER(TRIM('PAUSAS MENSUALIDADES'!$A$5:$A$500))=UPPER(TRIM(A39)))*('PAUSAS MENSUALIDADES'!$B$5:$B$500=mes)*(UPPER(TRIM('PAUSAS MENSUALIDADES'!$D$5:$D$500))="APLICAR"))>0,abonoActivo,SUMIFS('ABONOS MENSUALIDADES'!$F$5:$F$500,'ABONOS MENSUALIDADES'!$C$5:$C$500,A39,'ABONOS MENSUALIDADES'!$D$5:$D$500,mes,'ABONOS MENSUALIDADES'!$G$5:$G$500,"<>*CONSOLIDADO EN PAGOS*")>0,esperadaBruta,MAX(IFNA(VLOOKUP(B39,COSTOS!$A$3:$B$13,2,FALSE),0)-150,0),IF(AND(cobrarDesde<>"",mes<cobrarDesde),"AÚN NO INICIA",IF(pausada,"PAUSADA",IF(AND(abonoActivo,COUNTIFS('ABONOS MENSUALIDADES'!$C$5:$C$500,A39,'ABONOS MENSUALIDADES'!$D$5:$D$500,mes,'ABONOS MENSUALIDADES'!$G$5:$G$500,"*MENSUALIDAD LIQUIDADA*")=0),"ABONO",IF(N(D39)>=esperadaBruta,"COBRADA",IF(N(D39)>0,"ABONO","PENDIENTE")))))))} -> COBRADA | G39: {=IF(A39="","",IFERROR(INDEX('BASE DE DATOSS'!I:I,ROW()-13),""))} -> 46054
A40: {=IFERROR(INDEX('BASE DE DATOSS'!A:A,ROW()-13),"")} -> ISABELA ESTEFANIA CASTILLO LLAMAS | B40: {=IF(A40="","",IFERROR(INDEX('BASE DE DATOSS'!C:C,ROW()-13),""))} -> KIDS 1 | C40: {=IF(A40="","",LET(mes,DATE($E$2,MATCH($B$2,'ESTADO CONTABLE'!$A$5:$A$16,0),1),cobrarDesde,IFERROR(INDEX('BASE DE DATOSS'!I:I,ROW()-13),""),pausada,SUMPRODUCT((UPPER(TRIM('PAUSAS MENSUALIDADES'!$A$5:$A$500))=UPPER(TRIM(A40)))*('PAUSAS MENSUALIDADES'!$B$5:$B$500=mes)*(UPPER(TRIM('PAUSAS MENSUALIDADES'!$D$5:$D$500))="APLICAR"))>0,IF(OR(AND(cobrarDesde<>"",mes<cobrarDesde),pausada),0,MAX(IFNA(VLOOKUP(B40,COSTOS!$A$3:$B$13,2,FALSE),0)-150,0)/1.16)))} -> 818.96552 | D40: {=IF(A40="","",LET(mes,DATE($E$2,MATCH($B$2,'ESTADO CONTABLE'!$A$5:$A$16,0),1),abonos,SUMIFS('ABONOS MENSUALIDADES'!$F$5:$F$500,'ABONOS MENSUALIDADES'!$C$5:$C$500,A40,'ABONOS MENSUALIDADES'!$D$5:$D$500,mes),pago,CHOOSE(MATCH($B$2,'ESTADO CONTABLE'!$A$5:$A$16,0),IFNA(_xlfn.XLOOKUP(A40,PAGOS!$A$2:$A$996,PAGOS!$E$2:$E$996,""),""),IFNA(_xlfn.XLOOKUP(A40,PAGOS!$A$2:$A$996,PAGOS!$G$2:$G$996,""),""),IFNA(_xlfn.XLOOKUP(A40,PAGOS!$A$2:$A$996,PAGOS!$J$2:$J$996,""),""),IFNA(_xlfn.XLOOKUP(A40,PAGOS!$A$2:$A$996,PAGOS!$M$2:$M$996,""),""),IFNA(_xlfn.XLOOKUP(A40,PAGOS!$A$2:$A$996,PAGOS!$P$2:$P$996,""),""),IFNA(_xlfn.XLOOKUP(A40,PAGOS!$A$2:$A$996,PAGOS!$S$2:$S$996,""),""),IFNA(_xlfn.XLOOKUP(A40,PAGOS!$A$2:$A$996,PAGOS!$V$2:$V$996,""),""),IFNA(_xlfn.XLOOKUP(A40,PAGOS!$A$2:$A$996,PAGOS!$Y$2:$Y$996,""),""),IFNA(_xlfn.XLOOKUP(A40,PAGOS!$A$2:$A$996,PAGOS!$AB$2:$AB$996,""),""),IFNA(_xlfn.XLOOKUP(A40,PAGOS!$A$2:$A$996,PAGOS!$AE$2:$AE$996,""),""),IFNA(_xlfn.XLOOKUP(A40,PAGOS!$A$2:$A$996,PAGOS!$AH$2:$AH$996,""),""),IFNA(_xlfn.XLOOKUP(A40,PAGOS!$A$2:$A$996,PAGOS!$AK$2:$AK$996,""),"")),IF(abonos>0,abonos,pago)))} -> 950 | E40: =IFERROR(__xludf.DUMMYFUNCTION("IF(A40="""","""",LET(mes,DATE($E$2,MATCH($B$2,'ESTADO CONTABLE'!$A$5:$A$16,0),1),abonos,SUMIFS('ABONOS MENSUALIDADES'!$F$5:$F$500,'ABONOS MENSUALIDADES'!$C$5:$C$500,A40,'ABONOS MENSUALIDADES'!$D$5:$D$500,mes),metodoDirecto,CHOOSE(MATCH($B$2,'ESTADO CONTAB"&"LE'!$A$5:$A$16,0),IF(ISNUMBER(D40),""POR CLASIFICAR"",""""),IFNA(XLOOKUP(A40,PAGOS!$A$2:$A$996,PAGOS!$H$2:$H$996,""""),""""),IFNA(XLOOKUP(A40,PAGOS!$A$2:$A$996,PAGOS!$K$2:$K$996,""""),""""),IFNA(XLOOKUP(A40,PAGOS!$A$2:$A$996,PAGOS!$N$2:$N$996,""""),""""),"&"IFNA(XLOOKUP(A40,PAGOS!$A$2:$A$996,PAGOS!$Q$2:$Q$996,""""),""""),IFNA(XLOOKUP(A40,PAGOS!$A$2:$A$996,PAGOS!$T$2:$T$996,""""),""""),IFNA(XLOOKUP(A40,PAGOS!$A$2:$A$996,PAGOS!$W$2:$W$996,""""),""""),IFNA(XLOOKUP(A40,PAGOS!$A$2:$A$996,PAGOS!$Z$2:$Z$996,""""),"&"""""),IFNA(XLOOKUP(A40,PAGOS!$A$2:$A$996,PAGOS!$AC$2:$AC$996,""""),""""),IFNA(XLOOKUP(A40,PAGOS!$A$2:$A$996,PAGOS!$AF$2:$AF$996,""""),""""),IFNA(XLOOKUP(A40,PAGOS!$A$2:$A$996,PAGOS!$AI$2:$AI$996,""""),""""),IFNA(XLOOKUP(A40,PAGOS!$A$2:$A$996,PAGOS!$AL$2:$"&"AL$996,""""),"""")),IF(abonos>0,IFERROR(TEXTJOIN("" + "",TRUE,UNIQUE(FILTER('ABONOS MENSUALIDADES'!$E$5:$E$500,'ABONOS MENSUALIDADES'!$C$5:$C$500=A40,'ABONOS MENSUALIDADES'!$D$5:$D$500=mes))),""""),metodoDirecto)))"),"TRANSFERENCIA") -> TRANSFERENCIA | F40: {=IF(A40="","",LET(mes,DATE($E$2,MATCH($B$2,'ESTADO CONTABLE'!$A$5:$A$16,0),1),cobrarDesde,IFERROR(INDEX('BASE DE DATOSS'!I:I,ROW()-13),""),pausada,SUMPRODUCT((UPPER(TRIM('PAUSAS MENSUALIDADES'!$A$5:$A$500))=UPPER(TRIM(A40)))*('PAUSAS MENSUALIDADES'!$B$5:$B$500=mes)*(UPPER(TRIM('PAUSAS MENSUALIDADES'!$D$5:$D$500))="APLICAR"))>0,abonoActivo,SUMIFS('ABONOS MENSUALIDADES'!$F$5:$F$500,'ABONOS MENSUALIDADES'!$C$5:$C$500,A40,'ABONOS MENSUALIDADES'!$D$5:$D$500,mes,'ABONOS MENSUALIDADES'!$G$5:$G$500,"<>*CONSOLIDADO EN PAGOS*")>0,esperadaBruta,MAX(IFNA(VLOOKUP(B40,COSTOS!$A$3:$B$13,2,FALSE),0)-150,0),IF(AND(cobrarDesde<>"",mes<cobrarDesde),"AÚN NO INICIA",IF(pausada,"PAUSADA",IF(AND(abonoActivo,COUNTIFS('ABONOS MENSUALIDADES'!$C$5:$C$500,A40,'ABONOS MENSUALIDADES'!$D$5:$D$500,mes,'ABONOS MENSUALIDADES'!$G$5:$G$500,"*MENSUALIDAD LIQUIDADA*")=0),"ABONO",IF(N(D40)>=esperadaBruta,"COBRADA",IF(N(D40)>0,"ABONO","PENDIENTE")))))))} -> COBRADA | G40: {=IF(A40="","",IFERROR(INDEX('BASE DE DATOSS'!I:I,ROW()-13),""))} -> 46054
A41: {=IFERROR(INDEX('BASE DE DATOSS'!A:A,ROW()-13),"")} -> DIANA MARISOL OCHOA CORONA | B41: {=IF(A41="","",IFERROR(INDEX('BASE DE DATOSS'!C:C,ROW()-13),""))} -> ADULTS 1 | C41: {=IF(A41="","",LET(mes,DATE($E$2,MATCH($B$2,'ESTADO CONTABLE'!$A$5:$A$16,0),1),cobrarDesde,IFERROR(INDEX('BASE DE DATOSS'!I:I,ROW()-13),""),pausada,SUMPRODUCT((UPPER(TRIM('PAUSAS MENSUALIDADES'!$A$5:$A$500))=UPPER(TRIM(A41)))*('PAUSAS MENSUALIDADES'!$B$5:$B$500=mes)*(UPPER(TRIM('PAUSAS MENSUALIDADES'!$D$5:$D$500))="APLICAR"))>0,IF(OR(AND(cobrarDesde<>"",mes<cobrarDesde),pausada),0,MAX(IFNA(VLOOKUP(B41,COSTOS!$A$3:$B$13,2,FALSE),0)-150,0)/1.16)))} -> 991.37931 | D41: {=IF(A41="","",LET(mes,DATE($E$2,MATCH($B$2,'ESTADO CONTABLE'!$A$5:$A$16,0),1),abonos,SUMIFS('ABONOS MENSUALIDADES'!$F$5:$F$500,'ABONOS MENSUALIDADES'!$C$5:$C$500,A41,'ABONOS MENSUALIDADES'!$D$5:$D$500,mes),pago,CHOOSE(MATCH($B$2,'ESTADO CONTABLE'!$A$5:$A$16,0),IFNA(_xlfn.XLOOKUP(A41,PAGOS!$A$2:$A$996,PAGOS!$E$2:$E$996,""),""),IFNA(_xlfn.XLOOKUP(A41,PAGOS!$A$2:$A$996,PAGOS!$G$2:$G$996,""),""),IFNA(_xlfn.XLOOKUP(A41,PAGOS!$A$2:$A$996,PAGOS!$J$2:$J$996,""),""),IFNA(_xlfn.XLOOKUP(A41,PAGOS!$A$2:$A$996,PAGOS!$M$2:$M$996,""),""),IFNA(_xlfn.XLOOKUP(A41,PAGOS!$A$2:$A$996,PAGOS!$P$2:$P$996,""),""),IFNA(_xlfn.XLOOKUP(A41,PAGOS!$A$2:$A$996,PAGOS!$S$2:$S$996,""),""),IFNA(_xlfn.XLOOKUP(A41,PAGOS!$A$2:$A$996,PAGOS!$V$2:$V$996,""),""),IFNA(_xlfn.XLOOKUP(A41,PAGOS!$A$2:$A$996,PAGOS!$Y$2:$Y$996,""),""),IFNA(_xlfn.XLOOKUP(A41,PAGOS!$A$2:$A$996,PAGOS!$AB$2:$AB$996,""),""),IFNA(_xlfn.XLOOKUP(A41,PAGOS!$A$2:$A$996,PAGOS!$AE$2:$AE$996,""),""),IFNA(_xlfn.XLOOKUP(A41,PAGOS!$A$2:$A$996,PAGOS!$AH$2:$AH$996,""),""),IFNA(_xlfn.XLOOKUP(A41,PAGOS!$A$2:$A$996,PAGOS!$AK$2:$AK$996,""),"")),IF(abonos>0,abonos,pago)))} -> 1300 | E41: =IFERROR(__xludf.DUMMYFUNCTION("IF(A41="""","""",LET(mes,DATE($E$2,MATCH($B$2,'ESTADO CONTABLE'!$A$5:$A$16,0),1),abonos,SUMIFS('ABONOS MENSUALIDADES'!$F$5:$F$500,'ABONOS MENSUALIDADES'!$C$5:$C$500,A41,'ABONOS MENSUALIDADES'!$D$5:$D$500,mes),metodoDirecto,CHOOSE(MATCH($B$2,'ESTADO CONTAB"&"LE'!$A$5:$A$16,0),IF(ISNUMBER(D41),""POR CLASIFICAR"",""""),IFNA(XLOOKUP(A41,PAGOS!$A$2:$A$996,PAGOS!$H$2:$H$996,""""),""""),IFNA(XLOOKUP(A41,PAGOS!$A$2:$A$996,PAGOS!$K$2:$K$996,""""),""""),IFNA(XLOOKUP(A41,PAGOS!$A$2:$A$996,PAGOS!$N$2:$N$996,""""),""""),"&"IFNA(XLOOKUP(A41,PAGOS!$A$2:$A$996,PAGOS!$Q$2:$Q$996,""""),""""),IFNA(XLOOKUP(A41,PAGOS!$A$2:$A$996,PAGOS!$T$2:$T$996,""""),""""),IFNA(XLOOKUP(A41,PAGOS!$A$2:$A$996,PAGOS!$W$2:$W$996,""""),""""),IFNA(XLOOKUP(A41,PAGOS!$A$2:$A$996,PAGOS!$Z$2:$Z$996,""""),"&"""""),IFNA(XLOOKUP(A41,PAGOS!$A$2:$A$996,PAGOS!$AC$2:$AC$996,""""),""""),IFNA(XLOOKUP(A41,PAGOS!$A$2:$A$996,PAGOS!$AF$2:$AF$996,""""),""""),IFNA(XLOOKUP(A41,PAGOS!$A$2:$A$996,PAGOS!$AI$2:$AI$996,""""),""""),IFNA(XLOOKUP(A41,PAGOS!$A$2:$A$996,PAGOS!$AL$2:$"&"AL$996,""""),"""")),IF(abonos>0,IFERROR(TEXTJOIN("" + "",TRUE,UNIQUE(FILTER('ABONOS MENSUALIDADES'!$E$5:$E$500,'ABONOS MENSUALIDADES'!$C$5:$C$500=A41,'ABONOS MENSUALIDADES'!$D$5:$D$500=mes))),""""),metodoDirecto)))"),"EFECTIVO") -> EFECTIVO | F41: {=IF(A41="","",LET(mes,DATE($E$2,MATCH($B$2,'ESTADO CONTABLE'!$A$5:$A$16,0),1),cobrarDesde,IFERROR(INDEX('BASE DE DATOSS'!I:I,ROW()-13),""),pausada,SUMPRODUCT((UPPER(TRIM('PAUSAS MENSUALIDADES'!$A$5:$A$500))=UPPER(TRIM(A41)))*('PAUSAS MENSUALIDADES'!$B$5:$B$500=mes)*(UPPER(TRIM('PAUSAS MENSUALIDADES'!$D$5:$D$500))="APLICAR"))>0,abonoActivo,SUMIFS('ABONOS MENSUALIDADES'!$F$5:$F$500,'ABONOS MENSUALIDADES'!$C$5:$C$500,A41,'ABONOS MENSUALIDADES'!$D$5:$D$500,mes,'ABONOS MENSUALIDADES'!$G$5:$G$500,"<>*CONSOLIDADO EN PAGOS*")>0,esperadaBruta,MAX(IFNA(VLOOKUP(B41,COSTOS!$A$3:$B$13,2,FALSE),0)-150,0),IF(AND(cobrarDesde<>"",mes<cobrarDesde),"AÚN NO INICIA",IF(pausada,"PAUSADA",IF(AND(abonoActivo,COUNTIFS('ABONOS MENSUALIDADES'!$C$5:$C$500,A41,'ABONOS MENSUALIDADES'!$D$5:$D$500,mes,'ABONOS MENSUALIDADES'!$G$5:$G$500,"*MENSUALIDAD LIQUIDADA*")=0),"ABONO",IF(N(D41)>=esperadaBruta,"COBRADA",IF(N(D41)>0,"ABONO","PENDIENTE")))))))} -> COBRADA | G41: {=IF(A41="","",IFERROR(INDEX('BASE DE DATOSS'!I:I,ROW()-13),""))} -> 46054
A42: {=IFERROR(INDEX('BASE DE DATOSS'!A:A,ROW()-13),"")} -> EVA REGINA FUENTES VEGA | B42: {=IF(A42="","",IFERROR(INDEX('BASE DE DATOSS'!C:C,ROW()-13),""))} -> KIDS 1 | C42: {=IF(A42="","",LET(mes,DATE($E$2,MATCH($B$2,'ESTADO CONTABLE'!$A$5:$A$16,0),1),cobrarDesde,IFERROR(INDEX('BASE DE DATOSS'!I:I,ROW()-13),""),pausada,SUMPRODUCT((UPPER(TRIM('PAUSAS MENSUALIDADES'!$A$5:$A$500))=UPPER(TRIM(A42)))*('PAUSAS MENSUALIDADES'!$B$5:$B$500=mes)*(UPPER(TRIM('PAUSAS MENSUALIDADES'!$D$5:$D$500))="APLICAR"))>0,IF(OR(AND(cobrarDesde<>"",mes<cobrarDesde),pausada),0,MAX(IFNA(VLOOKUP(B42,COSTOS!$A$3:$B$13,2,FALSE),0)-150,0)/1.16)))} -> 818.96552 | D42: {=IF(A42="","",LET(mes,DATE($E$2,MATCH($B$2,'ESTADO CONTABLE'!$A$5:$A$16,0),1),abonos,SUMIFS('ABONOS MENSUALIDADES'!$F$5:$F$500,'ABONOS MENSUALIDADES'!$C$5:$C$500,A42,'ABONOS MENSUALIDADES'!$D$5:$D$500,mes),pago,CHOOSE(MATCH($B$2,'ESTADO CONTABLE'!$A$5:$A$16,0),IFNA(_xlfn.XLOOKUP(A42,PAGOS!$A$2:$A$996,PAGOS!$E$2:$E$996,""),""),IFNA(_xlfn.XLOOKUP(A42,PAGOS!$A$2:$A$996,PAGOS!$G$2:$G$996,""),""),IFNA(_xlfn.XLOOKUP(A42,PAGOS!$A$2:$A$996,PAGOS!$J$2:$J$996,""),""),IFNA(_xlfn.XLOOKUP(A42,PAGOS!$A$2:$A$996,PAGOS!$M$2:$M$996,""),""),IFNA(_xlfn.XLOOKUP(A42,PAGOS!$A$2:$A$996,PAGOS!$P$2:$P$996,""),""),IFNA(_xlfn.XLOOKUP(A42,PAGOS!$A$2:$A$996,PAGOS!$S$2:$S$996,""),""),IFNA(_xlfn.XLOOKUP(A42,PAGOS!$A$2:$A$996,PAGOS!$V$2:$V$996,""),""),IFNA(_xlfn.XLOOKUP(A42,PAGOS!$A$2:$A$996,PAGOS!$Y$2:$Y$996,""),""),IFNA(_xlfn.XLOOKUP(A42,PAGOS!$A$2:$A$996,PAGOS!$AB$2:$AB$996,""),""),IFNA(_xlfn.XLOOKUP(A42,PAGOS!$A$2:$A$996,PAGOS!$AE$2:$AE$996,""),""),IFNA(_xlfn.XLOOKUP(A42,PAGOS!$A$2:$A$996,PAGOS!$AH$2:$AH$996,""),""),IFNA(_xlfn.XLOOKUP(A42,PAGOS!$A$2:$A$996,PAGOS!$AK$2:$AK$996,""),"")),IF(abonos>0,abonos,pago)))} -> 1100 | E42: =IFERROR(__xludf.DUMMYFUNCTION("IF(A42="""","""",LET(mes,DATE($E$2,MATCH($B$2,'ESTADO CONTABLE'!$A$5:$A$16,0),1),abonos,SUMIFS('ABONOS MENSUALIDADES'!$F$5:$F$500,'ABONOS MENSUALIDADES'!$C$5:$C$500,A42,'ABONOS MENSUALIDADES'!$D$5:$D$500,mes),metodoDirecto,CHOOSE(MATCH($B$2,'ESTADO CONTAB"&"LE'!$A$5:$A$16,0),IF(ISNUMBER(D42),""POR CLASIFICAR"",""""),IFNA(XLOOKUP(A42,PAGOS!$A$2:$A$996,PAGOS!$H$2:$H$996,""""),""""),IFNA(XLOOKUP(A42,PAGOS!$A$2:$A$996,PAGOS!$K$2:$K$996,""""),""""),IFNA(XLOOKUP(A42,PAGOS!$A$2:$A$996,PAGOS!$N$2:$N$996,""""),""""),"&"IFNA(XLOOKUP(A42,PAGOS!$A$2:$A$996,PAGOS!$Q$2:$Q$996,""""),""""),IFNA(XLOOKUP(A42,PAGOS!$A$2:$A$996,PAGOS!$T$2:$T$996,""""),""""),IFNA(XLOOKUP(A42,PAGOS!$A$2:$A$996,PAGOS!$W$2:$W$996,""""),""""),IFNA(XLOOKUP(A42,PAGOS!$A$2:$A$996,PAGOS!$Z$2:$Z$996,""""),"&"""""),IFNA(XLOOKUP(A42,PAGOS!$A$2:$A$996,PAGOS!$AC$2:$AC$996,""""),""""),IFNA(XLOOKUP(A42,PAGOS!$A$2:$A$996,PAGOS!$AF$2:$AF$996,""""),""""),IFNA(XLOOKUP(A42,PAGOS!$A$2:$A$996,PAGOS!$AI$2:$AI$996,""""),""""),IFNA(XLOOKUP(A42,PAGOS!$A$2:$A$996,PAGOS!$AL$2:$"&"AL$996,""""),"""")),IF(abonos>0,IFERROR(TEXTJOIN("" + "",TRUE,UNIQUE(FILTER('ABONOS MENSUALIDADES'!$E$5:$E$500,'ABONOS MENSUALIDADES'!$C$5:$C$500=A42,'ABONOS MENSUALIDADES'!$D$5:$D$500=mes))),""""),metodoDirecto)))"),"TRANSFERENCIA") -> TRANSFERENCIA | F42: {=IF(A42="","",LET(mes,DATE($E$2,MATCH($B$2,'ESTADO CONTABLE'!$A$5:$A$16,0),1),cobrarDesde,IFERROR(INDEX('BASE DE DATOSS'!I:I,ROW()-13),""),pausada,SUMPRODUCT((UPPER(TRIM('PAUSAS MENSUALIDADES'!$A$5:$A$500))=UPPER(TRIM(A42)))*('PAUSAS MENSUALIDADES'!$B$5:$B$500=mes)*(UPPER(TRIM('PAUSAS MENSUALIDADES'!$D$5:$D$500))="APLICAR"))>0,abonoActivo,SUMIFS('ABONOS MENSUALIDADES'!$F$5:$F$500,'ABONOS MENSUALIDADES'!$C$5:$C$500,A42,'ABONOS MENSUALIDADES'!$D$5:$D$500,mes,'ABONOS MENSUALIDADES'!$G$5:$G$500,"<>*CONSOLIDADO EN PAGOS*")>0,esperadaBruta,MAX(IFNA(VLOOKUP(B42,COSTOS!$A$3:$B$13,2,FALSE),0)-150,0),IF(AND(cobrarDesde<>"",mes<cobrarDesde),"AÚN NO INICIA",IF(pausada,"PAUSADA",IF(AND(abonoActivo,COUNTIFS('ABONOS MENSUALIDADES'!$C$5:$C$500,A42,'ABONOS MENSUALIDADES'!$D$5:$D$500,mes,'ABONOS MENSUALIDADES'!$G$5:$G$500,"*MENSUALIDAD LIQUIDADA*")=0),"ABONO",IF(N(D42)>=esperadaBruta,"COBRADA",IF(N(D42)>0,"ABONO","PENDIENTE")))))))} -> COBRADA | G42: {=IF(A42="","",IFERROR(INDEX('BASE DE DATOSS'!I:I,ROW()-13),""))} -> 46082
A43: {=IFERROR(INDEX('BASE DE DATOSS'!A:A,ROW()-13),"")} -> JESSICA FERNANDEZ GUTIERREZ | B43: {=IF(A43="","",IFERROR(INDEX('BASE DE DATOSS'!C:C,ROW()-13),""))} -> MATUTINO | C43: {=IF(A43="","",LET(mes,DATE($E$2,MATCH($B$2,'ESTADO CONTABLE'!$A$5:$A$16,0),1),cobrarDesde,IFERROR(INDEX('BASE DE DATOSS'!I:I,ROW()-13),""),pausada,SUMPRODUCT((UPPER(TRIM('PAUSAS MENSUALIDADES'!$A$5:$A$500))=UPPER(TRIM(A43)))*('PAUSAS MENSUALIDADES'!$B$5:$B$500=mes)*(UPPER(TRIM('PAUSAS MENSUALIDADES'!$D$5:$D$500))="APLICAR"))>0,IF(OR(AND(cobrarDesde<>"",mes<cobrarDesde),pausada),0,MAX(IFNA(VLOOKUP(B43,COSTOS!$A$3:$B$13,2,FALSE),0)-150,0)/1.16)))} -> 818.96552 | D43: {=IF(A43="","",LET(mes,DATE($E$2,MATCH($B$2,'ESTADO CONTABLE'!$A$5:$A$16,0),1),abonos,SUMIFS('ABONOS MENSUALIDADES'!$F$5:$F$500,'ABONOS MENSUALIDADES'!$C$5:$C$500,A43,'ABONOS MENSUALIDADES'!$D$5:$D$500,mes),pago,CHOOSE(MATCH($B$2,'ESTADO CONTABLE'!$A$5:$A$16,0),IFNA(_xlfn.XLOOKUP(A43,PAGOS!$A$2:$A$996,PAGOS!$E$2:$E$996,""),""),IFNA(_xlfn.XLOOKUP(A43,PAGOS!$A$2:$A$996,PAGOS!$G$2:$G$996,""),""),IFNA(_xlfn.XLOOKUP(A43,PAGOS!$A$2:$A$996,PAGOS!$J$2:$J$996,""),""),IFNA(_xlfn.XLOOKUP(A43,PAGOS!$A$2:$A$996,PAGOS!$M$2:$M$996,""),""),IFNA(_xlfn.XLOOKUP(A43,PAGOS!$A$2:$A$996,PAGOS!$P$2:$P$996,""),""),IFNA(_xlfn.XLOOKUP(A43,PAGOS!$A$2:$A$996,PAGOS!$S$2:$S$996,""),""),IFNA(_xlfn.XLOOKUP(A43,PAGOS!$A$2:$A$996,PAGOS!$V$2:$V$996,""),""),IFNA(_xlfn.XLOOKUP(A43,PAGOS!$A$2:$A$996,PAGOS!$Y$2:$Y$996,""),""),IFNA(_xlfn.XLOOKUP(A43,PAGOS!$A$2:$A$996,PAGOS!$AB$2:$AB$996,""),""),IFNA(_xlfn.XLOOKUP(A43,PAGOS!$A$2:$A$996,PAGOS!$AE$2:$AE$996,""),""),IFNA(_xlfn.XLOOKUP(A43,PAGOS!$A$2:$A$996,PAGOS!$AH$2:$AH$996,""),""),IFNA(_xlfn.XLOOKUP(A43,PAGOS!$A$2:$A$996,PAGOS!$AK$2:$AK$996,""),"")),IF(abonos>0,abonos,pago)))} -> 950 | E43: =IFERROR(__xludf.DUMMYFUNCTION("IF(A43="""","""",LET(mes,DATE($E$2,MATCH($B$2,'ESTADO CONTABLE'!$A$5:$A$16,0),1),abonos,SUMIFS('ABONOS MENSUALIDADES'!$F$5:$F$500,'ABONOS MENSUALIDADES'!$C$5:$C$500,A43,'ABONOS MENSUALIDADES'!$D$5:$D$500,mes),metodoDirecto,CHOOSE(MATCH($B$2,'ESTADO CONTAB"&"LE'!$A$5:$A$16,0),IF(ISNUMBER(D43),""POR CLASIFICAR"",""""),IFNA(XLOOKUP(A43,PAGOS!$A$2:$A$996,PAGOS!$H$2:$H$996,""""),""""),IFNA(XLOOKUP(A43,PAGOS!$A$2:$A$996,PAGOS!$K$2:$K$996,""""),""""),IFNA(XLOOKUP(A43,PAGOS!$A$2:$A$996,PAGOS!$N$2:$N$996,""""),""""),"&"IFNA(XLOOKUP(A43,PAGOS!$A$2:$A$996,PAGOS!$Q$2:$Q$996,""""),""""),IFNA(XLOOKUP(A43,PAGOS!$A$2:$A$996,PAGOS!$T$2:$T$996,""""),""""),IFNA(XLOOKUP(A43,PAGOS!$A$2:$A$996,PAGOS!$W$2:$W$996,""""),""""),IFNA(XLOOKUP(A43,PAGOS!$A$2:$A$996,PAGOS!$Z$2:$Z$996,""""),"&"""""),IFNA(XLOOKUP(A43,PAGOS!$A$2:$A$996,PAGOS!$AC$2:$AC$996,""""),""""),IFNA(XLOOKUP(A43,PAGOS!$A$2:$A$996,PAGOS!$AF$2:$AF$996,""""),""""),IFNA(XLOOKUP(A43,PAGOS!$A$2:$A$996,PAGOS!$AI$2:$AI$996,""""),""""),IFNA(XLOOKUP(A43,PAGOS!$A$2:$A$996,PAGOS!$AL$2:$"&"AL$996,""""),"""")),IF(abonos>0,IFERROR(TEXTJOIN("" + "",TRUE,UNIQUE(FILTER('ABONOS MENSUALIDADES'!$E$5:$E$500,'ABONOS MENSUALIDADES'!$C$5:$C$500=A43,'ABONOS MENSUALIDADES'!$D$5:$D$500=mes))),""""),metodoDirecto)))"),"TERMINAL") -> TERMINAL | F43: {=IF(A43="","",LET(mes,DATE($E$2,MATCH($B$2,'ESTADO CONTABLE'!$A$5:$A$16,0),1),cobrarDesde,IFERROR(INDEX('BASE DE DATOSS'!I:I,ROW()-13),""),pausada,SUMPRODUCT((UPPER(TRIM('PAUSAS MENSUALIDADES'!$A$5:$A$500))=UPPER(TRIM(A43)))*('PAUSAS MENSUALIDADES'!$B$5:$B$500=mes)*(UPPER(TRIM('PAUSAS MENSUALIDADES'!$D$5:$D$500))="APLICAR"))>0,abonoActivo,SUMIFS('ABONOS MENSUALIDADES'!$F$5:$F$500,'ABONOS MENSUALIDADES'!$C$5:$C$500,A43,'ABONOS MENSUALIDADES'!$D$5:$D$500,mes,'ABONOS MENSUALIDADES'!$G$5:$G$500,"<>*CONSOLIDADO EN PAGOS*")>0,esperadaBruta,MAX(IFNA(VLOOKUP(B43,COSTOS!$A$3:$B$13,2,FALSE),0)-150,0),IF(AND(cobrarDesde<>"",mes<cobrarDesde),"AÚN NO INICIA",IF(pausada,"PAUSADA",IF(AND(abonoActivo,COUNTIFS('ABONOS MENSUALIDADES'!$C$5:$C$500,A43,'ABONOS MENSUALIDADES'!$D$5:$D$500,mes,'ABONOS MENSUALIDADES'!$G$5:$G$500,"*MENSUALIDAD LIQUIDADA*")=0),"ABONO",IF(N(D43)>=esperadaBruta,"COBRADA",IF(N(D43)>0,"ABONO","PENDIENTE")))))))} -> COBRADA | G43: {=IF(A43="","",IFERROR(INDEX('BASE DE DATOSS'!I:I,ROW()-13),""))} -> 46082
A44: {=IFERROR(INDEX('BASE DE DATOSS'!A:A,ROW()-13),"")} -> CINTHIA MICHELLE CAZARES GUTIERREZ | B44: {=IF(A44="","",IFERROR(INDEX('BASE DE DATOSS'!C:C,ROW()-13),""))} -> KIDS 1 | C44: {=IF(A44="","",LET(mes,DATE($E$2,MATCH($B$2,'ESTADO CONTABLE'!$A$5:$A$16,0),1),cobrarDesde,IFERROR(INDEX('BASE DE DATOSS'!I:I,ROW()-13),""),pausada,SUMPRODUCT((UPPER(TRIM('PAUSAS MENSUALIDADES'!$A$5:$A$500))=UPPER(TRIM(A44)))*('PAUSAS MENSUALIDADES'!$B$5:$B$500=mes)*(UPPER(TRIM('PAUSAS MENSUALIDADES'!$D$5:$D$500))="APLICAR"))>0,IF(OR(AND(cobrarDesde<>"",mes<cobrarDesde),pausada),0,MAX(IFNA(VLOOKUP(B44,COSTOS!$A$3:$B$13,2,FALSE),0)-150,0)/1.16)))} -> 818.96552 | D44: {=IF(A44="","",LET(mes,DATE($E$2,MATCH($B$2,'ESTADO CONTABLE'!$A$5:$A$16,0),1),abonos,SUMIFS('ABONOS MENSUALIDADES'!$F$5:$F$500,'ABONOS MENSUALIDADES'!$C$5:$C$500,A44,'ABONOS MENSUALIDADES'!$D$5:$D$500,mes),pago,CHOOSE(MATCH($B$2,'ESTADO CONTABLE'!$A$5:$A$16,0),IFNA(_xlfn.XLOOKUP(A44,PAGOS!$A$2:$A$996,PAGOS!$E$2:$E$996,""),""),IFNA(_xlfn.XLOOKUP(A44,PAGOS!$A$2:$A$996,PAGOS!$G$2:$G$996,""),""),IFNA(_xlfn.XLOOKUP(A44,PAGOS!$A$2:$A$996,PAGOS!$J$2:$J$996,""),""),IFNA(_xlfn.XLOOKUP(A44,PAGOS!$A$2:$A$996,PAGOS!$M$2:$M$996,""),""),IFNA(_xlfn.XLOOKUP(A44,PAGOS!$A$2:$A$996,PAGOS!$P$2:$P$996,""),""),IFNA(_xlfn.XLOOKUP(A44,PAGOS!$A$2:$A$996,PAGOS!$S$2:$S$996,""),""),IFNA(_xlfn.XLOOKUP(A44,PAGOS!$A$2:$A$996,PAGOS!$V$2:$V$996,""),""),IFNA(_xlfn.XLOOKUP(A44,PAGOS!$A$2:$A$996,PAGOS!$Y$2:$Y$996,""),""),IFNA(_xlfn.XLOOKUP(A44,PAGOS!$A$2:$A$996,PAGOS!$AB$2:$AB$996,""),""),IFNA(_xlfn.XLOOKUP(A44,PAGOS!$A$2:$A$996,PAGOS!$AE$2:$AE$996,""),""),IFNA(_xlfn.XLOOKUP(A44,PAGOS!$A$2:$A$996,PAGOS!$AH$2:$AH$996,""),""),IFNA(_xlfn.XLOOKUP(A44,PAGOS!$A$2:$A$996,PAGOS!$AK$2:$AK$996,""),"")),IF(abonos>0,abonos,pago)))} -> 1100 | E44: =IFERROR(__xludf.DUMMYFUNCTION("IF(A44="""","""",LET(mes,DATE($E$2,MATCH($B$2,'ESTADO CONTABLE'!$A$5:$A$16,0),1),abonos,SUMIFS('ABONOS MENSUALIDADES'!$F$5:$F$500,'ABONOS MENSUALIDADES'!$C$5:$C$500,A44,'ABONOS MENSUALIDADES'!$D$5:$D$500,mes),metodoDirecto,CHOOSE(MATCH($B$2,'ESTADO CONTAB"&"LE'!$A$5:$A$16,0),IF(ISNUMBER(D44),""POR CLASIFICAR"",""""),IFNA(XLOOKUP(A44,PAGOS!$A$2:$A$996,PAGOS!$H$2:$H$996,""""),""""),IFNA(XLOOKUP(A44,PAGOS!$A$2:$A$996,PAGOS!$K$2:$K$996,""""),""""),IFNA(XLOOKUP(A44,PAGOS!$A$2:$A$996,PAGOS!$N$2:$N$996,""""),""""),"&"IFNA(XLOOKUP(A44,PAGOS!$A$2:$A$996,PAGOS!$Q$2:$Q$996,""""),""""),IFNA(XLOOKUP(A44,PAGOS!$A$2:$A$996,PAGOS!$T$2:$T$996,""""),""""),IFNA(XLOOKUP(A44,PAGOS!$A$2:$A$996,PAGOS!$W$2:$W$996,""""),""""),IFNA(XLOOKUP(A44,PAGOS!$A$2:$A$996,PAGOS!$Z$2:$Z$996,""""),"&"""""),IFNA(XLOOKUP(A44,PAGOS!$A$2:$A$996,PAGOS!$AC$2:$AC$996,""""),""""),IFNA(XLOOKUP(A44,PAGOS!$A$2:$A$996,PAGOS!$AF$2:$AF$996,""""),""""),IFNA(XLOOKUP(A44,PAGOS!$A$2:$A$996,PAGOS!$AI$2:$AI$996,""""),""""),IFNA(XLOOKUP(A44,PAGOS!$A$2:$A$996,PAGOS!$AL$2:$"&"AL$996,""""),"""")),IF(abonos>0,IFERROR(TEXTJOIN("" + "",TRUE,UNIQUE(FILTER('ABONOS MENSUALIDADES'!$E$5:$E$500,'ABONOS MENSUALIDADES'!$C$5:$C$500=A44,'ABONOS MENSUALIDADES'!$D$5:$D$500=mes))),""""),metodoDirecto)))"),"TRANSFERENCIA") -> TRANSFERENCIA | F44: {=IF(A44="","",LET(mes,DATE($E$2,MATCH($B$2,'ESTADO CONTABLE'!$A$5:$A$16,0),1),cobrarDesde,IFERROR(INDEX('BASE DE DATOSS'!I:I,ROW()-13),""),pausada,SUMPRODUCT((UPPER(TRIM('PAUSAS MENSUALIDADES'!$A$5:$A$500))=UPPER(TRIM(A44)))*('PAUSAS MENSUALIDADES'!$B$5:$B$500=mes)*(UPPER(TRIM('PAUSAS MENSUALIDADES'!$D$5:$D$500))="APLICAR"))>0,abonoActivo,SUMIFS('ABONOS MENSUALIDADES'!$F$5:$F$500,'ABONOS MENSUALIDADES'!$C$5:$C$500,A44,'ABONOS MENSUALIDADES'!$D$5:$D$500,mes,'ABONOS MENSUALIDADES'!$G$5:$G$500,"<>*CONSOLIDADO EN PAGOS*")>0,esperadaBruta,MAX(IFNA(VLOOKUP(B44,COSTOS!$A$3:$B$13,2,FALSE),0)-150,0),IF(AND(cobrarDesde<>"",mes<cobrarDesde),"AÚN NO INICIA",IF(pausada,"PAUSADA",IF(AND(abonoActivo,COUNTIFS('ABONOS MENSUALIDADES'!$C$5:$C$500,A44,'ABONOS MENSUALIDADES'!$D$5:$D$500,mes,'ABONOS MENSUALIDADES'!$G$5:$G$500,"*MENSUALIDAD LIQUIDADA*")=0),"ABONO",IF(N(D44)>=esperadaBruta,"COBRADA",IF(N(D44)>0,"ABONO","PENDIENTE")))))))} -> COBRADA | G44: {=IF(A44="","",IFERROR(INDEX('BASE DE DATOSS'!I:I,ROW()-13),""))} -> 46113
A45: {=IFERROR(INDEX('BASE DE DATOSS'!A:A,ROW()-13),"")} -> ALLISON AMEZCUA LUNA | B45: {=IF(A45="","",IFERROR(INDEX('BASE DE DATOSS'!C:C,ROW()-13),""))} -> JR 2 | C45: {=IF(A45="","",LET(mes,DATE($E$2,MATCH($B$2,'ESTADO CONTABLE'!$A$5:$A$16,0),1),cobrarDesde,IFERROR(INDEX('BASE DE DATOSS'!I:I,ROW()-13),""),pausada,SUMPRODUCT((UPPER(TRIM('PAUSAS MENSUALIDADES'!$A$5:$A$500))=UPPER(TRIM(A45)))*('PAUSAS MENSUALIDADES'!$B$5:$B$500=mes)*(UPPER(TRIM('PAUSAS MENSUALIDADES'!$D$5:$D$500))="APLICAR"))>0,IF(OR(AND(cobrarDesde<>"",mes<cobrarDesde),pausada),0,MAX(IFNA(VLOOKUP(B45,COSTOS!$A$3:$B$13,2,FALSE),0)-150,0)/1.16)))} -> 689.65517 | D45: {=IF(A45="","",LET(mes,DATE($E$2,MATCH($B$2,'ESTADO CONTABLE'!$A$5:$A$16,0),1),abonos,SUMIFS('ABONOS MENSUALIDADES'!$F$5:$F$500,'ABONOS MENSUALIDADES'!$C$5:$C$500,A45,'ABONOS MENSUALIDADES'!$D$5:$D$500,mes),pago,CHOOSE(MATCH($B$2,'ESTADO CONTABLE'!$A$5:$A$16,0),IFNA(_xlfn.XLOOKUP(A45,PAGOS!$A$2:$A$996,PAGOS!$E$2:$E$996,""),""),IFNA(_xlfn.XLOOKUP(A45,PAGOS!$A$2:$A$996,PAGOS!$G$2:$G$996,""),""),IFNA(_xlfn.XLOOKUP(A45,PAGOS!$A$2:$A$996,PAGOS!$J$2:$J$996,""),""),IFNA(_xlfn.XLOOKUP(A45,PAGOS!$A$2:$A$996,PAGOS!$M$2:$M$996,""),""),IFNA(_xlfn.XLOOKUP(A45,PAGOS!$A$2:$A$996,PAGOS!$P$2:$P$996,""),""),IFNA(_xlfn.XLOOKUP(A45,PAGOS!$A$2:$A$996,PAGOS!$S$2:$S$996,""),""),IFNA(_xlfn.XLOOKUP(A45,PAGOS!$A$2:$A$996,PAGOS!$V$2:$V$996,""),""),IFNA(_xlfn.XLOOKUP(A45,PAGOS!$A$2:$A$996,PAGOS!$Y$2:$Y$996,""),""),IFNA(_xlfn.XLOOKUP(A45,PAGOS!$A$2:$A$996,PAGOS!$AB$2:$AB$996,""),""),IFNA(_xlfn.XLOOKUP(A45,PAGOS!$A$2:$A$996,PAGOS!$AE$2:$AE$996,""),""),IFNA(_xlfn.XLOOKUP(A45,PAGOS!$A$2:$A$996,PAGOS!$AH$2:$AH$996,""),""),IFNA(_xlfn.XLOOKUP(A45,PAGOS!$A$2:$A$996,PAGOS!$AK$2:$AK$996,""),"")),IF(abonos>0,abonos,pago)))} -> 950 | E45: =IFERROR(__xludf.DUMMYFUNCTION("IF(A45="""","""",LET(mes,DATE($E$2,MATCH($B$2,'ESTADO CONTABLE'!$A$5:$A$16,0),1),abonos,SUMIFS('ABONOS MENSUALIDADES'!$F$5:$F$500,'ABONOS MENSUALIDADES'!$C$5:$C$500,A45,'ABONOS MENSUALIDADES'!$D$5:$D$500,mes),metodoDirecto,CHOOSE(MATCH($B$2,'ESTADO CONTAB"&"LE'!$A$5:$A$16,0),IF(ISNUMBER(D45),""POR CLASIFICAR"",""""),IFNA(XLOOKUP(A45,PAGOS!$A$2:$A$996,PAGOS!$H$2:$H$996,""""),""""),IFNA(XLOOKUP(A45,PAGOS!$A$2:$A$996,PAGOS!$K$2:$K$996,""""),""""),IFNA(XLOOKUP(A45,PAGOS!$A$2:$A$996,PAGOS!$N$2:$N$996,""""),""""),"&"IFNA(XLOOKUP(A45,PAGOS!$A$2:$A$996,PAGOS!$Q$2:$Q$996,""""),""""),IFNA(XLOOKUP(A45,PAGOS!$A$2:$A$996,PAGOS!$T$2:$T$996,""""),""""),IFNA(XLOOKUP(A45,PAGOS!$A$2:$A$996,PAGOS!$W$2:$W$996,""""),""""),IFNA(XLOOKUP(A45,PAGOS!$A$2:$A$996,PAGOS!$Z$2:$Z$996,""""),"&"""""),IFNA(XLOOKUP(A45,PAGOS!$A$2:$A$996,PAGOS!$AC$2:$AC$996,""""),""""),IFNA(XLOOKUP(A45,PAGOS!$A$2:$A$996,PAGOS!$AF$2:$AF$996,""""),""""),IFNA(XLOOKUP(A45,PAGOS!$A$2:$A$996,PAGOS!$AI$2:$AI$996,""""),""""),IFNA(XLOOKUP(A45,PAGOS!$A$2:$A$996,PAGOS!$AL$2:$"&"AL$996,""""),"""")),IF(abonos>0,IFERROR(TEXTJOIN("" + "",TRUE,UNIQUE(FILTER('ABONOS MENSUALIDADES'!$E$5:$E$500,'ABONOS MENSUALIDADES'!$C$5:$C$500=A45,'ABONOS MENSUALIDADES'!$D$5:$D$500=mes))),""""),metodoDirecto)))"),"TRANSFERENCIA + EFECTIVO") -> TRANSFERENCIA + EFECTIVO | F45: {=IF(A45="","",LET(mes,DATE($E$2,MATCH($B$2,'ESTADO CONTABLE'!$A$5:$A$16,0),1),cobrarDesde,IFERROR(INDEX('BASE DE DATOSS'!I:I,ROW()-13),""),pausada,SUMPRODUCT((UPPER(TRIM('PAUSAS MENSUALIDADES'!$A$5:$A$500))=UPPER(TRIM(A45)))*('PAUSAS MENSUALIDADES'!$B$5:$B$500=mes)*(UPPER(TRIM('PAUSAS MENSUALIDADES'!$D$5:$D$500))="APLICAR"))>0,abonoActivo,SUMIFS('ABONOS MENSUALIDADES'!$F$5:$F$500,'ABONOS MENSUALIDADES'!$C$5:$C$500,A45,'ABONOS MENSUALIDADES'!$D$5:$D$500,mes,'ABONOS MENSUALIDADES'!$G$5:$G$500,"<>*CONSOLIDADO EN PAGOS*")>0,esperadaBruta,MAX(IFNA(VLOOKUP(B45,COSTOS!$A$3:$B$13,2,FALSE),0)-150,0),IF(AND(cobrarDesde<>"",mes<cobrarDesde),"AÚN NO INICIA",IF(pausada,"PAUSADA",IF(AND(abonoActivo,COUNTIFS('ABONOS MENSUALIDADES'!$C$5:$C$500,A45,'ABONOS MENSUALIDADES'!$D$5:$D$500,mes,'ABONOS MENSUALIDADES'!$G$5:$G$500,"*MENSUALIDAD LIQUIDADA*")=0),"ABONO",IF(N(D45)>=esperadaBruta,"COBRADA",IF(N(D45)>0,"ABONO","PENDIENTE")))))))} -> COBRADA | G45: {=IF(A45="","",IFERROR(INDEX('BASE DE DATOSS'!I:I,ROW()-13),""))} -> 46113
A46: {=IFERROR(INDEX('BASE DE DATOSS'!A:A,ROW()-13),"")} -> RENATA AMEZCUA LUNA | B46: {=IF(A46="","",IFERROR(INDEX('BASE DE DATOSS'!C:C,ROW()-13),""))} -> JR 2 | C46: {=IF(A46="","",LET(mes,DATE($E$2,MATCH($B$2,'ESTADO CONTABLE'!$A$5:$A$16,0),1),cobrarDesde,IFERROR(INDEX('BASE DE DATOSS'!I:I,ROW()-13),""),pausada,SUMPRODUCT((UPPER(TRIM('PAUSAS MENSUALIDADES'!$A$5:$A$500))=UPPER(TRIM(A46)))*('PAUSAS MENSUALIDADES'!$B$5:$B$500=mes)*(UPPER(TRIM('PAUSAS MENSUALIDADES'!$D$5:$D$500))="APLICAR"))>0,IF(OR(AND(cobrarDesde<>"",mes<cobrarDesde),pausada),0,MAX(IFNA(VLOOKUP(B46,COSTOS!$A$3:$B$13,2,FALSE),0)-150,0)/1.16)))} -> 689.65517 | D46: {=IF(A46="","",LET(mes,DATE($E$2,MATCH($B$2,'ESTADO CONTABLE'!$A$5:$A$16,0),1),abonos,SUMIFS('ABONOS MENSUALIDADES'!$F$5:$F$500,'ABONOS MENSUALIDADES'!$C$5:$C$500,A46,'ABONOS MENSUALIDADES'!$D$5:$D$500,mes),pago,CHOOSE(MATCH($B$2,'ESTADO CONTABLE'!$A$5:$A$16,0),IFNA(_xlfn.XLOOKUP(A46,PAGOS!$A$2:$A$996,PAGOS!$E$2:$E$996,""),""),IFNA(_xlfn.XLOOKUP(A46,PAGOS!$A$2:$A$996,PAGOS!$G$2:$G$996,""),""),IFNA(_xlfn.XLOOKUP(A46,PAGOS!$A$2:$A$996,PAGOS!$J$2:$J$996,""),""),IFNA(_xlfn.XLOOKUP(A46,PAGOS!$A$2:$A$996,PAGOS!$M$2:$M$996,""),""),IFNA(_xlfn.XLOOKUP(A46,PAGOS!$A$2:$A$996,PAGOS!$P$2:$P$996,""),""),IFNA(_xlfn.XLOOKUP(A46,PAGOS!$A$2:$A$996,PAGOS!$S$2:$S$996,""),""),IFNA(_xlfn.XLOOKUP(A46,PAGOS!$A$2:$A$996,PAGOS!$V$2:$V$996,""),""),IFNA(_xlfn.XLOOKUP(A46,PAGOS!$A$2:$A$996,PAGOS!$Y$2:$Y$996,""),""),IFNA(_xlfn.XLOOKUP(A46,PAGOS!$A$2:$A$996,PAGOS!$AB$2:$AB$996,""),""),IFNA(_xlfn.XLOOKUP(A46,PAGOS!$A$2:$A$996,PAGOS!$AE$2:$AE$996,""),""),IFNA(_xlfn.XLOOKUP(A46,PAGOS!$A$2:$A$996,PAGOS!$AH$2:$AH$996,""),""),IFNA(_xlfn.XLOOKUP(A46,PAGOS!$A$2:$A$996,PAGOS!$AK$2:$AK$996,""),"")),IF(abonos>0,abonos,pago)))} -> 950 | E46: =IFERROR(__xludf.DUMMYFUNCTION("IF(A46="""","""",LET(mes,DATE($E$2,MATCH($B$2,'ESTADO CONTABLE'!$A$5:$A$16,0),1),abonos,SUMIFS('ABONOS MENSUALIDADES'!$F$5:$F$500,'ABONOS MENSUALIDADES'!$C$5:$C$500,A46,'ABONOS MENSUALIDADES'!$D$5:$D$500,mes),metodoDirecto,CHOOSE(MATCH($B$2,'ESTADO CONTAB"&"LE'!$A$5:$A$16,0),IF(ISNUMBER(D46),""POR CLASIFICAR"",""""),IFNA(XLOOKUP(A46,PAGOS!$A$2:$A$996,PAGOS!$H$2:$H$996,""""),""""),IFNA(XLOOKUP(A46,PAGOS!$A$2:$A$996,PAGOS!$K$2:$K$996,""""),""""),IFNA(XLOOKUP(A46,PAGOS!$A$2:$A$996,PAGOS!$N$2:$N$996,""""),""""),"&"IFNA(XLOOKUP(A46,PAGOS!$A$2:$A$996,PAGOS!$Q$2:$Q$996,""""),""""),IFNA(XLOOKUP(A46,PAGOS!$A$2:$A$996,PAGOS!$T$2:$T$996,""""),""""),IFNA(XLOOKUP(A46,PAGOS!$A$2:$A$996,PAGOS!$W$2:$W$996,""""),""""),IFNA(XLOOKUP(A46,PAGOS!$A$2:$A$996,PAGOS!$Z$2:$Z$996,""""),"&"""""),IFNA(XLOOKUP(A46,PAGOS!$A$2:$A$996,PAGOS!$AC$2:$AC$996,""""),""""),IFNA(XLOOKUP(A46,PAGOS!$A$2:$A$996,PAGOS!$AF$2:$AF$996,""""),""""),IFNA(XLOOKUP(A46,PAGOS!$A$2:$A$996,PAGOS!$AI$2:$AI$996,""""),""""),IFNA(XLOOKUP(A46,PAGOS!$A$2:$A$996,PAGOS!$AL$2:$"&"AL$996,""""),"""")),IF(abonos>0,IFERROR(TEXTJOIN("" + "",TRUE,UNIQUE(FILTER('ABONOS MENSUALIDADES'!$E$5:$E$500,'ABONOS MENSUALIDADES'!$C$5:$C$500=A46,'ABONOS MENSUALIDADES'!$D$5:$D$500=mes))),""""),metodoDirecto)))"),"TRANSFERENCIA + EFECTIVO") -> TRANSFERENCIA + EFECTIVO | F46: {=IF(A46="","",LET(mes,DATE($E$2,MATCH($B$2,'ESTADO CONTABLE'!$A$5:$A$16,0),1),cobrarDesde,IFERROR(INDEX('BASE DE DATOSS'!I:I,ROW()-13),""),pausada,SUMPRODUCT((UPPER(TRIM('PAUSAS MENSUALIDADES'!$A$5:$A$500))=UPPER(TRIM(A46)))*('PAUSAS MENSUALIDADES'!$B$5:$B$500=mes)*(UPPER(TRIM('PAUSAS MENSUALIDADES'!$D$5:$D$500))="APLICAR"))>0,abonoActivo,SUMIFS('ABONOS MENSUALIDADES'!$F$5:$F$500,'ABONOS MENSUALIDADES'!$C$5:$C$500,A46,'ABONOS MENSUALIDADES'!$D$5:$D$500,mes,'ABONOS MENSUALIDADES'!$G$5:$G$500,"<>*CONSOLIDADO EN PAGOS*")>0,esperadaBruta,MAX(IFNA(VLOOKUP(B46,COSTOS!$A$3:$B$13,2,FALSE),0)-150,0),IF(AND(cobrarDesde<>"",mes<cobrarDesde),"AÚN NO INICIA",IF(pausada,"PAUSADA",IF(AND(abonoActivo,COUNTIFS('ABONOS MENSUALIDADES'!$C$5:$C$500,A46,'ABONOS MENSUALIDADES'!$D$5:$D$500,mes,'ABONOS MENSUALIDADES'!$G$5:$G$500,"*MENSUALIDAD LIQUIDADA*")=0),"ABONO",IF(N(D46)>=esperadaBruta,"COBRADA",IF(N(D46)>0,"ABONO","PENDIENTE")))))))} -> COBRADA | G46: {=IF(A46="","",IFERROR(INDEX('BASE DE DATOSS'!I:I,ROW()-13),""))} -> 46113
A47: {=IFERROR(INDEX('BASE DE DATOSS'!A:A,ROW()-13),"")} -> IRIS SAORI LOZANO PADILLA | B47: {=IF(A47="","",IFERROR(INDEX('BASE DE DATOSS'!C:C,ROW()-13),""))} -> JR 2 | C47: {=IF(A47="","",LET(mes,DATE($E$2,MATCH($B$2,'ESTADO CONTABLE'!$A$5:$A$16,0),1),cobrarDesde,IFERROR(INDEX('BASE DE DATOSS'!I:I,ROW()-13),""),pausada,SUMPRODUCT((UPPER(TRIM('PAUSAS MENSUALIDADES'!$A$5:$A$500))=UPPER(TRIM(A47)))*('PAUSAS MENSUALIDADES'!$B$5:$B$500=mes)*(UPPER(TRIM('PAUSAS MENSUALIDADES'!$D$5:$D$500))="APLICAR"))>0,IF(OR(AND(cobrarDesde<>"",mes<cobrarDesde),pausada),0,MAX(IFNA(VLOOKUP(B47,COSTOS!$A$3:$B$13,2,FALSE),0)-150,0)/1.16)))} -> 689.65517 | D47: {=IF(A47="","",LET(mes,DATE($E$2,MATCH($B$2,'ESTADO CONTABLE'!$A$5:$A$16,0),1),abonos,SUMIFS('ABONOS MENSUALIDADES'!$F$5:$F$500,'ABONOS MENSUALIDADES'!$C$5:$C$500,A47,'ABONOS MENSUALIDADES'!$D$5:$D$500,mes),pago,CHOOSE(MATCH($B$2,'ESTADO CONTABLE'!$A$5:$A$16,0),IFNA(_xlfn.XLOOKUP(A47,PAGOS!$A$2:$A$996,PAGOS!$E$2:$E$996,""),""),IFNA(_xlfn.XLOOKUP(A47,PAGOS!$A$2:$A$996,PAGOS!$G$2:$G$996,""),""),IFNA(_xlfn.XLOOKUP(A47,PAGOS!$A$2:$A$996,PAGOS!$J$2:$J$996,""),""),IFNA(_xlfn.XLOOKUP(A47,PAGOS!$A$2:$A$996,PAGOS!$M$2:$M$996,""),""),IFNA(_xlfn.XLOOKUP(A47,PAGOS!$A$2:$A$996,PAGOS!$P$2:$P$996,""),""),IFNA(_xlfn.XLOOKUP(A47,PAGOS!$A$2:$A$996,PAGOS!$S$2:$S$996,""),""),IFNA(_xlfn.XLOOKUP(A47,PAGOS!$A$2:$A$996,PAGOS!$V$2:$V$996,""),""),IFNA(_xlfn.XLOOKUP(A47,PAGOS!$A$2:$A$996,PAGOS!$Y$2:$Y$996,""),""),IFNA(_xlfn.XLOOKUP(A47,PAGOS!$A$2:$A$996,PAGOS!$AB$2:$AB$996,""),""),IFNA(_xlfn.XLOOKUP(A47,PAGOS!$A$2:$A$996,PAGOS!$AE$2:$AE$996,""),""),IFNA(_xlfn.XLOOKUP(A47,PAGOS!$A$2:$A$996,PAGOS!$AH$2:$AH$996,""),""),IFNA(_xlfn.XLOOKUP(A47,PAGOS!$A$2:$A$996,PAGOS!$AK$2:$AK$996,""),"")),IF(abonos>0,abonos,pago)))} -> 800 | E47: =IFERROR(__xludf.DUMMYFUNCTION("IF(A47="""","""",LET(mes,DATE($E$2,MATCH($B$2,'ESTADO CONTABLE'!$A$5:$A$16,0),1),abonos,SUMIFS('ABONOS MENSUALIDADES'!$F$5:$F$500,'ABONOS MENSUALIDADES'!$C$5:$C$500,A47,'ABONOS MENSUALIDADES'!$D$5:$D$500,mes),metodoDirecto,CHOOSE(MATCH($B$2,'ESTADO CONTAB"&"LE'!$A$5:$A$16,0),IF(ISNUMBER(D47),""POR CLASIFICAR"",""""),IFNA(XLOOKUP(A47,PAGOS!$A$2:$A$996,PAGOS!$H$2:$H$996,""""),""""),IFNA(XLOOKUP(A47,PAGOS!$A$2:$A$996,PAGOS!$K$2:$K$996,""""),""""),IFNA(XLOOKUP(A47,PAGOS!$A$2:$A$996,PAGOS!$N$2:$N$996,""""),""""),"&"IFNA(XLOOKUP(A47,PAGOS!$A$2:$A$996,PAGOS!$Q$2:$Q$996,""""),""""),IFNA(XLOOKUP(A47,PAGOS!$A$2:$A$996,PAGOS!$T$2:$T$996,""""),""""),IFNA(XLOOKUP(A47,PAGOS!$A$2:$A$996,PAGOS!$W$2:$W$996,""""),""""),IFNA(XLOOKUP(A47,PAGOS!$A$2:$A$996,PAGOS!$Z$2:$Z$996,""""),"&"""""),IFNA(XLOOKUP(A47,PAGOS!$A$2:$A$996,PAGOS!$AC$2:$AC$996,""""),""""),IFNA(XLOOKUP(A47,PAGOS!$A$2:$A$996,PAGOS!$AF$2:$AF$996,""""),""""),IFNA(XLOOKUP(A47,PAGOS!$A$2:$A$996,PAGOS!$AI$2:$AI$996,""""),""""),IFNA(XLOOKUP(A47,PAGOS!$A$2:$A$996,PAGOS!$AL$2:$"&"AL$996,""""),"""")),IF(abonos>0,IFERROR(TEXTJOIN("" + "",TRUE,UNIQUE(FILTER('ABONOS MENSUALIDADES'!$E$5:$E$500,'ABONOS MENSUALIDADES'!$C$5:$C$500=A47,'ABONOS MENSUALIDADES'!$D$5:$D$500=mes))),""""),metodoDirecto)))"),"EFECTIVO") -> EFECTIVO | F47: {=IF(A47="","",LET(mes,DATE($E$2,MATCH($B$2,'ESTADO CONTABLE'!$A$5:$A$16,0),1),cobrarDesde,IFERROR(INDEX('BASE DE DATOSS'!I:I,ROW()-13),""),pausada,SUMPRODUCT((UPPER(TRIM('PAUSAS MENSUALIDADES'!$A$5:$A$500))=UPPER(TRIM(A47)))*('PAUSAS MENSUALIDADES'!$B$5:$B$500=mes)*(UPPER(TRIM('PAUSAS MENSUALIDADES'!$D$5:$D$500))="APLICAR"))>0,abonoActivo,SUMIFS('ABONOS MENSUALIDADES'!$F$5:$F$500,'ABONOS MENSUALIDADES'!$C$5:$C$500,A47,'ABONOS MENSUALIDADES'!$D$5:$D$500,mes,'ABONOS MENSUALIDADES'!$G$5:$G$500,"<>*CONSOLIDADO EN PAGOS*")>0,esperadaBruta,MAX(IFNA(VLOOKUP(B47,COSTOS!$A$3:$B$13,2,FALSE),0)-150,0),IF(AND(cobrarDesde<>"",mes<cobrarDesde),"AÚN NO INICIA",IF(pausada,"PAUSADA",IF(AND(abonoActivo,COUNTIFS('ABONOS MENSUALIDADES'!$C$5:$C$500,A47,'ABONOS MENSUALIDADES'!$D$5:$D$500,mes,'ABONOS MENSUALIDADES'!$G$5:$G$500,"*MENSUALIDAD LIQUIDADA*")=0),"ABONO",IF(N(D47)>=esperadaBruta,"COBRADA",IF(N(D47)>0,"ABONO","PENDIENTE")))))))} -> COBRADA | G47: {=IF(A47="","",IFERROR(INDEX('BASE DE DATOSS'!I:I,ROW()-13),""))} -> 46113
A48: {=IFERROR(INDEX('BASE DE DATOSS'!A:A,ROW()-13),"")} -> IRKA VICTORIA GARCIA NAVARRO | B48: {=IF(A48="","",IFERROR(INDEX('BASE DE DATOSS'!C:C,ROW()-13),""))} -> JR 1 | C48: {=IF(A48="","",LET(mes,DATE($E$2,MATCH($B$2,'ESTADO CONTABLE'!$A$5:$A$16,0),1),cobrarDesde,IFERROR(INDEX('BASE DE DATOSS'!I:I,ROW()-13),""),pausada,SUMPRODUCT((UPPER(TRIM('PAUSAS MENSUALIDADES'!$A$5:$A$500))=UPPER(TRIM(A48)))*('PAUSAS MENSUALIDADES'!$B$5:$B$500=mes)*(UPPER(TRIM('PAUSAS MENSUALIDADES'!$D$5:$D$500))="APLICAR"))>0,IF(OR(AND(cobrarDesde<>"",mes<cobrarDesde),pausada),0,MAX(IFNA(VLOOKUP(B48,COSTOS!$A$3:$B$13,2,FALSE),0)-150,0)/1.16)))} -> 818.96552 | D48: {=IF(A48="","",LET(mes,DATE($E$2,MATCH($B$2,'ESTADO CONTABLE'!$A$5:$A$16,0),1),abonos,SUMIFS('ABONOS MENSUALIDADES'!$F$5:$F$500,'ABONOS MENSUALIDADES'!$C$5:$C$500,A48,'ABONOS MENSUALIDADES'!$D$5:$D$500,mes),pago,CHOOSE(MATCH($B$2,'ESTADO CONTABLE'!$A$5:$A$16,0),IFNA(_xlfn.XLOOKUP(A48,PAGOS!$A$2:$A$996,PAGOS!$E$2:$E$996,""),""),IFNA(_xlfn.XLOOKUP(A48,PAGOS!$A$2:$A$996,PAGOS!$G$2:$G$996,""),""),IFNA(_xlfn.XLOOKUP(A48,PAGOS!$A$2:$A$996,PAGOS!$J$2:$J$996,""),""),IFNA(_xlfn.XLOOKUP(A48,PAGOS!$A$2:$A$996,PAGOS!$M$2:$M$996,""),""),IFNA(_xlfn.XLOOKUP(A48,PAGOS!$A$2:$A$996,PAGOS!$P$2:$P$996,""),""),IFNA(_xlfn.XLOOKUP(A48,PAGOS!$A$2:$A$996,PAGOS!$S$2:$S$996,""),""),IFNA(_xlfn.XLOOKUP(A48,PAGOS!$A$2:$A$996,PAGOS!$V$2:$V$996,""),""),IFNA(_xlfn.XLOOKUP(A48,PAGOS!$A$2:$A$996,PAGOS!$Y$2:$Y$996,""),""),IFNA(_xlfn.XLOOKUP(A48,PAGOS!$A$2:$A$996,PAGOS!$AB$2:$AB$996,""),""),IFNA(_xlfn.XLOOKUP(A48,PAGOS!$A$2:$A$996,PAGOS!$AE$2:$AE$996,""),""),IFNA(_xlfn.XLOOKUP(A48,PAGOS!$A$2:$A$996,PAGOS!$AH$2:$AH$996,""),""),IFNA(_xlfn.XLOOKUP(A48,PAGOS!$A$2:$A$996,PAGOS!$AK$2:$AK$996,""),"")),IF(abonos>0,abonos,pago)))} -> 950 | E48: =IFERROR(__xludf.DUMMYFUNCTION("IF(A48="""","""",LET(mes,DATE($E$2,MATCH($B$2,'ESTADO CONTABLE'!$A$5:$A$16,0),1),abonos,SUMIFS('ABONOS MENSUALIDADES'!$F$5:$F$500,'ABONOS MENSUALIDADES'!$C$5:$C$500,A48,'ABONOS MENSUALIDADES'!$D$5:$D$500,mes),metodoDirecto,CHOOSE(MATCH($B$2,'ESTADO CONTAB"&"LE'!$A$5:$A$16,0),IF(ISNUMBER(D48),""POR CLASIFICAR"",""""),IFNA(XLOOKUP(A48,PAGOS!$A$2:$A$996,PAGOS!$H$2:$H$996,""""),""""),IFNA(XLOOKUP(A48,PAGOS!$A$2:$A$996,PAGOS!$K$2:$K$996,""""),""""),IFNA(XLOOKUP(A48,PAGOS!$A$2:$A$996,PAGOS!$N$2:$N$996,""""),""""),"&"IFNA(XLOOKUP(A48,PAGOS!$A$2:$A$996,PAGOS!$Q$2:$Q$996,""""),""""),IFNA(XLOOKUP(A48,PAGOS!$A$2:$A$996,PAGOS!$T$2:$T$996,""""),""""),IFNA(XLOOKUP(A48,PAGOS!$A$2:$A$996,PAGOS!$W$2:$W$996,""""),""""),IFNA(XLOOKUP(A48,PAGOS!$A$2:$A$996,PAGOS!$Z$2:$Z$996,""""),"&"""""),IFNA(XLOOKUP(A48,PAGOS!$A$2:$A$996,PAGOS!$AC$2:$AC$996,""""),""""),IFNA(XLOOKUP(A48,PAGOS!$A$2:$A$996,PAGOS!$AF$2:$AF$996,""""),""""),IFNA(XLOOKUP(A48,PAGOS!$A$2:$A$996,PAGOS!$AI$2:$AI$996,""""),""""),IFNA(XLOOKUP(A48,PAGOS!$A$2:$A$996,PAGOS!$AL$2:$"&"AL$996,""""),"""")),IF(abonos>0,IFERROR(TEXTJOIN("" + "",TRUE,UNIQUE(FILTER('ABONOS MENSUALIDADES'!$E$5:$E$500,'ABONOS MENSUALIDADES'!$C$5:$C$500=A48,'ABONOS MENSUALIDADES'!$D$5:$D$500=mes))),""""),metodoDirecto)))"),"TERMINAL") -> TERMINAL | F48: {=IF(A48="","",LET(mes,DATE($E$2,MATCH($B$2,'ESTADO CONTABLE'!$A$5:$A$16,0),1),cobrarDesde,IFERROR(INDEX('BASE DE DATOSS'!I:I,ROW()-13),""),pausada,SUMPRODUCT((UPPER(TRIM('PAUSAS MENSUALIDADES'!$A$5:$A$500))=UPPER(TRIM(A48)))*('PAUSAS MENSUALIDADES'!$B$5:$B$500=mes)*(UPPER(TRIM('PAUSAS MENSUALIDADES'!$D$5:$D$500))="APLICAR"))>0,abonoActivo,SUMIFS('ABONOS MENSUALIDADES'!$F$5:$F$500,'ABONOS MENSUALIDADES'!$C$5:$C$500,A48,'ABONOS MENSUALIDADES'!$D$5:$D$500,mes,'ABONOS MENSUALIDADES'!$G$5:$G$500,"<>*CONSOLIDADO EN PAGOS*")>0,esperadaBruta,MAX(IFNA(VLOOKUP(B48,COSTOS!$A$3:$B$13,2,FALSE),0)-150,0),IF(AND(cobrarDesde<>"",mes<cobrarDesde),"AÚN NO INICIA",IF(pausada,"PAUSADA",IF(AND(abonoActivo,COUNTIFS('ABONOS MENSUALIDADES'!$C$5:$C$500,A48,'ABONOS MENSUALIDADES'!$D$5:$D$500,mes,'ABONOS MENSUALIDADES'!$G$5:$G$500,"*MENSUALIDAD LIQUIDADA*")=0),"ABONO",IF(N(D48)>=esperadaBruta,"COBRADA",IF(N(D48)>0,"ABONO","PENDIENTE")))))))} -> COBRADA | G48: {=IF(A48="","",IFERROR(INDEX('BASE DE DATOSS'!I:I,ROW()-13),""))} -> 46113
A49: {=IFERROR(INDEX('BASE DE DATOSS'!A:A,ROW()-13),"")} -> BRENDA YUDITH CASTELL MARTINEZ | B49: {=IF(A49="","",IFERROR(INDEX('BASE DE DATOSS'!C:C,ROW()-13),""))} -> MATUTINO | C49: {=IF(A49="","",LET(mes,DATE($E$2,MATCH($B$2,'ESTADO CONTABLE'!$A$5:$A$16,0),1),cobrarDesde,IFERROR(INDEX('BASE DE DATOSS'!I:I,ROW()-13),""),pausada,SUMPRODUCT((UPPER(TRIM('PAUSAS MENSUALIDADES'!$A$5:$A$500))=UPPER(TRIM(A49)))*('PAUSAS MENSUALIDADES'!$B$5:$B$500=mes)*(UPPER(TRIM('PAUSAS MENSUALIDADES'!$D$5:$D$500))="APLICAR"))>0,IF(OR(AND(cobrarDesde<>"",mes<cobrarDesde),pausada),0,MAX(IFNA(VLOOKUP(B49,COSTOS!$A$3:$B$13,2,FALSE),0)-150,0)/1.16)))} -> 818.96552 | D49: {=IF(A49="","",LET(mes,DATE($E$2,MATCH($B$2,'ESTADO CONTABLE'!$A$5:$A$16,0),1),abonos,SUMIFS('ABONOS MENSUALIDADES'!$F$5:$F$500,'ABONOS MENSUALIDADES'!$C$5:$C$500,A49,'ABONOS MENSUALIDADES'!$D$5:$D$500,mes),pago,CHOOSE(MATCH($B$2,'ESTADO CONTABLE'!$A$5:$A$16,0),IFNA(_xlfn.XLOOKUP(A49,PAGOS!$A$2:$A$996,PAGOS!$E$2:$E$996,""),""),IFNA(_xlfn.XLOOKUP(A49,PAGOS!$A$2:$A$996,PAGOS!$G$2:$G$996,""),""),IFNA(_xlfn.XLOOKUP(A49,PAGOS!$A$2:$A$996,PAGOS!$J$2:$J$996,""),""),IFNA(_xlfn.XLOOKUP(A49,PAGOS!$A$2:$A$996,PAGOS!$M$2:$M$996,""),""),IFNA(_xlfn.XLOOKUP(A49,PAGOS!$A$2:$A$996,PAGOS!$P$2:$P$996,""),""),IFNA(_xlfn.XLOOKUP(A49,PAGOS!$A$2:$A$996,PAGOS!$S$2:$S$996,""),""),IFNA(_xlfn.XLOOKUP(A49,PAGOS!$A$2:$A$996,PAGOS!$V$2:$V$996,""),""),IFNA(_xlfn.XLOOKUP(A49,PAGOS!$A$2:$A$996,PAGOS!$Y$2:$Y$996,""),""),IFNA(_xlfn.XLOOKUP(A49,PAGOS!$A$2:$A$996,PAGOS!$AB$2:$AB$996,""),""),IFNA(_xlfn.XLOOKUP(A49,PAGOS!$A$2:$A$996,PAGOS!$AE$2:$AE$996,""),""),IFNA(_xlfn.XLOOKUP(A49,PAGOS!$A$2:$A$996,PAGOS!$AH$2:$AH$996,""),""),IFNA(_xlfn.XLOOKUP(A49,PAGOS!$A$2:$A$996,PAGOS!$AK$2:$AK$996,""),"")),IF(abonos>0,abonos,pago)))} -> 950 | E49: =IFERROR(__xludf.DUMMYFUNCTION("IF(A49="""","""",LET(mes,DATE($E$2,MATCH($B$2,'ESTADO CONTABLE'!$A$5:$A$16,0),1),abonos,SUMIFS('ABONOS MENSUALIDADES'!$F$5:$F$500,'ABONOS MENSUALIDADES'!$C$5:$C$500,A49,'ABONOS MENSUALIDADES'!$D$5:$D$500,mes),metodoDirecto,CHOOSE(MATCH($B$2,'ESTADO CONTAB"&"LE'!$A$5:$A$16,0),IF(ISNUMBER(D49),""POR CLASIFICAR"",""""),IFNA(XLOOKUP(A49,PAGOS!$A$2:$A$996,PAGOS!$H$2:$H$996,""""),""""),IFNA(XLOOKUP(A49,PAGOS!$A$2:$A$996,PAGOS!$K$2:$K$996,""""),""""),IFNA(XLOOKUP(A49,PAGOS!$A$2:$A$996,PAGOS!$N$2:$N$996,""""),""""),"&"IFNA(XLOOKUP(A49,PAGOS!$A$2:$A$996,PAGOS!$Q$2:$Q$996,""""),""""),IFNA(XLOOKUP(A49,PAGOS!$A$2:$A$996,PAGOS!$T$2:$T$996,""""),""""),IFNA(XLOOKUP(A49,PAGOS!$A$2:$A$996,PAGOS!$W$2:$W$996,""""),""""),IFNA(XLOOKUP(A49,PAGOS!$A$2:$A$996,PAGOS!$Z$2:$Z$996,""""),"&"""""),IFNA(XLOOKUP(A49,PAGOS!$A$2:$A$996,PAGOS!$AC$2:$AC$996,""""),""""),IFNA(XLOOKUP(A49,PAGOS!$A$2:$A$996,PAGOS!$AF$2:$AF$996,""""),""""),IFNA(XLOOKUP(A49,PAGOS!$A$2:$A$996,PAGOS!$AI$2:$AI$996,""""),""""),IFNA(XLOOKUP(A49,PAGOS!$A$2:$A$996,PAGOS!$AL$2:$"&"AL$996,""""),"""")),IF(abonos>0,IFERROR(TEXTJOIN("" + "",TRUE,UNIQUE(FILTER('ABONOS MENSUALIDADES'!$E$5:$E$500,'ABONOS MENSUALIDADES'!$C$5:$C$500=A49,'ABONOS MENSUALIDADES'!$D$5:$D$500=mes))),""""),metodoDirecto)))"),"EFECTIVO") -> EFECTIVO | F49: {=IF(A49="","",LET(mes,DATE($E$2,MATCH($B$2,'ESTADO CONTABLE'!$A$5:$A$16,0),1),cobrarDesde,IFERROR(INDEX('BASE DE DATOSS'!I:I,ROW()-13),""),pausada,SUMPRODUCT((UPPER(TRIM('PAUSAS MENSUALIDADES'!$A$5:$A$500))=UPPER(TRIM(A49)))*('PAUSAS MENSUALIDADES'!$B$5:$B$500=mes)*(UPPER(TRIM('PAUSAS MENSUALIDADES'!$D$5:$D$500))="APLICAR"))>0,abonoActivo,SUMIFS('ABONOS MENSUALIDADES'!$F$5:$F$500,'ABONOS MENSUALIDADES'!$C$5:$C$500,A49,'ABONOS MENSUALIDADES'!$D$5:$D$500,mes,'ABONOS MENSUALIDADES'!$G$5:$G$500,"<>*CONSOLIDADO EN PAGOS*")>0,esperadaBruta,MAX(IFNA(VLOOKUP(B49,COSTOS!$A$3:$B$13,2,FALSE),0)-150,0),IF(AND(cobrarDesde<>"",mes<cobrarDesde),"AÚN NO INICIA",IF(pausada,"PAUSADA",IF(AND(abonoActivo,COUNTIFS('ABONOS MENSUALIDADES'!$C$5:$C$500,A49,'ABONOS MENSUALIDADES'!$D$5:$D$500,mes,'ABONOS MENSUALIDADES'!$G$5:$G$500,"*MENSUALIDAD LIQUIDADA*")=0),"ABONO",IF(N(D49)>=esperadaBruta,"COBRADA",IF(N(D49)>0,"ABONO","PENDIENTE")))))))} -> COBRADA | G49: {=IF(A49="","",IFERROR(INDEX('BASE DE DATOSS'!I:I,ROW()-13),""))} -> 46113
A50: {=IFERROR(INDEX('BASE DE DATOSS'!A:A,ROW()-13),"")} -> AMERICA ALVAREZ SEPULVEDA | B50: {=IF(A50="","",IFERROR(INDEX('BASE DE DATOSS'!C:C,ROW()-13),""))} -> ADULTS 1 | C50: {=IF(A50="","",LET(mes,DATE($E$2,MATCH($B$2,'ESTADO CONTABLE'!$A$5:$A$16,0),1),cobrarDesde,IFERROR(INDEX('BASE DE DATOSS'!I:I,ROW()-13),""),pausada,SUMPRODUCT((UPPER(TRIM('PAUSAS MENSUALIDADES'!$A$5:$A$500))=UPPER(TRIM(A50)))*('PAUSAS MENSUALIDADES'!$B$5:$B$500=mes)*(UPPER(TRIM('PAUSAS MENSUALIDADES'!$D$5:$D$500))="APLICAR"))>0,IF(OR(AND(cobrarDesde<>"",mes<cobrarDesde),pausada),0,MAX(IFNA(VLOOKUP(B50,COSTOS!$A$3:$B$13,2,FALSE),0)-150,0)/1.16)))} -> 0 | D50: {=IF(A50="","",LET(mes,DATE($E$2,MATCH($B$2,'ESTADO CONTABLE'!$A$5:$A$16,0),1),abonos,SUMIFS('ABONOS MENSUALIDADES'!$F$5:$F$500,'ABONOS MENSUALIDADES'!$C$5:$C$500,A50,'ABONOS MENSUALIDADES'!$D$5:$D$500,mes),pago,CHOOSE(MATCH($B$2,'ESTADO CONTABLE'!$A$5:$A$16,0),IFNA(_xlfn.XLOOKUP(A50,PAGOS!$A$2:$A$996,PAGOS!$E$2:$E$996,""),""),IFNA(_xlfn.XLOOKUP(A50,PAGOS!$A$2:$A$996,PAGOS!$G$2:$G$996,""),""),IFNA(_xlfn.XLOOKUP(A50,PAGOS!$A$2:$A$996,PAGOS!$J$2:$J$996,""),""),IFNA(_xlfn.XLOOKUP(A50,PAGOS!$A$2:$A$996,PAGOS!$M$2:$M$996,""),""),IFNA(_xlfn.XLOOKUP(A50,PAGOS!$A$2:$A$996,PAGOS!$P$2:$P$996,""),""),IFNA(_xlfn.XLOOKUP(A50,PAGOS!$A$2:$A$996,PAGOS!$S$2:$S$996,""),""),IFNA(_xlfn.XLOOKUP(A50,PAGOS!$A$2:$A$996,PAGOS!$V$2:$V$996,""),""),IFNA(_xlfn.XLOOKUP(A50,PAGOS!$A$2:$A$996,PAGOS!$Y$2:$Y$996,""),""),IFNA(_xlfn.XLOOKUP(A50,PAGOS!$A$2:$A$996,PAGOS!$AB$2:$AB$996,""),""),IFNA(_xlfn.XLOOKUP(A50,PAGOS!$A$2:$A$996,PAGOS!$AE$2:$AE$996,""),""),IFNA(_xlfn.XLOOKUP(A50,PAGOS!$A$2:$A$996,PAGOS!$AH$2:$AH$996,""),""),IFNA(_xlfn.XLOOKUP(A50,PAGOS!$A$2:$A$996,PAGOS!$AK$2:$AK$996,""),"")),IF(abonos>0,abonos,pago)))} | E50: =IFERROR(__xludf.DUMMYFUNCTION("IF(A50="""","""",LET(mes,DATE($E$2,MATCH($B$2,'ESTADO CONTABLE'!$A$5:$A$16,0),1),abonos,SUMIFS('ABONOS MENSUALIDADES'!$F$5:$F$500,'ABONOS MENSUALIDADES'!$C$5:$C$500,A50,'ABONOS MENSUALIDADES'!$D$5:$D$500,mes),metodoDirecto,CHOOSE(MATCH($B$2,'ESTADO CONTAB"&"LE'!$A$5:$A$16,0),IF(ISNUMBER(D50),""POR CLASIFICAR"",""""),IFNA(XLOOKUP(A50,PAGOS!$A$2:$A$996,PAGOS!$H$2:$H$996,""""),""""),IFNA(XLOOKUP(A50,PAGOS!$A$2:$A$996,PAGOS!$K$2:$K$996,""""),""""),IFNA(XLOOKUP(A50,PAGOS!$A$2:$A$996,PAGOS!$N$2:$N$996,""""),""""),"&"IFNA(XLOOKUP(A50,PAGOS!$A$2:$A$996,PAGOS!$Q$2:$Q$996,""""),""""),IFNA(XLOOKUP(A50,PAGOS!$A$2:$A$996,PAGOS!$T$2:$T$996,""""),""""),IFNA(XLOOKUP(A50,PAGOS!$A$2:$A$996,PAGOS!$W$2:$W$996,""""),""""),IFNA(XLOOKUP(A50,PAGOS!$A$2:$A$996,PAGOS!$Z$2:$Z$996,""""),"&"""""),IFNA(XLOOKUP(A50,PAGOS!$A$2:$A$996,PAGOS!$AC$2:$AC$996,""""),""""),IFNA(XLOOKUP(A50,PAGOS!$A$2:$A$996,PAGOS!$AF$2:$AF$996,""""),""""),IFNA(XLOOKUP(A50,PAGOS!$A$2:$A$996,PAGOS!$AI$2:$AI$996,""""),""""),IFNA(XLOOKUP(A50,PAGOS!$A$2:$A$996,PAGOS!$AL$2:$"&"AL$996,""""),"""")),IF(abonos>0,IFERROR(TEXTJOIN("" + "",TRUE,UNIQUE(FILTER('ABONOS MENSUALIDADES'!$E$5:$E$500,'ABONOS MENSUALIDADES'!$C$5:$C$500=A50,'ABONOS MENSUALIDADES'!$D$5:$D$500=mes))),""""),metodoDirecto)))"),"") | F50: {=IF(A50="","",LET(mes,DATE($E$2,MATCH($B$2,'ESTADO CONTABLE'!$A$5:$A$16,0),1),cobrarDesde,IFERROR(INDEX('BASE DE DATOSS'!I:I,ROW()-13),""),pausada,SUMPRODUCT((UPPER(TRIM('PAUSAS MENSUALIDADES'!$A$5:$A$500))=UPPER(TRIM(A50)))*('PAUSAS MENSUALIDADES'!$B$5:$B$500=mes)*(UPPER(TRIM('PAUSAS MENSUALIDADES'!$D$5:$D$500))="APLICAR"))>0,abonoActivo,SUMIFS('ABONOS MENSUALIDADES'!$F$5:$F$500,'ABONOS MENSUALIDADES'!$C$5:$C$500,A50,'ABONOS MENSUALIDADES'!$D$5:$D$500,mes,'ABONOS MENSUALIDADES'!$G$5:$G$500,"<>*CONSOLIDADO EN PAGOS*")>0,esperadaBruta,MAX(IFNA(VLOOKUP(B50,COSTOS!$A$3:$B$13,2,FALSE),0)-150,0),IF(AND(cobrarDesde<>"",mes<cobrarDesde),"AÚN NO INICIA",IF(pausada,"PAUSADA",IF(AND(abonoActivo,COUNTIFS('ABONOS MENSUALIDADES'!$C$5:$C$500,A50,'ABONOS MENSUALIDADES'!$D$5:$D$500,mes,'ABONOS MENSUALIDADES'!$G$5:$G$500,"*MENSUALIDAD LIQUIDADA*")=0),"ABONO",IF(N(D50)>=esperadaBruta,"COBRADA",IF(N(D50)>0,"ABONO","PENDIENTE")))))))} -> PAUSADA | G50: {=IF(A50="","",IFERROR(INDEX('BASE DE DATOSS'!I:I,ROW()-13),""))} -> 46143
A51: {=IFERROR(INDEX('BASE DE DATOSS'!A:A,ROW()-13),"")} -> MAIA VICTORIA OCHOA COBIAN | B51: {=IF(A51="","",IFERROR(INDEX('BASE DE DATOSS'!C:C,ROW()-13),""))} -> JR 1 | C51: {=IF(A51="","",LET(mes,DATE($E$2,MATCH($B$2,'ESTADO CONTABLE'!$A$5:$A$16,0),1),cobrarDesde,IFERROR(INDEX('BASE DE DATOSS'!I:I,ROW()-13),""),pausada,SUMPRODUCT((UPPER(TRIM('PAUSAS MENSUALIDADES'!$A$5:$A$500))=UPPER(TRIM(A51)))*('PAUSAS MENSUALIDADES'!$B$5:$B$500=mes)*(UPPER(TRIM('PAUSAS MENSUALIDADES'!$D$5:$D$500))="APLICAR"))>0,IF(OR(AND(cobrarDesde<>"",mes<cobrarDesde),pausada),0,MAX(IFNA(VLOOKUP(B51,COSTOS!$A$3:$B$13,2,FALSE),0)-150,0)/1.16)))} -> 818.96552 | D51: {=IF(A51="","",LET(mes,DATE($E$2,MATCH($B$2,'ESTADO CONTABLE'!$A$5:$A$16,0),1),abonos,SUMIFS('ABONOS MENSUALIDADES'!$F$5:$F$500,'ABONOS MENSUALIDADES'!$C$5:$C$500,A51,'ABONOS MENSUALIDADES'!$D$5:$D$500,mes),pago,CHOOSE(MATCH($B$2,'ESTADO CONTABLE'!$A$5:$A$16,0),IFNA(_xlfn.XLOOKUP(A51,PAGOS!$A$2:$A$996,PAGOS!$E$2:$E$996,""),""),IFNA(_xlfn.XLOOKUP(A51,PAGOS!$A$2:$A$996,PAGOS!$G$2:$G$996,""),""),IFNA(_xlfn.XLOOKUP(A51,PAGOS!$A$2:$A$996,PAGOS!$J$2:$J$996,""),""),IFNA(_xlfn.XLOOKUP(A51,PAGOS!$A$2:$A$996,PAGOS!$M$2:$M$996,""),""),IFNA(_xlfn.XLOOKUP(A51,PAGOS!$A$2:$A$996,PAGOS!$P$2:$P$996,""),""),IFNA(_xlfn.XLOOKUP(A51,PAGOS!$A$2:$A$996,PAGOS!$S$2:$S$996,""),""),IFNA(_xlfn.XLOOKUP(A51,PAGOS!$A$2:$A$996,PAGOS!$V$2:$V$996,""),""),IFNA(_xlfn.XLOOKUP(A51,PAGOS!$A$2:$A$996,PAGOS!$Y$2:$Y$996,""),""),IFNA(_xlfn.XLOOKUP(A51,PAGOS!$A$2:$A$996,PAGOS!$AB$2:$AB$996,""),""),IFNA(_xlfn.XLOOKUP(A51,PAGOS!$A$2:$A$996,PAGOS!$AE$2:$AE$996,""),""),IFNA(_xlfn.XLOOKUP(A51,PAGOS!$A$2:$A$996,PAGOS!$AH$2:$AH$996,""),""),IFNA(_xlfn.XLOOKUP(A51,PAGOS!$A$2:$A$996,PAGOS!$AK$2:$AK$996,""),"")),IF(abonos>0,abonos,pago)))} -> 950 | E51: =IFERROR(__xludf.DUMMYFUNCTION("IF(A51="""","""",LET(mes,DATE($E$2,MATCH($B$2,'ESTADO CONTABLE'!$A$5:$A$16,0),1),abonos,SUMIFS('ABONOS MENSUALIDADES'!$F$5:$F$500,'ABONOS MENSUALIDADES'!$C$5:$C$500,A51,'ABONOS MENSUALIDADES'!$D$5:$D$500,mes),metodoDirecto,CHOOSE(MATCH($B$2,'ESTADO CONTAB"&"LE'!$A$5:$A$16,0),IF(ISNUMBER(D51),""POR CLASIFICAR"",""""),IFNA(XLOOKUP(A51,PAGOS!$A$2:$A$996,PAGOS!$H$2:$H$996,""""),""""),IFNA(XLOOKUP(A51,PAGOS!$A$2:$A$996,PAGOS!$K$2:$K$996,""""),""""),IFNA(XLOOKUP(A51,PAGOS!$A$2:$A$996,PAGOS!$N$2:$N$996,""""),""""),"&"IFNA(XLOOKUP(A51,PAGOS!$A$2:$A$996,PAGOS!$Q$2:$Q$996,""""),""""),IFNA(XLOOKUP(A51,PAGOS!$A$2:$A$996,PAGOS!$T$2:$T$996,""""),""""),IFNA(XLOOKUP(A51,PAGOS!$A$2:$A$996,PAGOS!$W$2:$W$996,""""),""""),IFNA(XLOOKUP(A51,PAGOS!$A$2:$A$996,PAGOS!$Z$2:$Z$996,""""),"&"""""),IFNA(XLOOKUP(A51,PAGOS!$A$2:$A$996,PAGOS!$AC$2:$AC$996,""""),""""),IFNA(XLOOKUP(A51,PAGOS!$A$2:$A$996,PAGOS!$AF$2:$AF$996,""""),""""),IFNA(XLOOKUP(A51,PAGOS!$A$2:$A$996,PAGOS!$AI$2:$AI$996,""""),""""),IFNA(XLOOKUP(A51,PAGOS!$A$2:$A$996,PAGOS!$AL$2:$"&"AL$996,""""),"""")),IF(abonos>0,IFERROR(TEXTJOIN("" + "",TRUE,UNIQUE(FILTER('ABONOS MENSUALIDADES'!$E$5:$E$500,'ABONOS MENSUALIDADES'!$C$5:$C$500=A51,'ABONOS MENSUALIDADES'!$D$5:$D$500=mes))),""""),metodoDirecto)))"),"EFECTIVO") -> EFECTIVO | F51: {=IF(A51="","",LET(mes,DATE($E$2,MATCH($B$2,'ESTADO CONTABLE'!$A$5:$A$16,0),1),cobrarDesde,IFERROR(INDEX('BASE DE DATOSS'!I:I,ROW()-13),""),pausada,SUMPRODUCT((UPPER(TRIM('PAUSAS MENSUALIDADES'!$A$5:$A$500))=UPPER(TRIM(A51)))*('PAUSAS MENSUALIDADES'!$B$5:$B$500=mes)*(UPPER(TRIM('PAUSAS MENSUALIDADES'!$D$5:$D$500))="APLICAR"))>0,abonoActivo,SUMIFS('ABONOS MENSUALIDADES'!$F$5:$F$500,'ABONOS MENSUALIDADES'!$C$5:$C$500,A51,'ABONOS MENSUALIDADES'!$D$5:$D$500,mes,'ABONOS MENSUALIDADES'!$G$5:$G$500,"<>*CONSOLIDADO EN PAGOS*")>0,esperadaBruta,MAX(IFNA(VLOOKUP(B51,COSTOS!$A$3:$B$13,2,FALSE),0)-150,0),IF(AND(cobrarDesde<>"",mes<cobrarDesde),"AÚN NO INICIA",IF(pausada,"PAUSADA",IF(AND(abonoActivo,COUNTIFS('ABONOS MENSUALIDADES'!$C$5:$C$500,A51,'ABONOS MENSUALIDADES'!$D$5:$D$500,mes,'ABONOS MENSUALIDADES'!$G$5:$G$500,"*MENSUALIDAD LIQUIDADA*")=0),"ABONO",IF(N(D51)>=esperadaBruta,"COBRADA",IF(N(D51)>0,"ABONO","PENDIENTE")))))))} -> COBRADA | G51: {=IF(A51="","",IFERROR(INDEX('BASE DE DATOSS'!I:I,ROW()-13),""))} -> 46174
A52: {=IFERROR(INDEX('BASE DE DATOSS'!A:A,ROW()-13),"")} -> ISABELLA ZOE CASTAÑEDA LUNA | B52: {=IF(A52="","",IFERROR(INDEX('BASE DE DATOSS'!C:C,ROW()-13),""))} -> JR 2 | C52: {=IF(A52="","",LET(mes,DATE($E$2,MATCH($B$2,'ESTADO CONTABLE'!$A$5:$A$16,0),1),cobrarDesde,IFERROR(INDEX('BASE DE DATOSS'!I:I,ROW()-13),""),pausada,SUMPRODUCT((UPPER(TRIM('PAUSAS MENSUALIDADES'!$A$5:$A$500))=UPPER(TRIM(A52)))*('PAUSAS MENSUALIDADES'!$B$5:$B$500=mes)*(UPPER(TRIM('PAUSAS MENSUALIDADES'!$D$5:$D$500))="APLICAR"))>0,IF(OR(AND(cobrarDesde<>"",mes<cobrarDesde),pausada),0,MAX(IFNA(VLOOKUP(B52,COSTOS!$A$3:$B$13,2,FALSE),0)-150,0)/1.16)))} -> 689.65517 | D52: {=IF(A52="","",LET(mes,DATE($E$2,MATCH($B$2,'ESTADO CONTABLE'!$A$5:$A$16,0),1),abonos,SUMIFS('ABONOS MENSUALIDADES'!$F$5:$F$500,'ABONOS MENSUALIDADES'!$C$5:$C$500,A52,'ABONOS MENSUALIDADES'!$D$5:$D$500,mes),pago,CHOOSE(MATCH($B$2,'ESTADO CONTABLE'!$A$5:$A$16,0),IFNA(_xlfn.XLOOKUP(A52,PAGOS!$A$2:$A$996,PAGOS!$E$2:$E$996,""),""),IFNA(_xlfn.XLOOKUP(A52,PAGOS!$A$2:$A$996,PAGOS!$G$2:$G$996,""),""),IFNA(_xlfn.XLOOKUP(A52,PAGOS!$A$2:$A$996,PAGOS!$J$2:$J$996,""),""),IFNA(_xlfn.XLOOKUP(A52,PAGOS!$A$2:$A$996,PAGOS!$M$2:$M$996,""),""),IFNA(_xlfn.XLOOKUP(A52,PAGOS!$A$2:$A$996,PAGOS!$P$2:$P$996,""),""),IFNA(_xlfn.XLOOKUP(A52,PAGOS!$A$2:$A$996,PAGOS!$S$2:$S$996,""),""),IFNA(_xlfn.XLOOKUP(A52,PAGOS!$A$2:$A$996,PAGOS!$V$2:$V$996,""),""),IFNA(_xlfn.XLOOKUP(A52,PAGOS!$A$2:$A$996,PAGOS!$Y$2:$Y$996,""),""),IFNA(_xlfn.XLOOKUP(A52,PAGOS!$A$2:$A$996,PAGOS!$AB$2:$AB$996,""),""),IFNA(_xlfn.XLOOKUP(A52,PAGOS!$A$2:$A$996,PAGOS!$AE$2:$AE$996,""),""),IFNA(_xlfn.XLOOKUP(A52,PAGOS!$A$2:$A$996,PAGOS!$AH$2:$AH$996,""),""),IFNA(_xlfn.XLOOKUP(A52,PAGOS!$A$2:$A$996,PAGOS!$AK$2:$AK$996,""),"")),IF(abonos>0,abonos,pago)))} -> 950 | E52: =IFERROR(__xludf.DUMMYFUNCTION("IF(A52="""","""",LET(mes,DATE($E$2,MATCH($B$2,'ESTADO CONTABLE'!$A$5:$A$16,0),1),abonos,SUMIFS('ABONOS MENSUALIDADES'!$F$5:$F$500,'ABONOS MENSUALIDADES'!$C$5:$C$500,A52,'ABONOS MENSUALIDADES'!$D$5:$D$500,mes),metodoDirecto,CHOOSE(MATCH($B$2,'ESTADO CONTAB"&"LE'!$A$5:$A$16,0),IF(ISNUMBER(D52),""POR CLASIFICAR"",""""),IFNA(XLOOKUP(A52,PAGOS!$A$2:$A$996,PAGOS!$H$2:$H$996,""""),""""),IFNA(XLOOKUP(A52,PAGOS!$A$2:$A$996,PAGOS!$K$2:$K$996,""""),""""),IFNA(XLOOKUP(A52,PAGOS!$A$2:$A$996,PAGOS!$N$2:$N$996,""""),""""),"&"IFNA(XLOOKUP(A52,PAGOS!$A$2:$A$996,PAGOS!$Q$2:$Q$996,""""),""""),IFNA(XLOOKUP(A52,PAGOS!$A$2:$A$996,PAGOS!$T$2:$T$996,""""),""""),IFNA(XLOOKUP(A52,PAGOS!$A$2:$A$996,PAGOS!$W$2:$W$996,""""),""""),IFNA(XLOOKUP(A52,PAGOS!$A$2:$A$996,PAGOS!$Z$2:$Z$996,""""),"&"""""),IFNA(XLOOKUP(A52,PAGOS!$A$2:$A$996,PAGOS!$AC$2:$AC$996,""""),""""),IFNA(XLOOKUP(A52,PAGOS!$A$2:$A$996,PAGOS!$AF$2:$AF$996,""""),""""),IFNA(XLOOKUP(A52,PAGOS!$A$2:$A$996,PAGOS!$AI$2:$AI$996,""""),""""),IFNA(XLOOKUP(A52,PAGOS!$A$2:$A$996,PAGOS!$AL$2:$"&"AL$996,""""),"""")),IF(abonos>0,IFERROR(TEXTJOIN("" + "",TRUE,UNIQUE(FILTER('ABONOS MENSUALIDADES'!$E$5:$E$500,'ABONOS MENSUALIDADES'!$C$5:$C$500=A52,'ABONOS MENSUALIDADES'!$D$5:$D$500=mes))),""""),metodoDirecto)))"),"EFECTIVO") -> EFECTIVO | F52: {=IF(A52="","",LET(mes,DATE($E$2,MATCH($B$2,'ESTADO CONTABLE'!$A$5:$A$16,0),1),cobrarDesde,IFERROR(INDEX('BASE DE DATOSS'!I:I,ROW()-13),""),pausada,SUMPRODUCT((UPPER(TRIM('PAUSAS MENSUALIDADES'!$A$5:$A$500))=UPPER(TRIM(A52)))*('PAUSAS MENSUALIDADES'!$B$5:$B$500=mes)*(UPPER(TRIM('PAUSAS MENSUALIDADES'!$D$5:$D$500))="APLICAR"))>0,abonoActivo,SUMIFS('ABONOS MENSUALIDADES'!$F$5:$F$500,'ABONOS MENSUALIDADES'!$C$5:$C$500,A52,'ABONOS MENSUALIDADES'!$D$5:$D$500,mes,'ABONOS MENSUALIDADES'!$G$5:$G$500,"<>*CONSOLIDADO EN PAGOS*")>0,esperadaBruta,MAX(IFNA(VLOOKUP(B52,COSTOS!$A$3:$B$13,2,FALSE),0)-150,0),IF(AND(cobrarDesde<>"",mes<cobrarDesde),"AÚN NO INICIA",IF(pausada,"PAUSADA",IF(AND(abonoActivo,COUNTIFS('ABONOS MENSUALIDADES'!$C$5:$C$500,A52,'ABONOS MENSUALIDADES'!$D$5:$D$500,mes,'ABONOS MENSUALIDADES'!$G$5:$G$500,"*MENSUALIDAD LIQUIDADA*")=0),"ABONO",IF(N(D52)>=esperadaBruta,"COBRADA",IF(N(D52)>0,"ABONO","PENDIENTE")))))))} -> COBRADA | G52: {=IF(A52="","",IFERROR(INDEX('BASE DE DATOSS'!I:I,ROW()-13),""))} -> 46174
A53: {=IFERROR(INDEX('BASE DE DATOSS'!A:A,ROW()-13),"")} -> NOVA RAMIREZ | B53: {=IF(A53="","",IFERROR(INDEX('BASE DE DATOSS'!C:C,ROW()-13),""))} -> KIDS 1 | C53: {=IF(A53="","",LET(mes,DATE($E$2,MATCH($B$2,'ESTADO CONTABLE'!$A$5:$A$16,0),1),cobrarDesde,IFERROR(INDEX('BASE DE DATOSS'!I:I,ROW()-13),""),pausada,SUMPRODUCT((UPPER(TRIM('PAUSAS MENSUALIDADES'!$A$5:$A$500))=UPPER(TRIM(A53)))*('PAUSAS MENSUALIDADES'!$B$5:$B$500=mes)*(UPPER(TRIM('PAUSAS MENSUALIDADES'!$D$5:$D$500))="APLICAR"))>0,IF(OR(AND(cobrarDesde<>"",mes<cobrarDesde),pausada),0,MAX(IFNA(VLOOKUP(B53,COSTOS!$A$3:$B$13,2,FALSE),0)-150,0)/1.16)))} -> 818.96552 | D53: {=IF(A53="","",LET(mes,DATE($E$2,MATCH($B$2,'ESTADO CONTABLE'!$A$5:$A$16,0),1),abonos,SUMIFS('ABONOS MENSUALIDADES'!$F$5:$F$500,'ABONOS MENSUALIDADES'!$C$5:$C$500,A53,'ABONOS MENSUALIDADES'!$D$5:$D$500,mes),pago,CHOOSE(MATCH($B$2,'ESTADO CONTABLE'!$A$5:$A$16,0),IFNA(_xlfn.XLOOKUP(A53,PAGOS!$A$2:$A$996,PAGOS!$E$2:$E$996,""),""),IFNA(_xlfn.XLOOKUP(A53,PAGOS!$A$2:$A$996,PAGOS!$G$2:$G$996,""),""),IFNA(_xlfn.XLOOKUP(A53,PAGOS!$A$2:$A$996,PAGOS!$J$2:$J$996,""),""),IFNA(_xlfn.XLOOKUP(A53,PAGOS!$A$2:$A$996,PAGOS!$M$2:$M$996,""),""),IFNA(_xlfn.XLOOKUP(A53,PAGOS!$A$2:$A$996,PAGOS!$P$2:$P$996,""),""),IFNA(_xlfn.XLOOKUP(A53,PAGOS!$A$2:$A$996,PAGOS!$S$2:$S$996,""),""),IFNA(_xlfn.XLOOKUP(A53,PAGOS!$A$2:$A$996,PAGOS!$V$2:$V$996,""),""),IFNA(_xlfn.XLOOKUP(A53,PAGOS!$A$2:$A$996,PAGOS!$Y$2:$Y$996,""),""),IFNA(_xlfn.XLOOKUP(A53,PAGOS!$A$2:$A$996,PAGOS!$AB$2:$AB$996,""),""),IFNA(_xlfn.XLOOKUP(A53,PAGOS!$A$2:$A$996,PAGOS!$AE$2:$AE$996,""),""),IFNA(_xlfn.XLOOKUP(A53,PAGOS!$A$2:$A$996,PAGOS!$AH$2:$AH$996,""),""),IFNA(_xlfn.XLOOKUP(A53,PAGOS!$A$2:$A$996,PAGOS!$AK$2:$AK$996,""),"")),IF(abonos>0,abonos,pago)))} -> 950 | E53: =IFERROR(__xludf.DUMMYFUNCTION("IF(A53="""","""",LET(mes,DATE($E$2,MATCH($B$2,'ESTADO CONTABLE'!$A$5:$A$16,0),1),abonos,SUMIFS('ABONOS MENSUALIDADES'!$F$5:$F$500,'ABONOS MENSUALIDADES'!$C$5:$C$500,A53,'ABONOS MENSUALIDADES'!$D$5:$D$500,mes),metodoDirecto,CHOOSE(MATCH($B$2,'ESTADO CONTAB"&"LE'!$A$5:$A$16,0),IF(ISNUMBER(D53),""POR CLASIFICAR"",""""),IFNA(XLOOKUP(A53,PAGOS!$A$2:$A$996,PAGOS!$H$2:$H$996,""""),""""),IFNA(XLOOKUP(A53,PAGOS!$A$2:$A$996,PAGOS!$K$2:$K$996,""""),""""),IFNA(XLOOKUP(A53,PAGOS!$A$2:$A$996,PAGOS!$N$2:$N$996,""""),""""),"&"IFNA(XLOOKUP(A53,PAGOS!$A$2:$A$996,PAGOS!$Q$2:$Q$996,""""),""""),IFNA(XLOOKUP(A53,PAGOS!$A$2:$A$996,PAGOS!$T$2:$T$996,""""),""""),IFNA(XLOOKUP(A53,PAGOS!$A$2:$A$996,PAGOS!$W$2:$W$996,""""),""""),IFNA(XLOOKUP(A53,PAGOS!$A$2:$A$996,PAGOS!$Z$2:$Z$996,""""),"&"""""),IFNA(XLOOKUP(A53,PAGOS!$A$2:$A$996,PAGOS!$AC$2:$AC$996,""""),""""),IFNA(XLOOKUP(A53,PAGOS!$A$2:$A$996,PAGOS!$AF$2:$AF$996,""""),""""),IFNA(XLOOKUP(A53,PAGOS!$A$2:$A$996,PAGOS!$AI$2:$AI$996,""""),""""),IFNA(XLOOKUP(A53,PAGOS!$A$2:$A$996,PAGOS!$AL$2:$"&"AL$996,""""),"""")),IF(abonos>0,IFERROR(TEXTJOIN("" + "",TRUE,UNIQUE(FILTER('ABONOS MENSUALIDADES'!$E$5:$E$500,'ABONOS MENSUALIDADES'!$C$5:$C$500=A53,'ABONOS MENSUALIDADES'!$D$5:$D$500=mes))),""""),metodoDirecto)))"),"TERMINAL") -> TERMINAL | F53: {=IF(A53="","",LET(mes,DATE($E$2,MATCH($B$2,'ESTADO CONTABLE'!$A$5:$A$16,0),1),cobrarDesde,IFERROR(INDEX('BASE DE DATOSS'!I:I,ROW()-13),""),pausada,SUMPRODUCT((UPPER(TRIM('PAUSAS MENSUALIDADES'!$A$5:$A$500))=UPPER(TRIM(A53)))*('PAUSAS MENSUALIDADES'!$B$5:$B$500=mes)*(UPPER(TRIM('PAUSAS MENSUALIDADES'!$D$5:$D$500))="APLICAR"))>0,abonoActivo,SUMIFS('ABONOS MENSUALIDADES'!$F$5:$F$500,'ABONOS MENSUALIDADES'!$C$5:$C$500,A53,'ABONOS MENSUALIDADES'!$D$5:$D$500,mes,'ABONOS MENSUALIDADES'!$G$5:$G$500,"<>*CONSOLIDADO EN PAGOS*")>0,esperadaBruta,MAX(IFNA(VLOOKUP(B53,COSTOS!$A$3:$B$13,2,FALSE),0)-150,0),IF(AND(cobrarDesde<>"",mes<cobrarDesde),"AÚN NO INICIA",IF(pausada,"PAUSADA",IF(AND(abonoActivo,COUNTIFS('ABONOS MENSUALIDADES'!$C$5:$C$500,A53,'ABONOS MENSUALIDADES'!$D$5:$D$500,mes,'ABONOS MENSUALIDADES'!$G$5:$G$500,"*MENSUALIDAD LIQUIDADA*")=0),"ABONO",IF(N(D53)>=esperadaBruta,"COBRADA",IF(N(D53)>0,"ABONO","PENDIENTE")))))))} -> COBRADA | G53: {=IF(A53="","",IFERROR(INDEX('BASE DE DATOSS'!I:I,ROW()-13),""))} -> 46174
A54: {=IFERROR(INDEX('BASE DE DATOSS'!A:A,ROW()-13),"")} -> ANDREA FERNANDA | B54: {=IF(A54="","",IFERROR(INDEX('BASE DE DATOSS'!C:C,ROW()-13),""))} -> SABATINO | C54: {=IF(A54="","",LET(mes,DATE($E$2,MATCH($B$2,'ESTADO CONTABLE'!$A$5:$A$16,0),1),cobrarDesde,IFERROR(INDEX('BASE DE DATOSS'!I:I,ROW()-13),""),pausada,SUMPRODUCT((UPPER(TRIM('PAUSAS MENSUALIDADES'!$A$5:$A$500))=UPPER(TRIM(A54)))*('PAUSAS MENSUALIDADES'!$B$5:$B$500=mes)*(UPPER(TRIM('PAUSAS MENSUALIDADES'!$D$5:$D$500))="APLICAR"))>0,IF(OR(AND(cobrarDesde<>"",mes<cobrarDesde),pausada),0,MAX(IFNA(VLOOKUP(B54,COSTOS!$A$3:$B$13,2,FALSE),0)-150,0)/1.16)))} -> 474.13793 | D54: {=IF(A54="","",LET(mes,DATE($E$2,MATCH($B$2,'ESTADO CONTABLE'!$A$5:$A$16,0),1),abonos,SUMIFS('ABONOS MENSUALIDADES'!$F$5:$F$500,'ABONOS MENSUALIDADES'!$C$5:$C$500,A54,'ABONOS MENSUALIDADES'!$D$5:$D$500,mes),pago,CHOOSE(MATCH($B$2,'ESTADO CONTABLE'!$A$5:$A$16,0),IFNA(_xlfn.XLOOKUP(A54,PAGOS!$A$2:$A$996,PAGOS!$E$2:$E$996,""),""),IFNA(_xlfn.XLOOKUP(A54,PAGOS!$A$2:$A$996,PAGOS!$G$2:$G$996,""),""),IFNA(_xlfn.XLOOKUP(A54,PAGOS!$A$2:$A$996,PAGOS!$J$2:$J$996,""),""),IFNA(_xlfn.XLOOKUP(A54,PAGOS!$A$2:$A$996,PAGOS!$M$2:$M$996,""),""),IFNA(_xlfn.XLOOKUP(A54,PAGOS!$A$2:$A$996,PAGOS!$P$2:$P$996,""),""),IFNA(_xlfn.XLOOKUP(A54,PAGOS!$A$2:$A$996,PAGOS!$S$2:$S$996,""),""),IFNA(_xlfn.XLOOKUP(A54,PAGOS!$A$2:$A$996,PAGOS!$V$2:$V$996,""),""),IFNA(_xlfn.XLOOKUP(A54,PAGOS!$A$2:$A$996,PAGOS!$Y$2:$Y$996,""),""),IFNA(_xlfn.XLOOKUP(A54,PAGOS!$A$2:$A$996,PAGOS!$AB$2:$AB$996,""),""),IFNA(_xlfn.XLOOKUP(A54,PAGOS!$A$2:$A$996,PAGOS!$AE$2:$AE$996,""),""),IFNA(_xlfn.XLOOKUP(A54,PAGOS!$A$2:$A$996,PAGOS!$AH$2:$AH$996,""),""),IFNA(_xlfn.XLOOKUP(A54,PAGOS!$A$2:$A$996,PAGOS!$AK$2:$AK$996,""),"")),IF(abonos>0,abonos,pago)))} -> 550 | E54: =IFERROR(__xludf.DUMMYFUNCTION("IF(A54="""","""",LET(mes,DATE($E$2,MATCH($B$2,'ESTADO CONTABLE'!$A$5:$A$16,0),1),abonos,SUMIFS('ABONOS MENSUALIDADES'!$F$5:$F$500,'ABONOS MENSUALIDADES'!$C$5:$C$500,A54,'ABONOS MENSUALIDADES'!$D$5:$D$500,mes),metodoDirecto,CHOOSE(MATCH($B$2,'ESTADO CONTAB"&"LE'!$A$5:$A$16,0),IF(ISNUMBER(D54),""POR CLASIFICAR"",""""),IFNA(XLOOKUP(A54,PAGOS!$A$2:$A$996,PAGOS!$H$2:$H$996,""""),""""),IFNA(XLOOKUP(A54,PAGOS!$A$2:$A$996,PAGOS!$K$2:$K$996,""""),""""),IFNA(XLOOKUP(A54,PAGOS!$A$2:$A$996,PAGOS!$N$2:$N$996,""""),""""),"&"IFNA(XLOOKUP(A54,PAGOS!$A$2:$A$996,PAGOS!$Q$2:$Q$996,""""),""""),IFNA(XLOOKUP(A54,PAGOS!$A$2:$A$996,PAGOS!$T$2:$T$996,""""),""""),IFNA(XLOOKUP(A54,PAGOS!$A$2:$A$996,PAGOS!$W$2:$W$996,""""),""""),IFNA(XLOOKUP(A54,PAGOS!$A$2:$A$996,PAGOS!$Z$2:$Z$996,""""),"&"""""),IFNA(XLOOKUP(A54,PAGOS!$A$2:$A$996,PAGOS!$AC$2:$AC$996,""""),""""),IFNA(XLOOKUP(A54,PAGOS!$A$2:$A$996,PAGOS!$AF$2:$AF$996,""""),""""),IFNA(XLOOKUP(A54,PAGOS!$A$2:$A$996,PAGOS!$AI$2:$AI$996,""""),""""),IFNA(XLOOKUP(A54,PAGOS!$A$2:$A$996,PAGOS!$AL$2:$"&"AL$996,""""),"""")),IF(abonos>0,IFERROR(TEXTJOIN("" + "",TRUE,UNIQUE(FILTER('ABONOS MENSUALIDADES'!$E$5:$E$500,'ABONOS MENSUALIDADES'!$C$5:$C$500=A54,'ABONOS MENSUALIDADES'!$D$5:$D$500=mes))),""""),metodoDirecto)))"),"TRANSFERENCIA") -> TRANSFERENCIA | F54: {=IF(A54="","",LET(mes,DATE($E$2,MATCH($B$2,'ESTADO CONTABLE'!$A$5:$A$16,0),1),cobrarDesde,IFERROR(INDEX('BASE DE DATOSS'!I:I,ROW()-13),""),pausada,SUMPRODUCT((UPPER(TRIM('PAUSAS MENSUALIDADES'!$A$5:$A$500))=UPPER(TRIM(A54)))*('PAUSAS MENSUALIDADES'!$B$5:$B$500=mes)*(UPPER(TRIM('PAUSAS MENSUALIDADES'!$D$5:$D$500))="APLICAR"))>0,abonoActivo,SUMIFS('ABONOS MENSUALIDADES'!$F$5:$F$500,'ABONOS MENSUALIDADES'!$C$5:$C$500,A54,'ABONOS MENSUALIDADES'!$D$5:$D$500,mes,'ABONOS MENSUALIDADES'!$G$5:$G$500,"<>*CONSOLIDADO EN PAGOS*")>0,esperadaBruta,MAX(IFNA(VLOOKUP(B54,COSTOS!$A$3:$B$13,2,FALSE),0)-150,0),IF(AND(cobrarDesde<>"",mes<cobrarDesde),"AÚN NO INICIA",IF(pausada,"PAUSADA",IF(AND(abonoActivo,COUNTIFS('ABONOS MENSUALIDADES'!$C$5:$C$500,A54,'ABONOS MENSUALIDADES'!$D$5:$D$500,mes,'ABONOS MENSUALIDADES'!$G$5:$G$500,"*MENSUALIDAD LIQUIDADA*")=0),"ABONO",IF(N(D54)>=esperadaBruta,"COBRADA",IF(N(D54)>0,"ABONO","PENDIENTE")))))))} -> COBRADA | G54: {=IF(A54="","",IFERROR(INDEX('BASE DE DATOSS'!I:I,ROW()-13),""))} -> 46174
A55: {=IFERROR(INDEX('BASE DE DATOSS'!A:A,ROW()-13),"")} -> DIANA VALENTINA CONTRERAS GARCIA | B55: {=IF(A55="","",IFERROR(INDEX('BASE DE DATOSS'!C:C,ROW()-13),""))} -> ADULTS 2 | C55: {=IF(A55="","",LET(mes,DATE($E$2,MATCH($B$2,'ESTADO CONTABLE'!$A$5:$A$16,0),1),cobrarDesde,IFERROR(INDEX('BASE DE DATOSS'!I:I,ROW()-13),""),pausada,SUMPRODUCT((UPPER(TRIM('PAUSAS MENSUALIDADES'!$A$5:$A$500))=UPPER(TRIM(A55)))*('PAUSAS MENSUALIDADES'!$B$5:$B$500=mes)*(UPPER(TRIM('PAUSAS MENSUALIDADES'!$D$5:$D$500))="APLICAR"))>0,IF(OR(AND(cobrarDesde<>"",mes<cobrarDesde),pausada),0,MAX(IFNA(VLOOKUP(B55,COSTOS!$A$3:$B$13,2,FALSE),0)-150,0)/1.16)))} -> 818.96552 | D55: {=IF(A55="","",LET(mes,DATE($E$2,MATCH($B$2,'ESTADO CONTABLE'!$A$5:$A$16,0),1),abonos,SUMIFS('ABONOS MENSUALIDADES'!$F$5:$F$500,'ABONOS MENSUALIDADES'!$C$5:$C$500,A55,'ABONOS MENSUALIDADES'!$D$5:$D$500,mes),pago,CHOOSE(MATCH($B$2,'ESTADO CONTABLE'!$A$5:$A$16,0),IFNA(_xlfn.XLOOKUP(A55,PAGOS!$A$2:$A$996,PAGOS!$E$2:$E$996,""),""),IFNA(_xlfn.XLOOKUP(A55,PAGOS!$A$2:$A$996,PAGOS!$G$2:$G$996,""),""),IFNA(_xlfn.XLOOKUP(A55,PAGOS!$A$2:$A$996,PAGOS!$J$2:$J$996,""),""),IFNA(_xlfn.XLOOKUP(A55,PAGOS!$A$2:$A$996,PAGOS!$M$2:$M$996,""),""),IFNA(_xlfn.XLOOKUP(A55,PAGOS!$A$2:$A$996,PAGOS!$P$2:$P$996,""),""),IFNA(_xlfn.XLOOKUP(A55,PAGOS!$A$2:$A$996,PAGOS!$S$2:$S$996,""),""),IFNA(_xlfn.XLOOKUP(A55,PAGOS!$A$2:$A$996,PAGOS!$V$2:$V$996,""),""),IFNA(_xlfn.XLOOKUP(A55,PAGOS!$A$2:$A$996,PAGOS!$Y$2:$Y$996,""),""),IFNA(_xlfn.XLOOKUP(A55,PAGOS!$A$2:$A$996,PAGOS!$AB$2:$AB$996,""),""),IFNA(_xlfn.XLOOKUP(A55,PAGOS!$A$2:$A$996,PAGOS!$AE$2:$AE$996,""),""),IFNA(_xlfn.XLOOKUP(A55,PAGOS!$A$2:$A$996,PAGOS!$AH$2:$AH$996,""),""),IFNA(_xlfn.XLOOKUP(A55,PAGOS!$A$2:$A$996,PAGOS!$AK$2:$AK$996,""),"")),IF(abonos>0,abonos,pago)))} -> 950 | E55: =IFERROR(__xludf.DUMMYFUNCTION("IF(A55="""","""",LET(mes,DATE($E$2,MATCH($B$2,'ESTADO CONTABLE'!$A$5:$A$16,0),1),abonos,SUMIFS('ABONOS MENSUALIDADES'!$F$5:$F$500,'ABONOS MENSUALIDADES'!$C$5:$C$500,A55,'ABONOS MENSUALIDADES'!$D$5:$D$500,mes),metodoDirecto,CHOOSE(MATCH($B$2,'ESTADO CONTAB"&"LE'!$A$5:$A$16,0),IF(ISNUMBER(D55),""POR CLASIFICAR"",""""),IFNA(XLOOKUP(A55,PAGOS!$A$2:$A$996,PAGOS!$H$2:$H$996,""""),""""),IFNA(XLOOKUP(A55,PAGOS!$A$2:$A$996,PAGOS!$K$2:$K$996,""""),""""),IFNA(XLOOKUP(A55,PAGOS!$A$2:$A$996,PAGOS!$N$2:$N$996,""""),""""),"&"IFNA(XLOOKUP(A55,PAGOS!$A$2:$A$996,PAGOS!$Q$2:$Q$996,""""),""""),IFNA(XLOOKUP(A55,PAGOS!$A$2:$A$996,PAGOS!$T$2:$T$996,""""),""""),IFNA(XLOOKUP(A55,PAGOS!$A$2:$A$996,PAGOS!$W$2:$W$996,""""),""""),IFNA(XLOOKUP(A55,PAGOS!$A$2:$A$996,PAGOS!$Z$2:$Z$996,""""),"&"""""),IFNA(XLOOKUP(A55,PAGOS!$A$2:$A$996,PAGOS!$AC$2:$AC$996,""""),""""),IFNA(XLOOKUP(A55,PAGOS!$A$2:$A$996,PAGOS!$AF$2:$AF$996,""""),""""),IFNA(XLOOKUP(A55,PAGOS!$A$2:$A$996,PAGOS!$AI$2:$AI$996,""""),""""),IFNA(XLOOKUP(A55,PAGOS!$A$2:$A$996,PAGOS!$AL$2:$"&"AL$996,""""),"""")),IF(abonos>0,IFERROR(TEXTJOIN("" + "",TRUE,UNIQUE(FILTER('ABONOS MENSUALIDADES'!$E$5:$E$500,'ABONOS MENSUALIDADES'!$C$5:$C$500=A55,'ABONOS MENSUALIDADES'!$D$5:$D$500=mes))),""""),metodoDirecto)))"),"EFECTIVO") -> EFECTIVO | F55: {=IF(A55="","",LET(mes,DATE($E$2,MATCH($B$2,'ESTADO CONTABLE'!$A$5:$A$16,0),1),cobrarDesde,IFERROR(INDEX('BASE DE DATOSS'!I:I,ROW()-13),""),pausada,SUMPRODUCT((UPPER(TRIM('PAUSAS MENSUALIDADES'!$A$5:$A$500))=UPPER(TRIM(A55)))*('PAUSAS MENSUALIDADES'!$B$5:$B$500=mes)*(UPPER(TRIM('PAUSAS MENSUALIDADES'!$D$5:$D$500))="APLICAR"))>0,abonoActivo,SUMIFS('ABONOS MENSUALIDADES'!$F$5:$F$500,'ABONOS MENSUALIDADES'!$C$5:$C$500,A55,'ABONOS MENSUALIDADES'!$D$5:$D$500,mes,'ABONOS MENSUALIDADES'!$G$5:$G$500,"<>*CONSOLIDADO EN PAGOS*")>0,esperadaBruta,MAX(IFNA(VLOOKUP(B55,COSTOS!$A$3:$B$13,2,FALSE),0)-150,0),IF(AND(cobrarDesde<>"",mes<cobrarDesde),"AÚN NO INICIA",IF(pausada,"PAUSADA",IF(AND(abonoActivo,COUNTIFS('ABONOS MENSUALIDADES'!$C$5:$C$500,A55,'ABONOS MENSUALIDADES'!$D$5:$D$500,mes,'ABONOS MENSUALIDADES'!$G$5:$G$500,"*MENSUALIDAD LIQUIDADA*")=0),"ABONO",IF(N(D55)>=esperadaBruta,"COBRADA",IF(N(D55)>0,"ABONO","PENDIENTE")))))))} -> COBRADA | G55: {=IF(A55="","",IFERROR(INDEX('BASE DE DATOSS'!I:I,ROW()-13),""))} -> 46174
A56: {=IFERROR(INDEX('BASE DE DATOSS'!A:A,ROW()-13),"")} -> KARLA ELIZABETH CERNAS GARCÍA | B56: {=IF(A56="","",IFERROR(INDEX('BASE DE DATOSS'!C:C,ROW()-13),""))} -> SABATINO | C56: {=IF(A56="","",LET(mes,DATE($E$2,MATCH($B$2,'ESTADO CONTABLE'!$A$5:$A$16,0),1),cobrarDesde,IFERROR(INDEX('BASE DE DATOSS'!I:I,ROW()-13),""),pausada,SUMPRODUCT((UPPER(TRIM('PAUSAS MENSUALIDADES'!$A$5:$A$500))=UPPER(TRIM(A56)))*('PAUSAS MENSUALIDADES'!$B$5:$B$500=mes)*(UPPER(TRIM('PAUSAS MENSUALIDADES'!$D$5:$D$500))="APLICAR"))>0,IF(OR(AND(cobrarDesde<>"",mes<cobrarDesde),pausada),0,MAX(IFNA(VLOOKUP(B56,COSTOS!$A$3:$B$13,2,FALSE),0)-150,0)/1.16)))} -> 474.13793 | D56: {=IF(A56="","",LET(mes,DATE($E$2,MATCH($B$2,'ESTADO CONTABLE'!$A$5:$A$16,0),1),abonos,SUMIFS('ABONOS MENSUALIDADES'!$F$5:$F$500,'ABONOS MENSUALIDADES'!$C$5:$C$500,A56,'ABONOS MENSUALIDADES'!$D$5:$D$500,mes),pago,CHOOSE(MATCH($B$2,'ESTADO CONTABLE'!$A$5:$A$16,0),IFNA(_xlfn.XLOOKUP(A56,PAGOS!$A$2:$A$996,PAGOS!$E$2:$E$996,""),""),IFNA(_xlfn.XLOOKUP(A56,PAGOS!$A$2:$A$996,PAGOS!$G$2:$G$996,""),""),IFNA(_xlfn.XLOOKUP(A56,PAGOS!$A$2:$A$996,PAGOS!$J$2:$J$996,""),""),IFNA(_xlfn.XLOOKUP(A56,PAGOS!$A$2:$A$996,PAGOS!$M$2:$M$996,""),""),IFNA(_xlfn.XLOOKUP(A56,PAGOS!$A$2:$A$996,PAGOS!$P$2:$P$996,""),""),IFNA(_xlfn.XLOOKUP(A56,PAGOS!$A$2:$A$996,PAGOS!$S$2:$S$996,""),""),IFNA(_xlfn.XLOOKUP(A56,PAGOS!$A$2:$A$996,PAGOS!$V$2:$V$996,""),""),IFNA(_xlfn.XLOOKUP(A56,PAGOS!$A$2:$A$996,PAGOS!$Y$2:$Y$996,""),""),IFNA(_xlfn.XLOOKUP(A56,PAGOS!$A$2:$A$996,PAGOS!$AB$2:$AB$996,""),""),IFNA(_xlfn.XLOOKUP(A56,PAGOS!$A$2:$A$996,PAGOS!$AE$2:$AE$996,""),""),IFNA(_xlfn.XLOOKUP(A56,PAGOS!$A$2:$A$996,PAGOS!$AH$2:$AH$996,""),""),IFNA(_xlfn.XLOOKUP(A56,PAGOS!$A$2:$A$996,PAGOS!$AK$2:$AK$996,""),"")),IF(abonos>0,abonos,pago)))} -> 550 | E56: =IFERROR(__xludf.DUMMYFUNCTION("IF(A56="""","""",LET(mes,DATE($E$2,MATCH($B$2,'ESTADO CONTABLE'!$A$5:$A$16,0),1),abonos,SUMIFS('ABONOS MENSUALIDADES'!$F$5:$F$500,'ABONOS MENSUALIDADES'!$C$5:$C$500,A56,'ABONOS MENSUALIDADES'!$D$5:$D$500,mes),metodoDirecto,CHOOSE(MATCH($B$2,'ESTADO CONTAB"&"LE'!$A$5:$A$16,0),IF(ISNUMBER(D56),""POR CLASIFICAR"",""""),IFNA(XLOOKUP(A56,PAGOS!$A$2:$A$996,PAGOS!$H$2:$H$996,""""),""""),IFNA(XLOOKUP(A56,PAGOS!$A$2:$A$996,PAGOS!$K$2:$K$996,""""),""""),IFNA(XLOOKUP(A56,PAGOS!$A$2:$A$996,PAGOS!$N$2:$N$996,""""),""""),"&"IFNA(XLOOKUP(A56,PAGOS!$A$2:$A$996,PAGOS!$Q$2:$Q$996,""""),""""),IFNA(XLOOKUP(A56,PAGOS!$A$2:$A$996,PAGOS!$T$2:$T$996,""""),""""),IFNA(XLOOKUP(A56,PAGOS!$A$2:$A$996,PAGOS!$W$2:$W$996,""""),""""),IFNA(XLOOKUP(A56,PAGOS!$A$2:$A$996,PAGOS!$Z$2:$Z$996,""""),"&"""""),IFNA(XLOOKUP(A56,PAGOS!$A$2:$A$996,PAGOS!$AC$2:$AC$996,""""),""""),IFNA(XLOOKUP(A56,PAGOS!$A$2:$A$996,PAGOS!$AF$2:$AF$996,""""),""""),IFNA(XLOOKUP(A56,PAGOS!$A$2:$A$996,PAGOS!$AI$2:$AI$996,""""),""""),IFNA(XLOOKUP(A56,PAGOS!$A$2:$A$996,PAGOS!$AL$2:$"&"AL$996,""""),"""")),IF(abonos>0,IFERROR(TEXTJOIN("" + "",TRUE,UNIQUE(FILTER('ABONOS MENSUALIDADES'!$E$5:$E$500,'ABONOS MENSUALIDADES'!$C$5:$C$500=A56,'ABONOS MENSUALIDADES'!$D$5:$D$500=mes))),""""),metodoDirecto)))"),"TRANSFERENCIA") -> TRANSFERENCIA | F56: {=IF(A56="","",LET(mes,DATE($E$2,MATCH($B$2,'ESTADO CONTABLE'!$A$5:$A$16,0),1),cobrarDesde,IFERROR(INDEX('BASE DE DATOSS'!I:I,ROW()-13),""),pausada,SUMPRODUCT((UPPER(TRIM('PAUSAS MENSUALIDADES'!$A$5:$A$500))=UPPER(TRIM(A56)))*('PAUSAS MENSUALIDADES'!$B$5:$B$500=mes)*(UPPER(TRIM('PAUSAS MENSUALIDADES'!$D$5:$D$500))="APLICAR"))>0,abonoActivo,SUMIFS('ABONOS MENSUALIDADES'!$F$5:$F$500,'ABONOS MENSUALIDADES'!$C$5:$C$500,A56,'ABONOS MENSUALIDADES'!$D$5:$D$500,mes,'ABONOS MENSUALIDADES'!$G$5:$G$500,"<>*CONSOLIDADO EN PAGOS*")>0,esperadaBruta,MAX(IFNA(VLOOKUP(B56,COSTOS!$A$3:$B$13,2,FALSE),0)-150,0),IF(AND(cobrarDesde<>"",mes<cobrarDesde),"AÚN NO INICIA",IF(pausada,"PAUSADA",IF(AND(abonoActivo,COUNTIFS('ABONOS MENSUALIDADES'!$C$5:$C$500,A56,'ABONOS MENSUALIDADES'!$D$5:$D$500,mes,'ABONOS MENSUALIDADES'!$G$5:$G$500,"*MENSUALIDAD LIQUIDADA*")=0),"ABONO",IF(N(D56)>=esperadaBruta,"COBRADA",IF(N(D56)>0,"ABONO","PENDIENTE")))))))} -> COBRADA | G56: {=IF(A56="","",IFERROR(INDEX('BASE DE DATOSS'!I:I,ROW()-13),""))} -> 46204
A57: {=IFERROR(INDEX('BASE DE DATOSS'!A:A,ROW()-13),"")} -> XIMENA SARAHI MONTES CRUZ | B57: {=IF(A57="","",IFERROR(INDEX('BASE DE DATOSS'!C:C,ROW()-13),""))} -> KIDS 2 | C57: {=IF(A57="","",LET(mes,DATE($E$2,MATCH($B$2,'ESTADO CONTABLE'!$A$5:$A$16,0),1),cobrarDesde,IFERROR(INDEX('BASE DE DATOSS'!I:I,ROW()-13),""),pausada,SUMPRODUCT((UPPER(TRIM('PAUSAS MENSUALIDADES'!$A$5:$A$500))=UPPER(TRIM(A57)))*('PAUSAS MENSUALIDADES'!$B$5:$B$500=mes)*(UPPER(TRIM('PAUSAS MENSUALIDADES'!$D$5:$D$500))="APLICAR"))>0,IF(OR(AND(cobrarDesde<>"",mes<cobrarDesde),pausada),0,MAX(IFNA(VLOOKUP(B57,COSTOS!$A$3:$B$13,2,FALSE),0)-150,0)/1.16)))} -> 689.65517 | D57: {=IF(A57="","",LET(mes,DATE($E$2,MATCH($B$2,'ESTADO CONTABLE'!$A$5:$A$16,0),1),abonos,SUMIFS('ABONOS MENSUALIDADES'!$F$5:$F$500,'ABONOS MENSUALIDADES'!$C$5:$C$500,A57,'ABONOS MENSUALIDADES'!$D$5:$D$500,mes),pago,CHOOSE(MATCH($B$2,'ESTADO CONTABLE'!$A$5:$A$16,0),IFNA(_xlfn.XLOOKUP(A57,PAGOS!$A$2:$A$996,PAGOS!$E$2:$E$996,""),""),IFNA(_xlfn.XLOOKUP(A57,PAGOS!$A$2:$A$996,PAGOS!$G$2:$G$996,""),""),IFNA(_xlfn.XLOOKUP(A57,PAGOS!$A$2:$A$996,PAGOS!$J$2:$J$996,""),""),IFNA(_xlfn.XLOOKUP(A57,PAGOS!$A$2:$A$996,PAGOS!$M$2:$M$996,""),""),IFNA(_xlfn.XLOOKUP(A57,PAGOS!$A$2:$A$996,PAGOS!$P$2:$P$996,""),""),IFNA(_xlfn.XLOOKUP(A57,PAGOS!$A$2:$A$996,PAGOS!$S$2:$S$996,""),""),IFNA(_xlfn.XLOOKUP(A57,PAGOS!$A$2:$A$996,PAGOS!$V$2:$V$996,""),""),IFNA(_xlfn.XLOOKUP(A57,PAGOS!$A$2:$A$996,PAGOS!$Y$2:$Y$996,""),""),IFNA(_xlfn.XLOOKUP(A57,PAGOS!$A$2:$A$996,PAGOS!$AB$2:$AB$996,""),""),IFNA(_xlfn.XLOOKUP(A57,PAGOS!$A$2:$A$996,PAGOS!$AE$2:$AE$996,""),""),IFNA(_xlfn.XLOOKUP(A57,PAGOS!$A$2:$A$996,PAGOS!$AH$2:$AH$996,""),""),IFNA(_xlfn.XLOOKUP(A57,PAGOS!$A$2:$A$996,PAGOS!$AK$2:$AK$996,""),"")),IF(abonos>0,abonos,pago)))} -> 800 | E57: =IFERROR(__xludf.DUMMYFUNCTION("IF(A57="""","""",LET(mes,DATE($E$2,MATCH($B$2,'ESTADO CONTABLE'!$A$5:$A$16,0),1),abonos,SUMIFS('ABONOS MENSUALIDADES'!$F$5:$F$500,'ABONOS MENSUALIDADES'!$C$5:$C$500,A57,'ABONOS MENSUALIDADES'!$D$5:$D$500,mes),metodoDirecto,CHOOSE(MATCH($B$2,'ESTADO CONTAB"&"LE'!$A$5:$A$16,0),IF(ISNUMBER(D57),""POR CLASIFICAR"",""""),IFNA(XLOOKUP(A57,PAGOS!$A$2:$A$996,PAGOS!$H$2:$H$996,""""),""""),IFNA(XLOOKUP(A57,PAGOS!$A$2:$A$996,PAGOS!$K$2:$K$996,""""),""""),IFNA(XLOOKUP(A57,PAGOS!$A$2:$A$996,PAGOS!$N$2:$N$996,""""),""""),"&"IFNA(XLOOKUP(A57,PAGOS!$A$2:$A$996,PAGOS!$Q$2:$Q$996,""""),""""),IFNA(XLOOKUP(A57,PAGOS!$A$2:$A$996,PAGOS!$T$2:$T$996,""""),""""),IFNA(XLOOKUP(A57,PAGOS!$A$2:$A$996,PAGOS!$W$2:$W$996,""""),""""),IFNA(XLOOKUP(A57,PAGOS!$A$2:$A$996,PAGOS!$Z$2:$Z$996,""""),"&"""""),IFNA(XLOOKUP(A57,PAGOS!$A$2:$A$996,PAGOS!$AC$2:$AC$996,""""),""""),IFNA(XLOOKUP(A57,PAGOS!$A$2:$A$996,PAGOS!$AF$2:$AF$996,""""),""""),IFNA(XLOOKUP(A57,PAGOS!$A$2:$A$996,PAGOS!$AI$2:$AI$996,""""),""""),IFNA(XLOOKUP(A57,PAGOS!$A$2:$A$996,PAGOS!$AL$2:$"&"AL$996,""""),"""")),IF(abonos>0,IFERROR(TEXTJOIN("" + "",TRUE,UNIQUE(FILTER('ABONOS MENSUALIDADES'!$E$5:$E$500,'ABONOS MENSUALIDADES'!$C$5:$C$500=A57,'ABONOS MENSUALIDADES'!$D$5:$D$500=mes))),""""),metodoDirecto)))"),"TRANSFERENCIA") -> TRANSFERENCIA | F57: {=IF(A57="","",LET(mes,DATE($E$2,MATCH($B$2,'ESTADO CONTABLE'!$A$5:$A$16,0),1),cobrarDesde,IFERROR(INDEX('BASE DE DATOSS'!I:I,ROW()-13),""),pausada,SUMPRODUCT((UPPER(TRIM('PAUSAS MENSUALIDADES'!$A$5:$A$500))=UPPER(TRIM(A57)))*('PAUSAS MENSUALIDADES'!$B$5:$B$500=mes)*(UPPER(TRIM('PAUSAS MENSUALIDADES'!$D$5:$D$500))="APLICAR"))>0,abonoActivo,SUMIFS('ABONOS MENSUALIDADES'!$F$5:$F$500,'ABONOS MENSUALIDADES'!$C$5:$C$500,A57,'ABONOS MENSUALIDADES'!$D$5:$D$500,mes,'ABONOS MENSUALIDADES'!$G$5:$G$500,"<>*CONSOLIDADO EN PAGOS*")>0,esperadaBruta,MAX(IFNA(VLOOKUP(B57,COSTOS!$A$3:$B$13,2,FALSE),0)-150,0),IF(AND(cobrarDesde<>"",mes<cobrarDesde),"AÚN NO INICIA",IF(pausada,"PAUSADA",IF(AND(abonoActivo,COUNTIFS('ABONOS MENSUALIDADES'!$C$5:$C$500,A57,'ABONOS MENSUALIDADES'!$D$5:$D$500,mes,'ABONOS MENSUALIDADES'!$G$5:$G$500,"*MENSUALIDAD LIQUIDADA*")=0),"ABONO",IF(N(D57)>=esperadaBruta,"COBRADA",IF(N(D57)>0,"ABONO","PENDIENTE")))))))} -> COBRADA | G57: {=IF(A57="","",IFERROR(INDEX('BASE DE DATOSS'!I:I,ROW()-13),""))} -> 46204
A58: {=IFERROR(INDEX('BASE DE DATOSS'!A:A,ROW()-13),"")} -> CAROLINA MAGANA REBOLLEDO | B58: {=IF(A58="","",IFERROR(INDEX('BASE DE DATOSS'!C:C,ROW()-13),""))} -> SABATINO | C58: {=IF(A58="","",LET(mes,DATE($E$2,MATCH($B$2,'ESTADO CONTABLE'!$A$5:$A$16,0),1),cobrarDesde,IFERROR(INDEX('BASE DE DATOSS'!I:I,ROW()-13),""),pausada,SUMPRODUCT((UPPER(TRIM('PAUSAS MENSUALIDADES'!$A$5:$A$500))=UPPER(TRIM(A58)))*('PAUSAS MENSUALIDADES'!$B$5:$B$500=mes)*(UPPER(TRIM('PAUSAS MENSUALIDADES'!$D$5:$D$500))="APLICAR"))>0,IF(OR(AND(cobrarDesde<>"",mes<cobrarDesde),pausada),0,MAX(IFNA(VLOOKUP(B58,COSTOS!$A$3:$B$13,2,FALSE),0)-150,0)/1.16)))} -> 474.13793 | D58: {=IF(A58="","",LET(mes,DATE($E$2,MATCH($B$2,'ESTADO CONTABLE'!$A$5:$A$16,0),1),abonos,SUMIFS('ABONOS MENSUALIDADES'!$F$5:$F$500,'ABONOS MENSUALIDADES'!$C$5:$C$500,A58,'ABONOS MENSUALIDADES'!$D$5:$D$500,mes),pago,CHOOSE(MATCH($B$2,'ESTADO CONTABLE'!$A$5:$A$16,0),IFNA(_xlfn.XLOOKUP(A58,PAGOS!$A$2:$A$996,PAGOS!$E$2:$E$996,""),""),IFNA(_xlfn.XLOOKUP(A58,PAGOS!$A$2:$A$996,PAGOS!$G$2:$G$996,""),""),IFNA(_xlfn.XLOOKUP(A58,PAGOS!$A$2:$A$996,PAGOS!$J$2:$J$996,""),""),IFNA(_xlfn.XLOOKUP(A58,PAGOS!$A$2:$A$996,PAGOS!$M$2:$M$996,""),""),IFNA(_xlfn.XLOOKUP(A58,PAGOS!$A$2:$A$996,PAGOS!$P$2:$P$996,""),""),IFNA(_xlfn.XLOOKUP(A58,PAGOS!$A$2:$A$996,PAGOS!$S$2:$S$996,""),""),IFNA(_xlfn.XLOOKUP(A58,PAGOS!$A$2:$A$996,PAGOS!$V$2:$V$996,""),""),IFNA(_xlfn.XLOOKUP(A58,PAGOS!$A$2:$A$996,PAGOS!$Y$2:$Y$996,""),""),IFNA(_xlfn.XLOOKUP(A58,PAGOS!$A$2:$A$996,PAGOS!$AB$2:$AB$996,""),""),IFNA(_xlfn.XLOOKUP(A58,PAGOS!$A$2:$A$996,PAGOS!$AE$2:$AE$996,""),""),IFNA(_xlfn.XLOOKUP(A58,PAGOS!$A$2:$A$996,PAGOS!$AH$2:$AH$996,""),""),IFNA(_xlfn.XLOOKUP(A58,PAGOS!$A$2:$A$996,PAGOS!$AK$2:$AK$996,""),"")),IF(abonos>0,abonos,pago)))} -> 550 | E58: =IFERROR(__xludf.DUMMYFUNCTION("IF(A58="""","""",LET(mes,DATE($E$2,MATCH($B$2,'ESTADO CONTABLE'!$A$5:$A$16,0),1),abonos,SUMIFS('ABONOS MENSUALIDADES'!$F$5:$F$500,'ABONOS MENSUALIDADES'!$C$5:$C$500,A58,'ABONOS MENSUALIDADES'!$D$5:$D$500,mes),metodoDirecto,CHOOSE(MATCH($B$2,'ESTADO CONTAB"&"LE'!$A$5:$A$16,0),IF(ISNUMBER(D58),""POR CLASIFICAR"",""""),IFNA(XLOOKUP(A58,PAGOS!$A$2:$A$996,PAGOS!$H$2:$H$996,""""),""""),IFNA(XLOOKUP(A58,PAGOS!$A$2:$A$996,PAGOS!$K$2:$K$996,""""),""""),IFNA(XLOOKUP(A58,PAGOS!$A$2:$A$996,PAGOS!$N$2:$N$996,""""),""""),"&"IFNA(XLOOKUP(A58,PAGOS!$A$2:$A$996,PAGOS!$Q$2:$Q$996,""""),""""),IFNA(XLOOKUP(A58,PAGOS!$A$2:$A$996,PAGOS!$T$2:$T$996,""""),""""),IFNA(XLOOKUP(A58,PAGOS!$A$2:$A$996,PAGOS!$W$2:$W$996,""""),""""),IFNA(XLOOKUP(A58,PAGOS!$A$2:$A$996,PAGOS!$Z$2:$Z$996,""""),"&"""""),IFNA(XLOOKUP(A58,PAGOS!$A$2:$A$996,PAGOS!$AC$2:$AC$996,""""),""""),IFNA(XLOOKUP(A58,PAGOS!$A$2:$A$996,PAGOS!$AF$2:$AF$996,""""),""""),IFNA(XLOOKUP(A58,PAGOS!$A$2:$A$996,PAGOS!$AI$2:$AI$996,""""),""""),IFNA(XLOOKUP(A58,PAGOS!$A$2:$A$996,PAGOS!$AL$2:$"&"AL$996,""""),"""")),IF(abonos>0,IFERROR(TEXTJOIN("" + "",TRUE,UNIQUE(FILTER('ABONOS MENSUALIDADES'!$E$5:$E$500,'ABONOS MENSUALIDADES'!$C$5:$C$500=A58,'ABONOS MENSUALIDADES'!$D$5:$D$500=mes))),""""),metodoDirecto)))"),"EFECTIVO") -> EFECTIVO | F58: {=IF(A58="","",LET(mes,DATE($E$2,MATCH($B$2,'ESTADO CONTABLE'!$A$5:$A$16,0),1),cobrarDesde,IFERROR(INDEX('BASE DE DATOSS'!I:I,ROW()-13),""),pausada,SUMPRODUCT((UPPER(TRIM('PAUSAS MENSUALIDADES'!$A$5:$A$500))=UPPER(TRIM(A58)))*('PAUSAS MENSUALIDADES'!$B$5:$B$500=mes)*(UPPER(TRIM('PAUSAS MENSUALIDADES'!$D$5:$D$500))="APLICAR"))>0,abonoActivo,SUMIFS('ABONOS MENSUALIDADES'!$F$5:$F$500,'ABONOS MENSUALIDADES'!$C$5:$C$500,A58,'ABONOS MENSUALIDADES'!$D$5:$D$500,mes,'ABONOS MENSUALIDADES'!$G$5:$G$500,"<>*CONSOLIDADO EN PAGOS*")>0,esperadaBruta,MAX(IFNA(VLOOKUP(B58,COSTOS!$A$3:$B$13,2,FALSE),0)-150,0),IF(AND(cobrarDesde<>"",mes<cobrarDesde),"AÚN NO INICIA",IF(pausada,"PAUSADA",IF(AND(abonoActivo,COUNTIFS('ABONOS MENSUALIDADES'!$C$5:$C$500,A58,'ABONOS MENSUALIDADES'!$D$5:$D$500,mes,'ABONOS MENSUALIDADES'!$G$5:$G$500,"*MENSUALIDAD LIQUIDADA*")=0),"ABONO",IF(N(D58)>=esperadaBruta,"COBRADA",IF(N(D58)>0,"ABONO","PENDIENTE")))))))} -> COBRADA | G58: {=IF(A58="","",IFERROR(INDEX('BASE DE DATOSS'!I:I,ROW()-13),""))} -> 46235
A59: {=IFERROR(INDEX('BASE DE DATOSS'!A:A,ROW()-13),"")} -> LUCIANA ANGEL MACIAS | B59: {=IF(A59="","",IFERROR(INDEX('BASE DE DATOSS'!C:C,ROW()-13),""))} -> KIDS 1 | C59: {=IF(A59="","",LET(mes,DATE($E$2,MATCH($B$2,'ESTADO CONTABLE'!$A$5:$A$16,0),1),cobrarDesde,IFERROR(INDEX('BASE DE DATOSS'!I:I,ROW()-13),""),pausada,SUMPRODUCT((UPPER(TRIM('PAUSAS MENSUALIDADES'!$A$5:$A$500))=UPPER(TRIM(A59)))*('PAUSAS MENSUALIDADES'!$B$5:$B$500=mes)*(UPPER(TRIM('PAUSAS MENSUALIDADES'!$D$5:$D$500))="APLICAR"))>0,IF(OR(AND(cobrarDesde<>"",mes<cobrarDesde),pausada),0,MAX(IFNA(VLOOKUP(B59,COSTOS!$A$3:$B$13,2,FALSE),0)-150,0)/1.16)))} -> 818.96552 | D59: {=IF(A59="","",LET(mes,DATE($E$2,MATCH($B$2,'ESTADO CONTABLE'!$A$5:$A$16,0),1),abonos,SUMIFS('ABONOS MENSUALIDADES'!$F$5:$F$500,'ABONOS MENSUALIDADES'!$C$5:$C$500,A59,'ABONOS MENSUALIDADES'!$D$5:$D$500,mes),pago,CHOOSE(MATCH($B$2,'ESTADO CONTABLE'!$A$5:$A$16,0),IFNA(_xlfn.XLOOKUP(A59,PAGOS!$A$2:$A$996,PAGOS!$E$2:$E$996,""),""),IFNA(_xlfn.XLOOKUP(A59,PAGOS!$A$2:$A$996,PAGOS!$G$2:$G$996,""),""),IFNA(_xlfn.XLOOKUP(A59,PAGOS!$A$2:$A$996,PAGOS!$J$2:$J$996,""),""),IFNA(_xlfn.XLOOKUP(A59,PAGOS!$A$2:$A$996,PAGOS!$M$2:$M$996,""),""),IFNA(_xlfn.XLOOKUP(A59,PAGOS!$A$2:$A$996,PAGOS!$P$2:$P$996,""),""),IFNA(_xlfn.XLOOKUP(A59,PAGOS!$A$2:$A$996,PAGOS!$S$2:$S$996,""),""),IFNA(_xlfn.XLOOKUP(A59,PAGOS!$A$2:$A$996,PAGOS!$V$2:$V$996,""),""),IFNA(_xlfn.XLOOKUP(A59,PAGOS!$A$2:$A$996,PAGOS!$Y$2:$Y$996,""),""),IFNA(_xlfn.XLOOKUP(A59,PAGOS!$A$2:$A$996,PAGOS!$AB$2:$AB$996,""),""),IFNA(_xlfn.XLOOKUP(A59,PAGOS!$A$2:$A$996,PAGOS!$AE$2:$AE$996,""),""),IFNA(_xlfn.XLOOKUP(A59,PAGOS!$A$2:$A$996,PAGOS!$AH$2:$AH$996,""),""),IFNA(_xlfn.XLOOKUP(A59,PAGOS!$A$2:$A$996,PAGOS!$AK$2:$AK$996,""),"")),IF(abonos>0,abonos,pago)))} -> 1100 | E59: =IFERROR(__xludf.DUMMYFUNCTION("IF(A59="""","""",LET(mes,DATE($E$2,MATCH($B$2,'ESTADO CONTABLE'!$A$5:$A$16,0),1),abonos,SUMIFS('ABONOS MENSUALIDADES'!$F$5:$F$500,'ABONOS MENSUALIDADES'!$C$5:$C$500,A59,'ABONOS MENSUALIDADES'!$D$5:$D$500,mes),metodoDirecto,CHOOSE(MATCH($B$2,'ESTADO CONTAB"&"LE'!$A$5:$A$16,0),IF(ISNUMBER(D59),""POR CLASIFICAR"",""""),IFNA(XLOOKUP(A59,PAGOS!$A$2:$A$996,PAGOS!$H$2:$H$996,""""),""""),IFNA(XLOOKUP(A59,PAGOS!$A$2:$A$996,PAGOS!$K$2:$K$996,""""),""""),IFNA(XLOOKUP(A59,PAGOS!$A$2:$A$996,PAGOS!$N$2:$N$996,""""),""""),"&"IFNA(XLOOKUP(A59,PAGOS!$A$2:$A$996,PAGOS!$Q$2:$Q$996,""""),""""),IFNA(XLOOKUP(A59,PAGOS!$A$2:$A$996,PAGOS!$T$2:$T$996,""""),""""),IFNA(XLOOKUP(A59,PAGOS!$A$2:$A$996,PAGOS!$W$2:$W$996,""""),""""),IFNA(XLOOKUP(A59,PAGOS!$A$2:$A$996,PAGOS!$Z$2:$Z$996,""""),"&"""""),IFNA(XLOOKUP(A59,PAGOS!$A$2:$A$996,PAGOS!$AC$2:$AC$996,""""),""""),IFNA(XLOOKUP(A59,PAGOS!$A$2:$A$996,PAGOS!$AF$2:$AF$996,""""),""""),IFNA(XLOOKUP(A59,PAGOS!$A$2:$A$996,PAGOS!$AI$2:$AI$996,""""),""""),IFNA(XLOOKUP(A59,PAGOS!$A$2:$A$996,PAGOS!$AL$2:$"&"AL$996,""""),"""")),IF(abonos>0,IFERROR(TEXTJOIN("" + "",TRUE,UNIQUE(FILTER('ABONOS MENSUALIDADES'!$E$5:$E$500,'ABONOS MENSUALIDADES'!$C$5:$C$500=A59,'ABONOS MENSUALIDADES'!$D$5:$D$500=mes))),""""),metodoDirecto)))"),"EFECTIVO") -> EFECTIVO | F59: {=IF(A59="","",LET(mes,DATE($E$2,MATCH($B$2,'ESTADO CONTABLE'!$A$5:$A$16,0),1),cobrarDesde,IFERROR(INDEX('BASE DE DATOSS'!I:I,ROW()-13),""),pausada,SUMPRODUCT((UPPER(TRIM('PAUSAS MENSUALIDADES'!$A$5:$A$500))=UPPER(TRIM(A59)))*('PAUSAS MENSUALIDADES'!$B$5:$B$500=mes)*(UPPER(TRIM('PAUSAS MENSUALIDADES'!$D$5:$D$500))="APLICAR"))>0,abonoActivo,SUMIFS('ABONOS MENSUALIDADES'!$F$5:$F$500,'ABONOS MENSUALIDADES'!$C$5:$C$500,A59,'ABONOS MENSUALIDADES'!$D$5:$D$500,mes,'ABONOS MENSUALIDADES'!$G$5:$G$500,"<>*CONSOLIDADO EN PAGOS*")>0,esperadaBruta,MAX(IFNA(VLOOKUP(B59,COSTOS!$A$3:$B$13,2,FALSE),0)-150,0),IF(AND(cobrarDesde<>"",mes<cobrarDesde),"AÚN NO INICIA",IF(pausada,"PAUSADA",IF(AND(abonoActivo,COUNTIFS('ABONOS MENSUALIDADES'!$C$5:$C$500,A59,'ABONOS MENSUALIDADES'!$D$5:$D$500,mes,'ABONOS MENSUALIDADES'!$G$5:$G$500,"*MENSUALIDAD LIQUIDADA*")=0),"ABONO",IF(N(D59)>=esperadaBruta,"COBRADA",IF(N(D59)>0,"ABONO","PENDIENTE")))))))} -> COBRADA | G59: {=IF(A59="","",IFERROR(INDEX('BASE DE DATOSS'!I:I,ROW()-13),""))} -> 46235
A60: {=IFERROR(INDEX('BASE DE DATOSS'!A:A,ROW()-13),"")} -> AITANA PADILLA VARGAS | B60: {=IF(A60="","",IFERROR(INDEX('BASE DE DATOSS'!C:C,ROW()-13),""))} -> JR 1 | C60: {=IF(A60="","",LET(mes,DATE($E$2,MATCH($B$2,'ESTADO CONTABLE'!$A$5:$A$16,0),1),cobrarDesde,IFERROR(INDEX('BASE DE DATOSS'!I:I,ROW()-13),""),pausada,SUMPRODUCT((UPPER(TRIM('PAUSAS MENSUALIDADES'!$A$5:$A$500))=UPPER(TRIM(A60)))*('PAUSAS MENSUALIDADES'!$B$5:$B$500=mes)*(UPPER(TRIM('PAUSAS MENSUALIDADES'!$D$5:$D$500))="APLICAR"))>0,IF(OR(AND(cobrarDesde<>"",mes<cobrarDesde),pausada),0,MAX(IFNA(VLOOKUP(B60,COSTOS!$A$3:$B$13,2,FALSE),0)-150,0)/1.16)))} -> 818.96552 | D60: {=IF(A60="","",LET(mes,DATE($E$2,MATCH($B$2,'ESTADO CONTABLE'!$A$5:$A$16,0),1),abonos,SUMIFS('ABONOS MENSUALIDADES'!$F$5:$F$500,'ABONOS MENSUALIDADES'!$C$5:$C$500,A60,'ABONOS MENSUALIDADES'!$D$5:$D$500,mes),pago,CHOOSE(MATCH($B$2,'ESTADO CONTABLE'!$A$5:$A$16,0),IFNA(_xlfn.XLOOKUP(A60,PAGOS!$A$2:$A$996,PAGOS!$E$2:$E$996,""),""),IFNA(_xlfn.XLOOKUP(A60,PAGOS!$A$2:$A$996,PAGOS!$G$2:$G$996,""),""),IFNA(_xlfn.XLOOKUP(A60,PAGOS!$A$2:$A$996,PAGOS!$J$2:$J$996,""),""),IFNA(_xlfn.XLOOKUP(A60,PAGOS!$A$2:$A$996,PAGOS!$M$2:$M$996,""),""),IFNA(_xlfn.XLOOKUP(A60,PAGOS!$A$2:$A$996,PAGOS!$P$2:$P$996,""),""),IFNA(_xlfn.XLOOKUP(A60,PAGOS!$A$2:$A$996,PAGOS!$S$2:$S$996,""),""),IFNA(_xlfn.XLOOKUP(A60,PAGOS!$A$2:$A$996,PAGOS!$V$2:$V$996,""),""),IFNA(_xlfn.XLOOKUP(A60,PAGOS!$A$2:$A$996,PAGOS!$Y$2:$Y$996,""),""),IFNA(_xlfn.XLOOKUP(A60,PAGOS!$A$2:$A$996,PAGOS!$AB$2:$AB$996,""),""),IFNA(_xlfn.XLOOKUP(A60,PAGOS!$A$2:$A$996,PAGOS!$AE$2:$AE$996,""),""),IFNA(_xlfn.XLOOKUP(A60,PAGOS!$A$2:$A$996,PAGOS!$AH$2:$AH$996,""),""),IFNA(_xlfn.XLOOKUP(A60,PAGOS!$A$2:$A$996,PAGOS!$AK$2:$AK$996,""),"")),IF(abonos>0,abonos,pago)))} -> 950 | E60: =IFERROR(__xludf.DUMMYFUNCTION("IF(A60="""","""",LET(mes,DATE($E$2,MATCH($B$2,'ESTADO CONTABLE'!$A$5:$A$16,0),1),abonos,SUMIFS('ABONOS MENSUALIDADES'!$F$5:$F$500,'ABONOS MENSUALIDADES'!$C$5:$C$500,A60,'ABONOS MENSUALIDADES'!$D$5:$D$500,mes),metodoDirecto,CHOOSE(MATCH($B$2,'ESTADO CONTAB"&"LE'!$A$5:$A$16,0),IF(ISNUMBER(D60),""POR CLASIFICAR"",""""),IFNA(XLOOKUP(A60,PAGOS!$A$2:$A$996,PAGOS!$H$2:$H$996,""""),""""),IFNA(XLOOKUP(A60,PAGOS!$A$2:$A$996,PAGOS!$K$2:$K$996,""""),""""),IFNA(XLOOKUP(A60,PAGOS!$A$2:$A$996,PAGOS!$N$2:$N$996,""""),""""),"&"IFNA(XLOOKUP(A60,PAGOS!$A$2:$A$996,PAGOS!$Q$2:$Q$996,""""),""""),IFNA(XLOOKUP(A60,PAGOS!$A$2:$A$996,PAGOS!$T$2:$T$996,""""),""""),IFNA(XLOOKUP(A60,PAGOS!$A$2:$A$996,PAGOS!$W$2:$W$996,""""),""""),IFNA(XLOOKUP(A60,PAGOS!$A$2:$A$996,PAGOS!$Z$2:$Z$996,""""),"&"""""),IFNA(XLOOKUP(A60,PAGOS!$A$2:$A$996,PAGOS!$AC$2:$AC$996,""""),""""),IFNA(XLOOKUP(A60,PAGOS!$A$2:$A$996,PAGOS!$AF$2:$AF$996,""""),""""),IFNA(XLOOKUP(A60,PAGOS!$A$2:$A$996,PAGOS!$AI$2:$AI$996,""""),""""),IFNA(XLOOKUP(A60,PAGOS!$A$2:$A$996,PAGOS!$AL$2:$"&"AL$996,""""),"""")),IF(abonos>0,IFERROR(TEXTJOIN("" + "",TRUE,UNIQUE(FILTER('ABONOS MENSUALIDADES'!$E$5:$E$500,'ABONOS MENSUALIDADES'!$C$5:$C$500=A60,'ABONOS MENSUALIDADES'!$D$5:$D$500=mes))),""""),metodoDirecto)))"),"TRANSFERENCIA") -> TRANSFERENCIA | F60: {=IF(A60="","",LET(mes,DATE($E$2,MATCH($B$2,'ESTADO CONTABLE'!$A$5:$A$16,0),1),cobrarDesde,IFERROR(INDEX('BASE DE DATOSS'!I:I,ROW()-13),""),pausada,SUMPRODUCT((UPPER(TRIM('PAUSAS MENSUALIDADES'!$A$5:$A$500))=UPPER(TRIM(A60)))*('PAUSAS MENSUALIDADES'!$B$5:$B$500=mes)*(UPPER(TRIM('PAUSAS MENSUALIDADES'!$D$5:$D$500))="APLICAR"))>0,abonoActivo,SUMIFS('ABONOS MENSUALIDADES'!$F$5:$F$500,'ABONOS MENSUALIDADES'!$C$5:$C$500,A60,'ABONOS MENSUALIDADES'!$D$5:$D$500,mes,'ABONOS MENSUALIDADES'!$G$5:$G$500,"<>*CONSOLIDADO EN PAGOS*")>0,esperadaBruta,MAX(IFNA(VLOOKUP(B60,COSTOS!$A$3:$B$13,2,FALSE),0)-150,0),IF(AND(cobrarDesde<>"",mes<cobrarDesde),"AÚN NO INICIA",IF(pausada,"PAUSADA",IF(AND(abonoActivo,COUNTIFS('ABONOS MENSUALIDADES'!$C$5:$C$500,A60,'ABONOS MENSUALIDADES'!$D$5:$D$500,mes,'ABONOS MENSUALIDADES'!$G$5:$G$500,"*MENSUALIDAD LIQUIDADA*")=0),"ABONO",IF(N(D60)>=esperadaBruta,"COBRADA",IF(N(D60)>0,"ABONO","PENDIENTE")))))))} -> COBRADA | G60: {=IF(A60="","",IFERROR(INDEX('BASE DE DATOSS'!I:I,ROW()-13),""))} -> 46235
A61: {=IFERROR(INDEX('BASE DE DATOSS'!A:A,ROW()-13),"")} -> Sophie Dannae Estrada Solorzano | B61: {=IF(A61="","",IFERROR(INDEX('BASE DE DATOSS'!C:C,ROW()-13),""))} -> JR 1 | C61: {=IF(A61="","",LET(mes,DATE($E$2,MATCH($B$2,'ESTADO CONTABLE'!$A$5:$A$16,0),1),cobrarDesde,IFERROR(INDEX('BASE DE DATOSS'!I:I,ROW()-13),""),pausada,SUMPRODUCT((UPPER(TRIM('PAUSAS MENSUALIDADES'!$A$5:$A$500))=UPPER(TRIM(A61)))*('PAUSAS MENSUALIDADES'!$B$5:$B$500=mes)*(UPPER(TRIM('PAUSAS MENSUALIDADES'!$D$5:$D$500))="APLICAR"))>0,IF(OR(AND(cobrarDesde<>"",mes<cobrarDesde),pausada),0,MAX(IFNA(VLOOKUP(B61,COSTOS!$A$3:$B$13,2,FALSE),0)-150,0)/1.16)))} -> 818.96552 | D61: {=IF(A61="","",LET(mes,DATE($E$2,MATCH($B$2,'ESTADO CONTABLE'!$A$5:$A$16,0),1),abonos,SUMIFS('ABONOS MENSUALIDADES'!$F$5:$F$500,'ABONOS MENSUALIDADES'!$C$5:$C$500,A61,'ABONOS MENSUALIDADES'!$D$5:$D$500,mes),pago,CHOOSE(MATCH($B$2,'ESTADO CONTABLE'!$A$5:$A$16,0),IFNA(_xlfn.XLOOKUP(A61,PAGOS!$A$2:$A$996,PAGOS!$E$2:$E$996,""),""),IFNA(_xlfn.XLOOKUP(A61,PAGOS!$A$2:$A$996,PAGOS!$G$2:$G$996,""),""),IFNA(_xlfn.XLOOKUP(A61,PAGOS!$A$2:$A$996,PAGOS!$J$2:$J$996,""),""),IFNA(_xlfn.XLOOKUP(A61,PAGOS!$A$2:$A$996,PAGOS!$M$2:$M$996,""),""),IFNA(_xlfn.XLOOKUP(A61,PAGOS!$A$2:$A$996,PAGOS!$P$2:$P$996,""),""),IFNA(_xlfn.XLOOKUP(A61,PAGOS!$A$2:$A$996,PAGOS!$S$2:$S$996,""),""),IFNA(_xlfn.XLOOKUP(A61,PAGOS!$A$2:$A$996,PAGOS!$V$2:$V$996,""),""),IFNA(_xlfn.XLOOKUP(A61,PAGOS!$A$2:$A$996,PAGOS!$Y$2:$Y$996,""),""),IFNA(_xlfn.XLOOKUP(A61,PAGOS!$A$2:$A$996,PAGOS!$AB$2:$AB$996,""),""),IFNA(_xlfn.XLOOKUP(A61,PAGOS!$A$2:$A$996,PAGOS!$AE$2:$AE$996,""),""),IFNA(_xlfn.XLOOKUP(A61,PAGOS!$A$2:$A$996,PAGOS!$AH$2:$AH$996,""),""),IFNA(_xlfn.XLOOKUP(A61,PAGOS!$A$2:$A$996,PAGOS!$AK$2:$AK$996,""),"")),IF(abonos>0,abonos,pago)))} -> 950 | E61: =IFERROR(__xludf.DUMMYFUNCTION("IF(A61="""","""",LET(mes,DATE($E$2,MATCH($B$2,'ESTADO CONTABLE'!$A$5:$A$16,0),1),abonos,SUMIFS('ABONOS MENSUALIDADES'!$F$5:$F$500,'ABONOS MENSUALIDADES'!$C$5:$C$500,A61,'ABONOS MENSUALIDADES'!$D$5:$D$500,mes),metodoDirecto,CHOOSE(MATCH($B$2,'ESTADO CONTAB"&"LE'!$A$5:$A$16,0),IF(ISNUMBER(D61),""POR CLASIFICAR"",""""),IFNA(XLOOKUP(A61,PAGOS!$A$2:$A$996,PAGOS!$H$2:$H$996,""""),""""),IFNA(XLOOKUP(A61,PAGOS!$A$2:$A$996,PAGOS!$K$2:$K$996,""""),""""),IFNA(XLOOKUP(A61,PAGOS!$A$2:$A$996,PAGOS!$N$2:$N$996,""""),""""),"&"IFNA(XLOOKUP(A61,PAGOS!$A$2:$A$996,PAGOS!$Q$2:$Q$996,""""),""""),IFNA(XLOOKUP(A61,PAGOS!$A$2:$A$996,PAGOS!$T$2:$T$996,""""),""""),IFNA(XLOOKUP(A61,PAGOS!$A$2:$A$996,PAGOS!$W$2:$W$996,""""),""""),IFNA(XLOOKUP(A61,PAGOS!$A$2:$A$996,PAGOS!$Z$2:$Z$996,""""),"&"""""),IFNA(XLOOKUP(A61,PAGOS!$A$2:$A$996,PAGOS!$AC$2:$AC$996,""""),""""),IFNA(XLOOKUP(A61,PAGOS!$A$2:$A$996,PAGOS!$AF$2:$AF$996,""""),""""),IFNA(XLOOKUP(A61,PAGOS!$A$2:$A$996,PAGOS!$AI$2:$AI$996,""""),""""),IFNA(XLOOKUP(A61,PAGOS!$A$2:$A$996,PAGOS!$AL$2:$"&"AL$996,""""),"""")),IF(abonos>0,IFERROR(TEXTJOIN("" + "",TRUE,UNIQUE(FILTER('ABONOS MENSUALIDADES'!$E$5:$E$500,'ABONOS MENSUALIDADES'!$C$5:$C$500=A61,'ABONOS MENSUALIDADES'!$D$5:$D$500=mes))),""""),metodoDirecto)))"),"TRANSFERENCIA") -> TRANSFERENCIA | F61: {=IF(A61="","",LET(mes,DATE($E$2,MATCH($B$2,'ESTADO CONTABLE'!$A$5:$A$16,0),1),cobrarDesde,IFERROR(INDEX('BASE DE DATOSS'!I:I,ROW()-13),""),pausada,SUMPRODUCT((UPPER(TRIM('PAUSAS MENSUALIDADES'!$A$5:$A$500))=UPPER(TRIM(A61)))*('PAUSAS MENSUALIDADES'!$B$5:$B$500=mes)*(UPPER(TRIM('PAUSAS MENSUALIDADES'!$D$5:$D$500))="APLICAR"))>0,abonoActivo,SUMIFS('ABONOS MENSUALIDADES'!$F$5:$F$500,'ABONOS MENSUALIDADES'!$C$5:$C$500,A61,'ABONOS MENSUALIDADES'!$D$5:$D$500,mes,'ABONOS MENSUALIDADES'!$G$5:$G$500,"<>*CONSOLIDADO EN PAGOS*")>0,esperadaBruta,MAX(IFNA(VLOOKUP(B61,COSTOS!$A$3:$B$13,2,FALSE),0)-150,0),IF(AND(cobrarDesde<>"",mes<cobrarDesde),"AÚN NO INICIA",IF(pausada,"PAUSADA",IF(AND(abonoActivo,COUNTIFS('ABONOS MENSUALIDADES'!$C$5:$C$500,A61,'ABONOS MENSUALIDADES'!$D$5:$D$500,mes,'ABONOS MENSUALIDADES'!$G$5:$G$500,"*MENSUALIDAD LIQUIDADA*")=0),"ABONO",IF(N(D61)>=esperadaBruta,"COBRADA",IF(N(D61)>0,"ABONO","PENDIENTE")))))))} -> COBRADA | G61: {=IF(A61="","",IFERROR(INDEX('BASE DE DATOSS'!I:I,ROW()-13),""))} -> 46235
A62: {=IFERROR(INDEX('BASE DE DATOSS'!A:A,ROW()-13),"")} -> ITZIA AQUETZALLI CERVANTES OLIVO | B62: {=IF(A62="","",IFERROR(INDEX('BASE DE DATOSS'!C:C,ROW()-13),""))} -> KIDS 1 | C62: {=IF(A62="","",LET(mes,DATE($E$2,MATCH($B$2,'ESTADO CONTABLE'!$A$5:$A$16,0),1),cobrarDesde,IFERROR(INDEX('BASE DE DATOSS'!I:I,ROW()-13),""),pausada,SUMPRODUCT((UPPER(TRIM('PAUSAS MENSUALIDADES'!$A$5:$A$500))=UPPER(TRIM(A62)))*('PAUSAS MENSUALIDADES'!$B$5:$B$500=mes)*(UPPER(TRIM('PAUSAS MENSUALIDADES'!$D$5:$D$500))="APLICAR"))>0,IF(OR(AND(cobrarDesde<>"",mes<cobrarDesde),pausada),0,MAX(IFNA(VLOOKUP(B62,COSTOS!$A$3:$B$13,2,FALSE),0)-150,0)/1.16)))} -> 818.96552 | D62: {=IF(A62="","",LET(mes,DATE($E$2,MATCH($B$2,'ESTADO CONTABLE'!$A$5:$A$16,0),1),abonos,SUMIFS('ABONOS MENSUALIDADES'!$F$5:$F$500,'ABONOS MENSUALIDADES'!$C$5:$C$500,A62,'ABONOS MENSUALIDADES'!$D$5:$D$500,mes),pago,CHOOSE(MATCH($B$2,'ESTADO CONTABLE'!$A$5:$A$16,0),IFNA(_xlfn.XLOOKUP(A62,PAGOS!$A$2:$A$996,PAGOS!$E$2:$E$996,""),""),IFNA(_xlfn.XLOOKUP(A62,PAGOS!$A$2:$A$996,PAGOS!$G$2:$G$996,""),""),IFNA(_xlfn.XLOOKUP(A62,PAGOS!$A$2:$A$996,PAGOS!$J$2:$J$996,""),""),IFNA(_xlfn.XLOOKUP(A62,PAGOS!$A$2:$A$996,PAGOS!$M$2:$M$996,""),""),IFNA(_xlfn.XLOOKUP(A62,PAGOS!$A$2:$A$996,PAGOS!$P$2:$P$996,""),""),IFNA(_xlfn.XLOOKUP(A62,PAGOS!$A$2:$A$996,PAGOS!$S$2:$S$996,""),""),IFNA(_xlfn.XLOOKUP(A62,PAGOS!$A$2:$A$996,PAGOS!$V$2:$V$996,""),""),IFNA(_xlfn.XLOOKUP(A62,PAGOS!$A$2:$A$996,PAGOS!$Y$2:$Y$996,""),""),IFNA(_xlfn.XLOOKUP(A62,PAGOS!$A$2:$A$996,PAGOS!$AB$2:$AB$996,""),""),IFNA(_xlfn.XLOOKUP(A62,PAGOS!$A$2:$A$996,PAGOS!$AE$2:$AE$996,""),""),IFNA(_xlfn.XLOOKUP(A62,PAGOS!$A$2:$A$996,PAGOS!$AH$2:$AH$996,""),""),IFNA(_xlfn.XLOOKUP(A62,PAGOS!$A$2:$A$996,PAGOS!$AK$2:$AK$996,""),"")),IF(abonos>0,abonos,pago)))} -> 950 | E62: =IFERROR(__xludf.DUMMYFUNCTION("IF(A62="""","""",LET(mes,DATE($E$2,MATCH($B$2,'ESTADO CONTABLE'!$A$5:$A$16,0),1),abonos,SUMIFS('ABONOS MENSUALIDADES'!$F$5:$F$500,'ABONOS MENSUALIDADES'!$C$5:$C$500,A62,'ABONOS MENSUALIDADES'!$D$5:$D$500,mes),metodoDirecto,CHOOSE(MATCH($B$2,'ESTADO CONTAB"&"LE'!$A$5:$A$16,0),IF(ISNUMBER(D62),""POR CLASIFICAR"",""""),IFNA(XLOOKUP(A62,PAGOS!$A$2:$A$996,PAGOS!$H$2:$H$996,""""),""""),IFNA(XLOOKUP(A62,PAGOS!$A$2:$A$996,PAGOS!$K$2:$K$996,""""),""""),IFNA(XLOOKUP(A62,PAGOS!$A$2:$A$996,PAGOS!$N$2:$N$996,""""),""""),"&"IFNA(XLOOKUP(A62,PAGOS!$A$2:$A$996,PAGOS!$Q$2:$Q$996,""""),""""),IFNA(XLOOKUP(A62,PAGOS!$A$2:$A$996,PAGOS!$T$2:$T$996,""""),""""),IFNA(XLOOKUP(A62,PAGOS!$A$2:$A$996,PAGOS!$W$2:$W$996,""""),""""),IFNA(XLOOKUP(A62,PAGOS!$A$2:$A$996,PAGOS!$Z$2:$Z$996,""""),"&"""""),IFNA(XLOOKUP(A62,PAGOS!$A$2:$A$996,PAGOS!$AC$2:$AC$996,""""),""""),IFNA(XLOOKUP(A62,PAGOS!$A$2:$A$996,PAGOS!$AF$2:$AF$996,""""),""""),IFNA(XLOOKUP(A62,PAGOS!$A$2:$A$996,PAGOS!$AI$2:$AI$996,""""),""""),IFNA(XLOOKUP(A62,PAGOS!$A$2:$A$996,PAGOS!$AL$2:$"&"AL$996,""""),"""")),IF(abonos>0,IFERROR(TEXTJOIN("" + "",TRUE,UNIQUE(FILTER('ABONOS MENSUALIDADES'!$E$5:$E$500,'ABONOS MENSUALIDADES'!$C$5:$C$500=A62,'ABONOS MENSUALIDADES'!$D$5:$D$500=mes))),""""),metodoDirecto)))"),"TRANSFERENCIA") -> TRANSFERENCIA | F62: {=IF(A62="","",LET(mes,DATE($E$2,MATCH($B$2,'ESTADO CONTABLE'!$A$5:$A$16,0),1),cobrarDesde,IFERROR(INDEX('BASE DE DATOSS'!I:I,ROW()-13),""),pausada,SUMPRODUCT((UPPER(TRIM('PAUSAS MENSUALIDADES'!$A$5:$A$500))=UPPER(TRIM(A62)))*('PAUSAS MENSUALIDADES'!$B$5:$B$500=mes)*(UPPER(TRIM('PAUSAS MENSUALIDADES'!$D$5:$D$500))="APLICAR"))>0,abonoActivo,SUMIFS('ABONOS MENSUALIDADES'!$F$5:$F$500,'ABONOS MENSUALIDADES'!$C$5:$C$500,A62,'ABONOS MENSUALIDADES'!$D$5:$D$500,mes,'ABONOS MENSUALIDADES'!$G$5:$G$500,"<>*CONSOLIDADO EN PAGOS*")>0,esperadaBruta,MAX(IFNA(VLOOKUP(B62,COSTOS!$A$3:$B$13,2,FALSE),0)-150,0),IF(AND(cobrarDesde<>"",mes<cobrarDesde),"AÚN NO INICIA",IF(pausada,"PAUSADA",IF(AND(abonoActivo,COUNTIFS('ABONOS MENSUALIDADES'!$C$5:$C$500,A62,'ABONOS MENSUALIDADES'!$D$5:$D$500,mes,'ABONOS MENSUALIDADES'!$G$5:$G$500,"*MENSUALIDAD LIQUIDADA*")=0),"ABONO",IF(N(D62)>=esperadaBruta,"COBRADA",IF(N(D62)>0,"ABONO","PENDIENTE")))))))} -> COBRADA | G62: {=IF(A62="","",IFERROR(INDEX('BASE DE DATOSS'!I:I,ROW()-13),""))} -> 46235
